[
  {
    "review": "Продавец-консультант\n...\nРаботал меньше года Москва, сентябрь 2025\n1,5\nЧто нравится?\nКорпоративные скидки , обучение\nФорма, не плохой магазин в плане ремонта интерьера\nЧто можно улучшить?\nРуководство !!! Проведите им дополнительное обучение , проверяйте на компетентность!! Нет поддержки сотрудников которые стараются максимально на результат!\nРасширяйте ассортимент !\nОтвет представителя компании\nОктябрь 2025\nЗдравствуйте.\nСпасибо, что вы нашли время и поделились вашими впечатлениями.\nПриятно, что вы оценили интерьер магазина и отметили скидки и обучение для сотрудников.\nЗамечание о расширении ассортимента мы приняли во внимание.\nКроме того, мы бы хотели подробнее разобраться в вашей ситуации с руководством. Пожалуйста, напишите нам письмо на адрес: ru_hr_feedback@ecco.com. Спасибо!\nПреимущества и льготы\nСвоевременная оплата труда\nУдобное расположение работы\nПолезный отзыв\n 0\nСсылка на отзыв",
    "review__header-title": "Продавец-консультант",
    "share-block__item": "...",
    "tags__item": "Работал меньше года",
    "tags__item (2)": "Москва, сентябрь 2025",
    "dj-rating": "1,5",
    "review__title": "Что нравится?",
    "review__title (2)": "Что можно улучшить?",
    "review__answer": "Ответ представителя компании\nОктябрь 2025\nЗдравствуйте.\nСпасибо, что вы нашли время и поделились вашими впечатлениями.\nПриятно, что вы оценили интерьер магазина и отметили скидки и обучение для сотрудников.\nЗамечание о расширении ассортимента мы приняли во внимание.\nКроме того, мы бы хотели подробнее разобраться в вашей ситуации с руководством. Пожалуйста, напишите нам письмо на адрес: ru_hr_feedback@ecco.com. Спасибо!",
    "review__answer-title": "Ответ представителя компании",
    "review__answer-date": "Октябрь 2025",
    "review__title-privileges": "Преимущества и льготы",
    "tags__item (3)": "Своевременная оплата труда",
    "tags__item (4)": "Удобное расположение работы",
    "bt": "Полезный отзыв\n 0",
    "review__useful": "Полезный отзыв",
    "bt href": "https://dreamjob.ru/employers/25646?review_id=4071643",
    "bt (2)": "Ссылка на отзыв"
  },
  {
    "vacancies-banner__inner": "Вакансии в ECCO",
    "vacancies-banner__all href": "https://dreamjob.ru/employers/25646/vakansii",
    "vacancies-banner__all": "Все\n 74",
    "d-md-block": "Все",
    "vacancies-banner__head": "Продавец-консультант ECCO (МЕГА Парнас)",
    "vacancies-banner__сity": "Санкт-Петербург",
    "vacancies-banner__salary": "50 000 - 80 000 ₽",
    "job-vacancy__currency": "₽",
    "bt-master href": "https://dreamjob.ru/employers/25646/vakansii/126889064",
    "bt-master": "Посмотреть вакансию",
    "vacancies-banner__head (2)": "Продавец-консультант ECCO (ТЦ OZ МОЛЛ)",
    "vacancies-banner__сity (2)": "Краснодар",
    "vacancies-banner__salary (2)": "40 000 - 55 000 ₽",
    "bt-master href (2)": "https://dreamjob.ru/employers/25646/vakansii/126887530",
    "vacancies-banner__head (3)": "Директор магазина ECCO (Avenue Southwest)",
    "vacancies-banner__сity (3)": "Москва",
    "vacancies-banner__salary (3)": "90 000 - 130 000 ₽",
    "bt-master href (3)": "https://dreamjob.ru/employers/25646/vakansii/126887448",
    "vacancies-banner__head (4)": "Продавец-консультант ECCO (ТЦ Аура)",
    "vacancies-banner__сity (4)": "Новосибирск",
    "vacancies-banner__salary (4)": "от 60 000 ₽",
    "bt-master href (4)": "https://dreamjob.ru/employers/25646/vakansii/126045336",
    "vacancies-banner__head (5)": "Продавец-консультант ECCO ( ТЦ Бутово Молл)",
    "vacancies-banner__salary (5)": "60 000 - 80 000 ₽",
    "bt-master href (5)": "https://dreamjob.ru/employers/25646/vakansii/126110366"
  },
  {
    "review": "Продавец-консультант\n...\nРаботал 3-5 лет Москва, сентябрь 2025\n1,2\nЧто нравится?\nмне нравится в работодателе что он искренне обманывает сотрудников розницы и кормит свиней офиса а лишь сотрудники розницы и приносят хлеб этим свиньям\nЧто можно улучшить?\nулучшить ничего не получится как там работают долговые сотрудники оказаышиес в сложной жизненной ситуации поэтому офисные крысы этим максимально пытаются пользоваться\nОтвет представителя компании\nСентябрь 2025\nЗдравствуйте.\nЦеним вашу честность и открытость, но сожалеем, что впечатление оказалось негативным. Мы обеспокоены, что ситуация задевает вас лично, и хотели бы подробнее ее обсудить. Пожалуйста, напишите нам письмо на адрес: ru_hr_feedback@ecco.com. Спасибо!\nПолезный отзыв\n 2\nСсылка на отзыв",
    "review__header-title": "Продавец-консультант",
    "share-block__item": "...",
    "tags__item": "Работал 3-5 лет",
    "tags__item (2)": "Москва, сентябрь 2025",
    "dj-rating": "1,2",
    "review__title": "Что нравится?",
    "review__title (2)": "Что можно улучшить?",
    "review__answer": "Ответ представителя компании\nСентябрь 2025\nЗдравствуйте.\nЦеним вашу честность и открытость, но сожалеем, что впечатление оказалось негативным. Мы обеспокоены, что ситуация задевает вас лично, и хотели бы подробнее ее обсудить. Пожалуйста, напишите нам письмо на адрес: ru_hr_feedback@ecco.com. Спасибо!",
    "review__answer-title": "Ответ представителя компании",
    "review__answer-date": "Сентябрь 2025",
    "bt": "Полезный отзыв\n 2",
    "review__useful": "Полезный отзыв",
    "bt href": "https://dreamjob.ru/employers/25646?review_id=4056697",
    "bt (2)": "Ссылка на отзыв"
  },
  {
    "swiper-slide": "зарплата\n(7)"
  },
  {
    "review": "Отзыв сотрудника\n...\nРаботал 5-10 лет Москва, июнь 2025\n1,8\nЧто нравится?\nЗнаю все о магазинах, и корпоративной культуре данной компании.\nЧто можно улучшить?\nСоблюдение рабочих часов, снизить стресс в коллективе, повысить оклад, уменьшить премиальную часть зп.\nОтвет представителя компании\nИюнь 2025\nЗдравствуйте.\nМы ценим ваш многолетний опыт и знание компании изнутри.\nБудем признательны, если вы сможете более подробно рассказать об условиях работы, которые мы могли бы улучшить. Мы будем ждать от вас письмо на электронный адрес: ru_hr_feedback@ecco.com. Спасибо за ваши время и отзыв.\nПреимущества и льготы\nСвоевременная оплата труда\nНаличие кухни, места для обеда\nМедицинское страхование\nОплата больничного\nОплата мобильной связи\nКорпоративные мероприятия\nВсе 6\nПолезный отзыв\n 0\nСсылка на отзыв",
    "review__header-title": "Отзыв сотрудника",
    "share-block__item": "...",
    "tags__item": "Работал 5-10 лет",
    "tags__item (2)": "Москва, июнь 2025",
    "dj-rating": "1,8",
    "review__title": "Что нравится?",
    "review__title (2)": "Что можно улучшить?",
    "review__answer": "Ответ представителя компании\nИюнь 2025\nЗдравствуйте.\nМы ценим ваш многолетний опыт и знание компании изнутри.\nБудем признательны, если вы сможете более подробно рассказать об условиях работы, которые мы могли бы улучшить. Мы будем ждать от вас письмо на электронный адрес: ru_hr_feedback@ecco.com. Спасибо за ваши время и отзыв.",
    "review__answer-title": "Ответ представителя компании",
    "review__answer-date": "Июнь 2025",
    "review__title-privileges": "Преимущества и льготы",
    "tags__item (3)": "Своевременная оплата труда",
    "tags__item (4)": "Наличие кухни, места для обеда",
    "bt": "Полезный отзыв\n 0",
    "review__useful": "Полезный отзыв",
    "bt href": "https://dreamjob.ru/employers/25646?review_id=3745366",
    "bt (2)": "Ссылка на отзыв"
  },
  {
    "vacancies-banner__inner": "Вакансии в ECCO",
    "vacancies-banner__all href": "https://dreamjob.ru/employers/25646/vakansii",
    "vacancies-banner__all": "Все\n 74",
    "d-md-block": "Все",
    "vacancies-banner__head": "Продавец-консультант ECCO (МЕГА Парнас)",
    "vacancies-banner__сity": "Санкт-Петербург",
    "vacancies-banner__salary": "50 000 - 80 000 ₽",
    "job-vacancy__currency": "₽",
    "bt-master href": "https://dreamjob.ru/employers/25646/vakansii/126889064",
    "bt-master": "Посмотреть вакансию",
    "vacancies-banner__head (2)": "Продавец-консультант ECCO (ТЦ OZ МОЛЛ)",
    "vacancies-banner__сity (2)": "Краснодар",
    "vacancies-banner__salary (2)": "40 000 - 55 000 ₽",
    "bt-master href (2)": "https://dreamjob.ru/employers/25646/vakansii/126887530",
    "vacancies-banner__head (3)": "Директор магазина ECCO (Avenue Southwest)",
    "vacancies-banner__сity (3)": "Москва",
    "vacancies-banner__salary (3)": "90 000 - 130 000 ₽",
    "bt-master href (3)": "https://dreamjob.ru/employers/25646/vakansii/126887448",
    "vacancies-banner__head (4)": "Продавец-консультант ECCO (ТЦ Аура)",
    "vacancies-banner__сity (4)": "Новосибирск",
    "vacancies-banner__salary (4)": "от 60 000 ₽",
    "bt-master href (4)": "https://dreamjob.ru/employers/25646/vakansii/126045336",
    "vacancies-banner__head (5)": "Продавец-консультант ECCO ( ТЦ Бутово Молл)",
    "vacancies-banner__salary (5)": "60 000 - 80 000 ₽",
    "bt-master href (5)": "https://dreamjob.ru/employers/25646/vakansii/126110366"
  },
  {
    "review": "Продавец-консультант\n...\nРаботал 1-2 года Москва, декабрь 2024\n1,2\nЧто нравится?\nНи че го!!! Сложно сказать положительное, когда минусов больше чем плюсов\nЧто можно улучшить?\nУсловия труда, атмосферу в коллективе, заработную плату, график\nОтвет представителя компании\nДекабрь 2024\nЗдравствуйте.\nНам очень жаль, что ваши впечатления от работы оказались негативными. Если есть возможность, руководство магазина предлагает сотрудникам наиболее комфортные графики, а система адаптации помогает быстро влиться в коллектив и работу. Спасибо, что написали нам о вашем опыте и указали на ряд моментов, которые мы можем улучшить.\nПреимущества и льготы\nСвоевременная оплата труда\nОплата больничного\nПолезный отзыв\n 1\nСсылка на отзыв",
    "review__header-title": "Продавец-консультант",
    "share-block__item": "...",
    "tags__item": "Работал 1-2 года",
    "tags__item (2)": "Москва, декабрь 2024",
    "dj-rating": "1,2",
    "review__title": "Что нравится?",
    "review__title (2)": "Что можно улучшить?",
    "review__answer": "Ответ представителя компании\nДекабрь 2024\nЗдравствуйте.\nНам очень жаль, что ваши впечатления от работы оказались негативными. Если есть возможность, руководство магазина предлагает сотрудникам наиболее комфортные графики, а система адаптации помогает быстро влиться в коллектив и работу. Спасибо, что написали нам о вашем опыте и указали на ряд моментов, которые мы можем улучшить.",
    "review__answer-title": "Ответ представителя компании",
    "review__answer-date": "Декабрь 2024",
    "review__title-privileges": "Преимущества и льготы",
    "tags__item (3)": "Своевременная оплата труда",
    "tags__item (4)": "Оплата больничного",
    "bt": "Полезный отзыв\n 1",
    "review__useful": "Полезный отзыв",
    "bt href": "https://dreamjob.ru/employers/25646?review_id=3242776",
    "bt (2)": "Ссылка на отзыв"
  },
  {
    "review": "Продавец\n...\nРаботал 3-5 лет Москва, ноябрь 2024\n1,0\nЧто нравится?\nБелая зарплата, бесплатная обувь раз в полгода и на этом плюсы заканчиваются.\nЧто можно улучшить?\nОтношение вышестоящего руководства к линейному персоналу. Повышение зарплаты продавцам, условия труда. Нет даже места для приёма пищи.\nОтвет представителя компании\nНоябрь 2024\nЗдравствуйте.\nПриятно, что вы отметили официальную заработную плату и компенсацию обуви дважды в год. Мы работаем над тем, чтобы создать комфортную рабочую среду для всех наших сотрудников, перестраиваем зоны для приема пищи, организовываем мероприятия по сплочению коллектива. Спасибо, что указали на недочеты, мы примем во внимание.\nПолезный отзыв\n 1\nСсылка на отзыв",
    "review__header-title": "Продавец",
    "share-block__item": "...",
    "tags__item": "Работал 3-5 лет",
    "tags__item (2)": "Москва, ноябрь 2024",
    "dj-rating": "1,0",
    "review__title": "Что нравится?",
    "review__title (2)": "Что можно улучшить?",
    "review__answer": "Ответ представителя компании\nНоябрь 2024\nЗдравствуйте.\nПриятно, что вы отметили официальную заработную плату и компенсацию обуви дважды в год. Мы работаем над тем, чтобы создать комфортную рабочую среду для всех наших сотрудников, перестраиваем зоны для приема пищи, организовываем мероприятия по сплочению коллектива. Спасибо, что указали на недочеты, мы примем во внимание.",
    "review__answer-title": "Ответ представителя компании",
    "review__answer-date": "Ноябрь 2024",
    "bt": "Полезный отзыв\n 1",
    "review__useful": "Полезный отзыв",
    "bt href": "https://dreamjob.ru/employers/25646?review_id=3127597",
    "bt (2)": "Ссылка на отзыв"
  },
  {
    "review": "Бухгалтер по расчетам с поставщиками\n...\nРаботал 1-2 года Москва, октябрь 2024\n1,8\nЧто нравится?\nБлизость к дому, зарплата без задержек, из плюсов это все.\nЧто можно улучшить?\nУсловия труда, оборудование, остановить текучку кадров в бухгалтерии\nОтвет представителя компании\nНоябрь 2024\nЗдравствуйте.\nЗдорово, что вам было удобно добираться до работы. Приятно, что вы отметили своевременную выплату заработной платы. Спасибо за замечания об условиях труда и оборудовании для бухгалтеров, мы обратим внимание.\nПреимущества и льготы\nСвоевременная оплата труда\nПолезный отзыв\n 1\nСсылка на отзыв",
    "review__header-title": "Бухгалтер по расчетам с поставщиками",
    "share-block__item": "...",
    "tags__item": "Работал 1-2 года",
    "tags__item (2)": "Москва, октябрь 2024",
    "dj-rating": "1,8",
    "review__title": "Что нравится?",
    "review__title (2)": "Что можно улучшить?",
    "review__answer": "Ответ представителя компании\nНоябрь 2024\nЗдравствуйте.\nЗдорово, что вам было удобно добираться до работы. Приятно, что вы отметили своевременную выплату заработной платы. Спасибо за замечания об условиях труда и оборудовании для бухгалтеров, мы обратим внимание.",
    "review__answer-title": "Ответ представителя компании",
    "review__answer-date": "Ноябрь 2024",
    "review__title-privileges": "Преимущества и льготы",
    "tags__item (3)": "Своевременная оплата труда",
    "bt": "Полезный отзыв\n 1",
    "review__useful": "Полезный отзыв",
    "bt href": "https://dreamjob.ru/employers/25646?review_id=3079660",
    "bt (2)": "Ссылка на отзыв"
  },
  {
    "review": "Кладовщик\n...\nРаботал меньше года Москва, март 2024\n1,7\nЧто нравится?\nЕсть персональная скидка на продукцию. Относительно близко к дому, опытный коллектив\nЧто можно улучшить?\nСистему наставничества, мотивацию, отмены некоторых рабочих мероприятий\nПолезный отзыв\n 0\nСсылка на отзыв\nОтветить от лица компании",
    "review__header-title": "Кладовщик",
    "share-block__item": "...",
    "tags__item": "Работал меньше года",
    "tags__item (2)": "Москва, март 2024",
    "dj-rating": "1,7",
    "review__title": "Что нравится?",
    "review__title (2)": "Что можно улучшить?",
    "bt": "Полезный отзыв\n 0",
    "review__useful": "Полезный отзыв",
    "bt href": "https://dreamjob.ru/employers/25646?review_id=2411460",
    "bt (2)": "Ссылка на отзыв",
    "bt href (2)": "https://dreamjob.ru/page/employers"
  },
  {
    "review": "Администратор магазина\n...\nРаботал меньше года Москва, январь 2024\n1,5\nЧто нравится?\nинтересная история бренда\nЧто можно улучшить?\nусловия труда + заработную плату. работая на маленькой точке, как ни крути - получишь копейки)) меня взяли на работу в сезон отпусков и ни о каких 2/2 речи не шло вообще, при этом упариваешься + нужно учить бесконечный материал о компании. работать можешь за продавца, получая ставку меньше обычной, писать отчеты почему продано так мало и тд, самая скучая работа в моей жизни- ни денег, ни удовольствия) нужно быть фанатиком фирмы и работы в целом (кроме директора, никто им не был)\nОтвет представителя компании\nФевраль 2024\nЗдравствуйте.\nСпасибо за ваши время и отзыв.\nВаши замечания о заработной плате и условиях работы в компании мы обязательно передадим в соответствующий отдел.\nБудем признательны, если вы сможете описать их более подробно в письме на наш электронный адрес: ru_hr_feedback@ecco.com.\nПреимущества и льготы\nСвоевременная оплата труда\nПрофессиональное обучение\nПолезный отзыв\n 1\nСсылка на отзыв",
    "review__header-title": "Администратор магазина",
    "share-block__item": "...",
    "tags__item": "Работал меньше года",
    "tags__item (2)": "Москва, январь 2024",
    "dj-rating": "1,5",
    "review__title": "Что нравится?",
    "review__title (2)": "Что можно улучшить?",
    "review__answer": "Ответ представителя компании\nФевраль 2024\nЗдравствуйте.\nСпасибо за ваши время и отзыв.\nВаши замечания о заработной плате и условиях работы в компании мы обязательно передадим в соответствующий отдел.\nБудем признательны, если вы сможете описать их более подробно в письме на наш электронный адрес: ru_hr_feedback@ecco.com.",
    "review__answer-title": "Ответ представителя компании",
    "review__answer-date": "Февраль 2024",
    "review__title-privileges": "Преимущества и льготы",
    "tags__item (3)": "Своевременная оплата труда",
    "tags__item (4)": "Профессиональное обучение",
    "bt": "Полезный отзыв\n 1",
    "review__useful": "Полезный отзыв",
    "bt href": "https://dreamjob.ru/employers/25646?review_id=2310982",
    "bt (2)": "Ссылка на отзыв"
  },
  {
    "bt": "Посмотреть все зарплаты (109)",
    "bt href": "https://dreamjob.ru/employers/25646/zarplata",
    "job-vacancy__currency": "₽",
    "swiper-slide": "Посмотреть\nеще зарплаты"
  },
  {
    "review": "Отзыв сотрудника\n...\nРаботаю 1-2 года Москва, октябрь 2023\n1,0\nЧто нравится?\nкрасивый офис, офис недалеко от метро\nЧто можно улучшить?\nотношение к сотрудникам, уважение сотрудников, количество работы укладывается в рабочее время, работа только в рабочее время в рабочие дни и часы\nПреимущества и льготы\nНаличие кухни, места для обеда\nПолезный отзыв\n 0\nСсылка на отзыв\nОтветить от лица компании",
    "review__header-title": "Отзыв сотрудника",
    "share-block__item": "...",
    "tags__item": "Работаю 1-2 года",
    "tags__item (2)": "Москва, октябрь 2023",
    "dj-rating": "1,0",
    "review__title": "Что нравится?",
    "review__title (2)": "Что можно улучшить?",
    "review__title-privileges": "Преимущества и льготы",
    "tags__item (3)": "Наличие кухни, места для обеда",
    "bt": "Полезный отзыв\n 0",
    "review__useful": "Полезный отзыв",
    "bt href": "https://dreamjob.ru/employers/25646?review_id=2016742",
    "bt (2)": "Ссылка на отзыв",
    "bt href (2)": "https://dreamjob.ru/page/employers"
  },
  {
    "review": "Продавец-консультант\n...\nРаботаю 3-5 лет Москва, июль 2023\n1,7\nЧто нравится?\nТолько пожалуй близость к дому,ну еще бывает коллектив, я проработал в европейском, на автозаводской,более менее коллектив был на автозаводской.\nЧто можно улучшить?\nУлучшить можно было бы все, но руководство компании не ценит лучших сотрудников, вынуждает их увольняться , тк низкая зп ( а работу ты делаешь всю и кассир и кладовщик и администратор и за директора) а зп одна как продавец-консультант, и еще тебе претензий куча. Не советую эту компанию! Ни кому.\nПреимущества и льготы\nСвоевременная оплата труда\nУдобное расположение работы\nПолезный отзыв\n 5\nСсылка на отзыв\nОтветить от лица компании",
    "review__header-title": "Продавец-консультант",
    "share-block__item": "...",
    "tags__item": "Работаю 3-5 лет",
    "tags__item (2)": "Москва, июль 2023",
    "dj-rating": "1,7",
    "review__title": "Что нравится?",
    "review__title (2)": "Что можно улучшить?",
    "review__title-privileges": "Преимущества и льготы",
    "tags__item (3)": "Своевременная оплата труда",
    "tags__item (4)": "Удобное расположение работы",
    "bt": "Полезный отзыв\n 5",
    "review__useful": "Полезный отзыв",
    "bt href": "https://dreamjob.ru/employers/25646?review_id=1852236",
    "bt (2)": "Ссылка на отзыв",
    "bt href (2)": "https://dreamjob.ru/page/employers"
  }
]