[
  {
    "review": "Руководитель отдела RnD\n...\nРаботаю меньше года Москва, апрель 2025\n5,0\nУсловия труда\nУровень дохода\nКоллектив\nРуководство\nУсловия для отдыха\nВозможности роста\nЧто нравится?\nРабота удаленная, что почти всегда ведет к полному обезличиваю коллег и результатов работы, но не в этом случае: трушный коллектив, живые встречи и приятельское общение - это про ITDev\nДеятельность исследовательская, что дает возможность проявить свои лучшие качества и увидеть плоды собственной деятельности без непрерывного контроля, регламенту по составлению регламентов и прочего\nБольшое количество точек роста и высокий потенциал к нему (при условии продуктивной работы)\nЧто можно улучшить?\nСледствие молодости компании - отсутствие ДМС (что кстати вообще не минус, потому что по факту это часть ФОТа, которая не доходит до сотрудников)\nПреимущества и льготы\nСвоевременная оплата труда\nУдаленная работа\nГибкий рабочий график\nПрофессиональное обучение\nСистема наставничества\nПолезный отзыв\n 0\nСсылка на отзыв\nОтветить от лица компании",
    "review__header-title": "Руководитель отдела RnD",
    "share-block__item": "...",
    "tags__item": "Работаю меньше года",
    "tags__item (2)": "Москва, апрель 2025",
    "dj-rating": "5,0",
    "review__title": "Что нравится?",
    "review__title (2)": "Что можно улучшить?",
    "review__title-privileges": "Преимущества и льготы",
    "tags__item (3)": "Своевременная оплата труда",
    "tags__item (4)": "Удаленная работа",
    "tags__item (5)": "Гибкий рабочий график",
    "tags__item (6)": "Профессиональное обучение",
    "tags__item (7)": "Система наставничества",
    "bt": "Полезный отзыв\n 0",
    "review__useful": "Полезный отзыв",
    "bt href": "https://dreamjob.ru/employers/5874703?review_id=3644736",
    "bt (2)": "Ссылка на отзыв",
    "bt href (2)": "https://dreamjob.ru/page/employers",
    "bt (3)": "Ответить от лица компании"
  },
  {
    "tags__item": "От 1 года до 3 лет",
    "tags__item (2)": "Можно удаленно"
  },
  {
    "review": "Менеджер по продажам\n...\nРаботал меньше года Люберцы, апрель 2025\n4,7\nЧто нравится?\nВозможности для роста в компании, так как компания только начинает свой путь и можно вырасти до руководителя. Также супер адекватное руководство\nЧто можно улучшить?\nМожно доработать обучение, так как все происходит вручную, можно автоматизировать\nПреимущества и льготы\nУдаленная работа\nГибкий рабочий график\nОплата мобильной связи\nСистема наставничества\nКорпоративные мероприятия\nВсе 5\nПолезный отзыв\n 0\nСсылка на отзыв\nОтветить от лица компании",
    "review__header-title": "Менеджер по продажам",
    "share-block__item": "...",
    "tags__item": "Работал меньше года",
    "tags__item (2)": "Люберцы, апрель 2025",
    "dj-rating": "4,7",
    "review__title": "Что нравится?",
    "review__title (2)": "Что можно улучшить?",
    "review__title-privileges": "Преимущества и льготы",
    "tags__item (3)": "Удаленная работа",
    "tags__item (4)": "Гибкий рабочий график",
    "tags__item (5)": "Оплата мобильной связи",
    "tags__item (6)": "Система наставничества",
    "tags__item (7)": "Корпоративные мероприятия",
    "bt": "Полезный отзыв\n 0",
    "review__useful": "Полезный отзыв",
    "bt href": "https://dreamjob.ru/employers/5874703?review_id=3644467",
    "bt (2)": "Ссылка на отзыв",
    "bt href (2)": "https://dreamjob.ru/page/employers",
    "bt (3)": "Ответить от лица компании",
    "bt (4)": "Все 5"
  },
  {
    "review": "Отзыв сотрудника\n...\nРаботаю 1-2 года Люберцы, апрель 2025\n5,0\nЧто нравится?\nКрутой коллектив, сильная команда и прекрасное руководство. Все что нужно для работы в удовольствие с прекрасной зп\nЧто можно улучшить?\nНе могу назвать недостатки этой работы, все было на высшем уровне\nПреимущества и льготы\nСвоевременная оплата труда\nУдобное расположение работы\nУдаленная работа\nГибкий рабочий график\nПрофессиональное обучение\nСистема наставничества\nКорпоративные мероприятия\nВсе 7\nПолезный отзыв\n 0\nСсылка на отзыв\nОтветить от лица компании",
    "review__header-title": "Отзыв сотрудника",
    "share-block__item": "...",
    "tags__item": "Работаю 1-2 года",
    "tags__item (2)": "Люберцы, апрель 2025",
    "dj-rating": "5,0",
    "review__title": "Что нравится?",
    "review__title (2)": "Что можно улучшить?",
    "review__title-privileges": "Преимущества и льготы",
    "tags__item (3)": "Своевременная оплата труда",
    "tags__item (4)": "Удобное расположение работы",
    "tags__item (5)": "Удаленная работа",
    "tags__item (6)": "Гибкий рабочий график",
    "tags__item (7)": "Профессиональное обучение",
    "bt": "Полезный отзыв\n 0",
    "review__useful": "Полезный отзыв",
    "bt href": "https://dreamjob.ru/employers/5874703?review_id=3644479",
    "bt (2)": "Ссылка на отзыв",
    "bt href (2)": "https://dreamjob.ru/page/employers",
    "bt (3)": "Ответить от лица компании",
    "bt (4)": "Все 7"
  }
]