[
  {
    "review": "Агент по недвижимости\n...\nРаботаю меньше года Москва, октябрь 2025\n1,0\nЧто нравится?\nНичего не нравится, компания полностью игнорирует чаты, обращения.\nЧто можно улучшить?\nУлучшить отношение к будущим сотрудникам, потому что сначала HR высылает приглашение на обсуждение деталей вакансии, а потом просто игнорирует везде, но после присылает сообщение, что моб кандидатуру уже рассмотрят. Очень пахнет \"профессионализмом\" со стороны сотрудника по подбору персонала.\nПреимущества и льготы\nКорпоративные мероприятия\nПолезный отзыв\n 2\nСсылка на отзыв\nОтветить от лица компании",
    "review__header-title": "Агент по недвижимости",
    "share-block__item": "...",
    "tags__item": "Работаю меньше года",
    "tags__item (2)": "Москва, октябрь 2025",
    "dj-rating": "1,0",
    "review__title": "Что нравится?",
    "review__title (2)": "Что можно улучшить?",
    "review__title-privileges": "Преимущества и льготы",
    "tags__item (3)": "Корпоративные мероприятия",
    "bt": "Полезный отзыв\n 2",
    "review__useful": "Полезный отзыв",
    "bt href": "https://dreamjob.ru/employers/302146?review_id=4141910",
    "bt (2)": "Ссылка на отзыв",
    "bt href (2)": "https://dreamjob.ru/page/employers",
    "bt (3)": "Ответить от лица компании"
  },
  {
    "vacancies-banner__inner": "Вакансии в Homeapp",
    "vacancies-banner__all href": "https://dreamjob.ru/employers/302146/vakansii",
    "vacancies-banner__all": "Все\n 17",
    "d-md-none": "Все",
    "vacancies-banner__head": "Руководитель отдела продаж (РОП) в AI-компанию Homeapp",
    "vacancies-banner__сity": "Москва",
    "vacancies-banner__salary": "150 000 - 400 000 ₽",
    "job-vacancy__currency": "₽",
    "bt-master href": "https://dreamjob.ru/employers/302146/vakansii/126881255",
    "bt-master": "Посмотреть вакансию",
    "vacancies-banner__head (2)": "Эксперт по Аренде жилой недвижимости в технологическую компанию Homeapp",
    "vacancies-banner__salary (2)": "от 300 000 ₽",
    "bt-master href (2)": "https://dreamjob.ru/employers/302146/vakansii/126836555",
    "vacancies-banner__head (3)": "Агент по Аренде жилой недвижимости в технологическую компанию Homeapp (Москва Сити)",
    "bt-master href (3)": "https://dreamjob.ru/employers/302146/vakansii/126814179",
    "vacancies-banner__head (4)": "Менеджер по недвижимости Homeapp (Москва Сити)",
    "vacancies-banner__salary (4)": "400 000 - 800 000 ₽",
    "bt-master href (4)": "https://dreamjob.ru/employers/302146/vakansii/126814098",
    "vacancies-banner__head (5)": "Менеджер по продаже недвижимости (Москва Сити)",
    "vacancies-banner__salary (5)": "300 000 - 700 000 ₽",
    "bt-master href (5)": "https://dreamjob.ru/employers/302146/vakansii/126814017"
  },
  {
    "review": "Агент по недвижимости\n...\nРаботаю меньше года Москва, октябрь 2025\n5,0\nЧто нравится?\nВ Homeapp крутой коллектив, всегда все поймут, поддержат\nОбучение реально работает- после него не страшно звонить клиентам и выезжать на встречи\nЕсть маркетинг, клиенты, CRM-все для того, что бы заниматься делом, а не рутиной\nОчень давольно что попала сюда- больше перспектив\nЧто можно улучшить?\nСоздавать благоприятный климат и мотивировать сотрудников через бонусы и карьерный рост\nПреимущества и льготы\nУдобное расположение работы\nУдаленная работа\nНаличие кухни, места для обеда\nГибкий рабочий график\nСистема наставничества\nВсе 5\nПолезный отзыв\n 0\nСсылка на отзыв\nОтветить от лица компании",
    "review__header-title": "Агент по недвижимости",
    "share-block__item": "...",
    "tags__item": "Работаю меньше года",
    "tags__item (2)": "Москва, октябрь 2025",
    "dj-rating": "5,0",
    "review__title": "Что нравится?",
    "review__title (2)": "Что можно улучшить?",
    "review__title-privileges": "Преимущества и льготы",
    "tags__item (3)": "Удобное расположение работы",
    "bt": "Полезный отзыв\n 0",
    "review__useful": "Полезный отзыв",
    "bt href": "https://dreamjob.ru/employers/302146?review_id=4092760",
    "bt (2)": "Ссылка на отзыв",
    "bt href (2)": "https://dreamjob.ru/page/employers",
    "bt (3)": "Ответить от лица компании",
    "tags__item (4)": "Удаленная работа",
    "tags__item (5)": "Наличие кухни, места для обеда",
    "tags__item (6)": "Гибкий рабочий график",
    "tags__item (7)": "Система наставничества",
    "bt (4)": "Все 5"
  },
  {
    "swiper-slide": "обучение\n(9)"
  },
  {
    "review": "Агент по недвижимости\n...\nРаботаю меньше года Москва, октябрь 2025\n5,0\nЧто нравится?\nИзначально шла сюда, зная, что это работа на будущее. Данная компания дала мне хорошую школу и ресурсы для развития, хорошего старта. Еще нравится, что есть наставничество, что позволяет корректировать свою рабочую для улучшения результата, нравится что есть системность , благодаря которой поддерживается твоя дисциплина. Эта компания помогла мне выйти на желаемый доход, еще + в том, что все начисляется моментально и не нужно ждать\nЧто можно улучшить?\nВ целом это компания развивается, поэтому все впереди, нужно до конца систематизировать использование искусственного интеллекта\nОтвет представителя компании\nОктябрь 2025\nСпасибо за отзыв и за то, что отметили сильные стороны Homeapp — системность, наставничество и возможности для роста.\nМы рады, что компания стала для вас площадкой для развития и достижения финансовых целей.\nСогласны: потенциал AI-технологий огромен, и мы уже активно масштабируем их использование во всех процессах.\n\nHR-команда Homeapp\nПреимущества и льготы\nСвоевременная оплата труда\nНаличие кухни, места для обеда\nГибкий рабочий график\nПрофессиональное обучение\nОплата мобильной связи\nСистема наставничества\nВсе 6\nПолезный отзыв\n 0\nСсылка на отзыв",
    "review__header-title": "Агент по недвижимости",
    "share-block__item": "...",
    "tags__item": "Работаю меньше года",
    "tags__item (2)": "Москва, октябрь 2025",
    "dj-rating": "5,0",
    "review__title": "Что нравится?",
    "review__title (2)": "Что можно улучшить?",
    "review__title-privileges": "Преимущества и льготы",
    "tags__item (3)": "Своевременная оплата труда",
    "bt": "Полезный отзыв\n 0",
    "review__useful": "Полезный отзыв",
    "bt href": "https://dreamjob.ru/employers/302146?review_id=4092741",
    "bt (2)": "Ссылка на отзыв",
    "tags__item (4)": "Наличие кухни, места для обеда",
    "tags__item (5)": "Гибкий рабочий график",
    "tags__item (6)": "Профессиональное обучение",
    "tags__item (7)": "Оплата мобильной связи",
    "bt (4)": "Все 6",
    "review__answer": "Ответ представителя компании\nОктябрь 2025\nСпасибо за отзыв и за то, что отметили сильные стороны Homeapp — системность, наставничество и возможности для роста.\nМы рады, что компания стала для вас площадкой для развития и достижения финансовых целей.\nСогласны: потенциал AI-технологий огромен, и мы уже активно масштабируем их использование во всех процессах.\n\nHR-команда Homeapp",
    "review__answer-title": "Ответ представителя компании",
    "review__answer-date": "Октябрь 2025",
    "tags__item (8)": "Система наставничества"
  },
  {
    "vacancies-banner__inner": "Вакансии в Homeapp",
    "vacancies-banner__all href": "https://dreamjob.ru/employers/302146/vakansii",
    "vacancies-banner__all": "Все\n 17",
    "d-md-none": "Все",
    "vacancies-banner__head": "Руководитель отдела продаж (РОП) в AI-компанию Homeapp",
    "vacancies-banner__сity": "Москва",
    "vacancies-banner__salary": "150 000 - 400 000 ₽",
    "job-vacancy__currency": "₽",
    "bt-master href": "https://dreamjob.ru/employers/302146/vakansii/126881255",
    "bt-master": "Посмотреть вакансию",
    "vacancies-banner__head (2)": "Эксперт по Аренде жилой недвижимости в технологическую компанию Homeapp",
    "vacancies-banner__salary (2)": "от 300 000 ₽",
    "bt-master href (2)": "https://dreamjob.ru/employers/302146/vakansii/126836555",
    "vacancies-banner__head (3)": "Агент по Аренде жилой недвижимости в технологическую компанию Homeapp (Москва Сити)",
    "bt-master href (3)": "https://dreamjob.ru/employers/302146/vakansii/126814179",
    "vacancies-banner__head (4)": "Менеджер по недвижимости Homeapp (Москва Сити)",
    "vacancies-banner__salary (4)": "400 000 - 800 000 ₽",
    "bt-master href (4)": "https://dreamjob.ru/employers/302146/vakansii/126814098",
    "vacancies-banner__head (5)": "Менеджер по продаже недвижимости (Москва Сити)",
    "vacancies-banner__salary (5)": "300 000 - 700 000 ₽",
    "bt-master href (5)": "https://dreamjob.ru/employers/302146/vakansii/126814017"
  },
  {
    "review": "Руководитель отдела\n...\nРаботал 1-2 года Москва, октябрь 2025\n2,0\nЧто нравится?\nЮридическая поддержка. Сопровождение агентов на всех этапах - от предварительного соглашения до заключения сделки. Просторный офис, не далеко от метро.\nЧто можно улучшить?\nУскорить выплаты комиссионных агентам. Очень долгие выплаты после полностью закрытых сделок. Срок ожидания от одного до нескольких месяцев.\nОтвет представителя компании\nОктябрь 2025\nМы благодарим вас за отзыв — он помогает нам совершенствовать внутренние процессы и делать взаимодействие ещё удобнее.\n\nHomeapp действительно уделяет большое внимание юридическому сопровождению и прозрачности расчётов. Все выплаты проходят строго по регламенту, без задержек — по мере закрытия сделок и подписания документов. В компании уже выстроена система быстрых и прозрачных расчётов, а бизнес-процессы регулярно совершенствуются, чтобы поддерживать этот уровень скорости и удобства.\n\nСпасибо, что отметили сильные стороны нашей команды и условия работы. Нам важно, чтобы опыт взаимодействия с компанией оставался положительным и после завершения сотрудничества.\n\nHR-команда Homeapp\nПреимущества и льготы\nНаличие кухни, места для обеда\nГибкий рабочий график\nСистема наставничества\nВсе 3\nПолезный отзыв\n 4\nСсылка на отзыв",
    "review__header-title": "Руководитель отдела",
    "share-block__item": "...",
    "tags__item": "Работал 1-2 года",
    "tags__item (2)": "Москва, октябрь 2025",
    "dj-rating": "2,0",
    "review__title": "Что нравится?",
    "review__title (2)": "Что можно улучшить?",
    "review__title-privileges": "Преимущества и льготы",
    "tags__item (3)": "Наличие кухни, места для обеда",
    "bt": "Полезный отзыв\n 4",
    "review__useful": "Полезный отзыв",
    "bt href": "https://dreamjob.ru/employers/302146?review_id=4091453",
    "bt (2)": "Ссылка на отзыв",
    "tags__item (4)": "Гибкий рабочий график",
    "tags__item (5)": "Система наставничества",
    "bt (4)": "Все 3",
    "review__answer": "Ответ представителя компании\nОктябрь 2025\nМы благодарим вас за отзыв — он помогает нам совершенствовать внутренние процессы и делать взаимодействие ещё удобнее.\n\nHomeapp действительно уделяет большое внимание юридическому сопровождению и прозрачности расчётов. Все выплаты проходят строго по регламенту, без задержек — по мере закрытия сделок и подписания документов. В компании уже выстроена система быстрых и прозрачных расчётов, а бизнес-процессы регулярно совершенствуются, чтобы поддерживать этот уровень скорости и удобства.\n\nСпасибо, что отметили сильные стороны нашей команды и условия работы. Нам важно, чтобы опыт взаимодействия с компанией оставался положительным и после завершения сотрудничества.\n\nHR-команда Homeapp",
    "review__answer-title": "Ответ представителя компании",
    "review__answer-date": "Октябрь 2025"
  },
  {
    "review": "Агент по недвижимости\n...\nРаботаю меньше года октябрь 2025\n5,0\nЧто нравится?\nОтличное место для старта карьеры, обучение с нуля, есть выплаты на старте. Для меня все максимально комфортно и понятно. График работы выстраиваешь под себя, работать приходится много, но доход соответственно тоже высокий.\nЧто можно улучшить?\nВ дальнейшем расширять офис или открывать новые, коллектив заметно растет!\nОтвет представителя компании\nОктябрь 2025\nСпасибо за вашу оценку и подробный отзыв! Рады, что отметили обучение с нуля, выплаты на старте и удобство с гибким графиком — именно на это делаем упор для комфортного входа в профессию. Согласны: темп у нас высокий, и доход действительно растёт вместе с вкладом и самоорганизацией — мы честно говорим об этом на старте.\n\nСпасибо, что помогаете нам становиться лучше!\nHR-команда Homeapp\nПреимущества и льготы\nСвоевременная оплата труда\nУдобное расположение работы\nНаличие кухни, места для обеда\nГибкий рабочий график\nОплата мобильной связи\nСистема наставничества\nКорпоративные мероприятия\nВсе 7\nПолезный отзыв\n 1\nСсылка на отзыв",
    "review__header-title": "Агент по недвижимости",
    "share-block__item": "...",
    "tags__item": "Работаю меньше года",
    "tags__item (2)": "октябрь 2025",
    "dj-rating": "5,0",
    "review__title": "Что нравится?",
    "review__title (2)": "Что можно улучшить?",
    "review__title-privileges": "Преимущества и льготы",
    "tags__item (3)": "Своевременная оплата труда",
    "bt": "Полезный отзыв\n 1",
    "review__useful": "Полезный отзыв",
    "bt href": "https://dreamjob.ru/employers/302146?review_id=4086677",
    "bt (2)": "Ссылка на отзыв",
    "tags__item (4)": "Удобное расположение работы",
    "tags__item (5)": "Наличие кухни, места для обеда",
    "tags__item (6)": "Гибкий рабочий график",
    "tags__item (7)": "Оплата мобильной связи",
    "bt (4)": "Все 7",
    "review__answer": "Ответ представителя компании\nОктябрь 2025\nСпасибо за вашу оценку и подробный отзыв! Рады, что отметили обучение с нуля, выплаты на старте и удобство с гибким графиком — именно на это делаем упор для комфортного входа в профессию. Согласны: темп у нас высокий, и доход действительно растёт вместе с вкладом и самоорганизацией — мы честно говорим об этом на старте.\n\nСпасибо, что помогаете нам становиться лучше!\nHR-команда Homeapp",
    "review__answer-title": "Ответ представителя компании",
    "review__answer-date": "Октябрь 2025",
    "tags__item (8)": "Система наставничества",
    "tags__item (9)": "Корпоративные мероприятия"
  },
  {
    "review": "Эксперт по продажам\n...\nРаботаю меньше года Москва, август 2025\n4,8\nЧто нравится?\n- понятные цели достижения результата в компании\n- открытость\n- внедрение новых технологий в процесс работы\n- стремление к совершенству и достижению поставленных задач\n- хороший профессиональный коллектив\n- грамотное обучение для новых сотрудников\nЧто можно улучшить?\n- повышение узнаваемости бренда компании\n- развитие новых направлений\nОтвет представителя компании\nОктябрь 2025\nБлагодарим вас за отзыв и за то, что отметили сильные стороны компании!\n\nHomeapp действительно развивается в сторону прозрачности, технологий и командной работы — для нас важно, чтобы каждый сотрудник понимал цели, видел результат и чувствовал поддержку коллег и наставников.\n\nМы согласны: повышение узнаваемости бренда и развитие новых направлений — это важные задачи, над которыми команда уже активно работает.\n\nСпасибо, что вы с нами и помогаете Homeapp становиться ещё сильнее!\nHR-команда Homeapp\nПреимущества и льготы\nСвоевременная оплата труда\nУдобное расположение работы\nУдаленная работа\nНаличие кухни, места для обеда\nПрофессиональное обучение\nСистема наставничества\nКорпоративные мероприятия\nВсе 7\nПолезный отзыв\n 2\nСсылка на отзыв",
    "review__header-title": "Эксперт по продажам",
    "share-block__item": "...",
    "tags__item": "Работаю меньше года",
    "tags__item (2)": "Москва, август 2025",
    "dj-rating": "4,8",
    "review__title": "Что нравится?",
    "review__title (2)": "Что можно улучшить?",
    "review__title-privileges": "Преимущества и льготы",
    "tags__item (3)": "Своевременная оплата труда",
    "bt": "Полезный отзыв\n 2",
    "review__useful": "Полезный отзыв",
    "bt href": "https://dreamjob.ru/employers/302146?review_id=3924812",
    "bt (2)": "Ссылка на отзыв",
    "tags__item (4)": "Удобное расположение работы",
    "tags__item (5)": "Удаленная работа",
    "tags__item (6)": "Наличие кухни, места для обеда",
    "tags__item (7)": "Профессиональное обучение",
    "bt (4)": "Все 7",
    "review__answer": "Ответ представителя компании\nОктябрь 2025\nБлагодарим вас за отзыв и за то, что отметили сильные стороны компании!\n\nHomeapp действительно развивается в сторону прозрачности, технологий и командной работы — для нас важно, чтобы каждый сотрудник понимал цели, видел результат и чувствовал поддержку коллег и наставников.\n\nМы согласны: повышение узнаваемости бренда и развитие новых направлений — это важные задачи, над которыми команда уже активно работает.\n\nСпасибо, что вы с нами и помогаете Homeapp становиться ещё сильнее!\nHR-команда Homeapp",
    "review__answer-title": "Ответ представителя компании",
    "review__answer-date": "Октябрь 2025",
    "tags__item (8)": "Система наставничества",
    "tags__item (9)": "Корпоративные мероприятия"
  },
  {
    "review": "Брокер по недвижимости\n...\nРаботаю 1-2 года август 2025\n5,0\nЧто нравится?\nЭто лучшая компания, в которой мне повезло работать.\nКогда выбирала компанию для меня были важны : репутация, стабильность, узнаваемость и технологичность=скорость процессов. Всё это влияет на доверие клиентов, что очень важно в клиентском бизнесе, влияет на настрой в работе и результат.\nМне важно было, чтобы в компании была система обучения и развития, адаптация, внятная программа для новичков. Я пришла нулёвой, и чтобы плавно вникнуть во все процессы, быстро начать зарабатывать, понимала, это must have. Приятно была удивлена институту наставничества. Не в омут с головой, не в океан неопределённости, а «тебе помогут», это критически важно в начале! В компании регулярно проводятся тренинги, внешние и внутренние, чувствуешь постоянный рост!\nЕсть удобная СРМ, мобильное приложение, удобные корп.мессенджеры - всё супер технологично! База знаний укомплектована всеми шаблонами юр.доков, внутренними материалами компании, работающими сезонно обновляющимися скриптами для работы.\nИ, конечно же, про деньги: Прозрачная высокая мотивация: нет потолка для доходов, процент позволяющий не анализировать, «а сколько сейчас у соседа», а работать и зарабатывать весьма достойно. Еще одна «боль» брокеров - Лиды. Входящий поток компания обеспечивает с помощью сайта, рекламы, базы, прозвона колл-центра, это очень заряжает на работу! Корпоративная культура высокая, командный дух на уровне,\nатмосферка классная, вайб современный, быстрый, лёгкий, ценности у людей достойные, всё это чувствуется в общении друг с другом и в отношении брокеров к клиентам. Приятно работать. Как подобает бирюзовым компаниям, здесь инициатива выслушивается/учитывается/поддерживается. Руководители доступны для диалога. Есть поддержка юристов, маркетологов. Крутые корпоративы-это отдельная тема, которую можно прочувствовать, будучи частью этой успешной команды!\nЧто можно улучшить?\nВыпускать больше контента в соц сетях и создать онлайн-школу, у компании крутые наработки, чтобы их передавать и масштабировать.\nОтвет представителя компании\nОктябрь 2025\nСпасибо за такой вдохновляющий отзыв! 💫\nРады, что вы цените системность, технологии и командную атмосферу — именно это делает Homeapp особенным местом для роста.\n\nHR-команда Homeapp\nПреимущества и льготы\nСвоевременная оплата труда\nУдобное расположение работы\nУдаленная работа\nНаличие кухни, места для обеда\nГибкий рабочий график\nПрофессиональное обучение\nСистема наставничества\nКорпоративные мероприятия\nВсе 8\nПолезный отзыв\n 2\nСсылка на отзыв",
    "review__header-title": "Брокер по недвижимости",
    "share-block__item": "...",
    "tags__item": "Работаю 1-2 года",
    "tags__item (2)": "август 2025",
    "dj-rating": "5,0",
    "review__title": "Что нравится?",
    "review__title (2)": "Что можно улучшить?",
    "review__title-privileges": "Преимущества и льготы",
    "tags__item (3)": "Своевременная оплата труда",
    "bt": "Полезный отзыв\n 2",
    "review__useful": "Полезный отзыв",
    "bt href": "https://dreamjob.ru/employers/302146?review_id=3924643",
    "bt (2)": "Ссылка на отзыв",
    "tags__item (4)": "Удобное расположение работы",
    "tags__item (5)": "Удаленная работа",
    "tags__item (6)": "Наличие кухни, места для обеда",
    "tags__item (7)": "Гибкий рабочий график",
    "bt (4)": "Все 8",
    "review__answer": "Ответ представителя компании\nОктябрь 2025\nСпасибо за такой вдохновляющий отзыв! 💫\nРады, что вы цените системность, технологии и командную атмосферу — именно это делает Homeapp особенным местом для роста.\n\nHR-команда Homeapp",
    "review__answer-title": "Ответ представителя компании",
    "review__answer-date": "Октябрь 2025",
    "tags__item (8)": "Профессиональное обучение",
    "tags__item (9)": "Система наставничества",
    "tags__item (10)": "Корпоративные мероприятия"
  },
  {
    "review": "Эксперт по продажам\n...\nРаботаю 3-5 лет Москва, август 2025\n4,7\nЧто нравится?\nВыбирал из 10 агентств. Понравилось, что много людей работает, просторный офис, отличаются от других, применяют технологии, делятся информацией и новостями, готовы меняться вместе со временем.\nЧто можно улучшить?\nМожно было бы нанять сотрудника, который постоянно занимался бы хозяйственными вопросами. И поменять башню в Сити на более удобную. Но это придирки. Понимаю, что они влекут дополнительные расходы.\nПреимущества и льготы\nУдобное расположение работы\nУдаленная работа\nНаличие кухни, места для обеда\nГибкий рабочий график\nПрофессиональное обучение\nСистема наставничества\nКорпоративные мероприятия\nВсе 7\nПолезный отзыв\n 2\nСсылка на отзыв\nОтветить от лица компании",
    "review__header-title": "Эксперт по продажам",
    "share-block__item": "...",
    "tags__item": "Работаю 3-5 лет",
    "tags__item (2)": "Москва, август 2025",
    "dj-rating": "4,7",
    "review__title": "Что нравится?",
    "review__title (2)": "Что можно улучшить?",
    "review__title-privileges": "Преимущества и льготы",
    "tags__item (3)": "Удобное расположение работы",
    "bt": "Полезный отзыв\n 2",
    "review__useful": "Полезный отзыв",
    "bt href": "https://dreamjob.ru/employers/302146?review_id=3924332",
    "bt (2)": "Ссылка на отзыв",
    "bt href (2)": "https://dreamjob.ru/page/employers",
    "bt (3)": "Ответить от лица компании",
    "tags__item (4)": "Удаленная работа",
    "tags__item (5)": "Наличие кухни, места для обеда",
    "tags__item (6)": "Гибкий рабочий график",
    "tags__item (7)": "Профессиональное обучение",
    "bt (4)": "Все 7",
    "tags__item (8)": "Система наставничества",
    "tags__item (9)": "Корпоративные мероприятия"
  },
  {
    "bt": "Посмотреть все зарплаты (7)",
    "bt href": "https://dreamjob.ru/employers/302146/zarplata",
    "job-vacancy__currency": "₽",
    "swiper-slide": "Посмотреть\nеще зарплаты"
  },
  {
    "review": "Менеджер по продажам недвижимости\n...\nРаботаю 1-2 года август 2025\n5,0\nЧто нравится?\nРабота в компании Homeapp стала для меня значимым шагом в карьере. Здесь активно инвестируют в обучение сотрудников: регулярно проводятся тренинги, разбираются сложные сделки, и есть доступ к удобной современной CRM-системе. Руководство действительно заботится о том, чтобы каждый сотрудник добивался успеха, предоставляя наставничество, помощь с юр. вопросами и маркетинг. Зарплата напрямую зависит от результатов работы, система выплат очень прозрачная, и при усердии можно зарабатывать больше, чем предлагает рынок. Отдельно + классному офису Москва Сити! Это супер!\nЧто можно улучшить?\nЕще больше корпоративных встреч, Это, единственное, что хотелось бы улучшить\nПреимущества и льготы\nСвоевременная оплата труда\nУдобное расположение работы\nНаличие кухни, места для обеда\nГибкий рабочий график\nПрофессиональное обучение\nМесто для парковки\nОплата мобильной связи\nСистема наставничества\nКорпоративные мероприятия\nВсе 9\nПолезный отзыв\n 1\nСсылка на отзыв\nОтветить от лица компании",
    "review__header-title": "Менеджер по продажам недвижимости",
    "share-block__item": "...",
    "tags__item": "Работаю 1-2 года",
    "tags__item (2)": "август 2025",
    "dj-rating": "5,0",
    "review__title": "Что нравится?",
    "review__title (2)": "Что можно улучшить?",
    "review__title-privileges": "Преимущества и льготы",
    "tags__item (3)": "Своевременная оплата труда",
    "bt": "Полезный отзыв\n 1",
    "review__useful": "Полезный отзыв",
    "bt href": "https://dreamjob.ru/employers/302146?review_id=3914896",
    "bt (2)": "Ссылка на отзыв",
    "bt href (2)": "https://dreamjob.ru/page/employers",
    "bt (3)": "Ответить от лица компании",
    "tags__item (4)": "Удобное расположение работы",
    "tags__item (5)": "Наличие кухни, места для обеда",
    "tags__item (6)": "Гибкий рабочий график",
    "tags__item (7)": "Профессиональное обучение",
    "bt (4)": "Все 9",
    "tags__item (8)": "Место для парковки",
    "tags__item (9)": "Оплата мобильной связи",
    "tags__item (10)": "Система наставничества"
  },
  {
    "review": "Менеджер по продажам\n...\nРаботаю 1-2 года Москва, июнь 2025\n4,7\nЧто нравится?\nХочется отметить отдельно формат обучения в компании. Если у Вас нет опыта, то всему научат и дадут максимально полное погружение в профессию. Всегда на связи руководитель, адаптолог, на любые вопросы ответят и помогут разобраться в сложных ситуациях.\n\nУдобный и красивый офис - работать одно удовольствие!\nВсе нравится, спасибо за такой подход к делу и сотрудникам.\nЧто можно улучшить?\nНет каких-либо комментариев. В офисе есть все ( в том числе кофе, печеньки, чай, кухня), что необходимо для продуктивной работы.\nПреимущества и льготы\nСвоевременная оплата труда\nУдобное расположение работы\nУдаленная работа\nНаличие кухни, места для обеда\nГибкий рабочий график\nПрофессиональное обучение\nСистема наставничества\nКорпоративные мероприятия\nВсе 8\nПолезный отзыв\n 2\nСсылка на отзыв\nОтветить от лица компании",
    "review__header-title": "Менеджер по продажам",
    "share-block__item": "...",
    "tags__item": "Работаю 1-2 года",
    "tags__item (2)": "Москва, июнь 2025",
    "dj-rating": "4,7",
    "review__title": "Что нравится?",
    "review__title (2)": "Что можно улучшить?",
    "review__title-privileges": "Преимущества и льготы",
    "tags__item (3)": "Своевременная оплата труда",
    "bt": "Полезный отзыв\n 2",
    "review__useful": "Полезный отзыв",
    "bt href": "https://dreamjob.ru/employers/302146?review_id=3802466",
    "bt (2)": "Ссылка на отзыв",
    "bt href (2)": "https://dreamjob.ru/page/employers",
    "bt (3)": "Ответить от лица компании",
    "tags__item (4)": "Удобное расположение работы",
    "tags__item (5)": "Удаленная работа",
    "tags__item (6)": "Наличие кухни, места для обеда",
    "tags__item (7)": "Гибкий рабочий график",
    "bt (4)": "Все 8",
    "tags__item (8)": "Профессиональное обучение",
    "tags__item (9)": "Система наставничества",
    "tags__item (10)": "Корпоративные мероприятия"
  }
]