[
  {
    "review": "Специалист по тендерам\n...\nРаботал меньше года Москва, октябрь 2024\n1,0\nЧто нравится?\nДанная компания ищет специалиста по тендерам в Госперевод. Сначала просят сделать наисложнейшие задания на английском и русском языке, у меня ушло 2,5 дня. Я сделала это задание без ошибок, и вообще мало знаю людей, ктобы такое сделал. Потом вызывают на собеседование в Госперевод на Павелецкой. Там крупная женщина, которая очень тихо говорит под нос и смотрит на вам пронизывающим оценивающим взглядом принимает решение, что вы не им не подходите. На мои попытки узнать по какой же причине моя кандидатура не подходит в ответ получила только молчание.\nЧто можно улучшить?\nКоммуникацию после собеседования\nПолезный отзыв\n 16\nСсылка на отзыв\nОтветить от лица компании",
    "review__header-title": "Специалист по тендерам",
    "tags__item (2)": "Москва, октябрь 2024",
    "dj-rating": "1,0",
    "bt": "Полезный отзыв\n 16",
    "bt href": "https://dreamjob.ru/employers/120981?review_id=3000060"
  },
  {
    "review": "Отзыв сотрудника\n...\nРаботал меньше года Москва, январь 2024\n1,8\nЧто нравится?\nУдалённый формат работы.\nРазные виды трудоустройства.\nСвоевременные выплаты\nЧто можно улучшить?\nМного нагрузки, за такую маленькую зп\nПосле увольнения не выплатили премию за проделанную работу, это оговаривалось заранее, но компания решила не придерживаться договоренностей\nПреимущества и льготы\nУдаленная работа\nПолезный отзыв\n 24\nСсылка на отзыв\nОтветить от лица компании",
    "review__header-title": "Отзыв сотрудника",
    "tags__item (2)": "Москва, январь 2024",
    "dj-rating": "1,8",
    "bt": "Полезный отзыв\n 24",
    "bt href": "https://dreamjob.ru/employers/120981?review_id=2263824",
    "review__title-privileges": "Преимущества и льготы",
    "tags__item (3)": "Удаленная работа"
  },
  {
    "review": "Отзыв сотрудника\n...\nРаботал меньше года Москва, сентябрь 2022\n1,7\nЧто нравится?\nДостаточно комфортная обстановка в команде (между несколькими отделами), приятное общение, интересные проекты, но их очень мало.\nЧто можно улучшить?\nМало интересных проектов, мало условий для комфортной работы в офисе, выстроенная связь с топ-менеджментом немного кривовата, текучка кадров, неудобные технологии, безынициативность руководителей, психологический прессинг.\nПреимущества и льготы\nСвоевременная оплата труда\nУдаленная работа\nНаличие кухни, места для обеда\nОплата больничного\nВсе 4\nПолезный отзыв\n 7\nСсылка на отзыв\nОтветить от лица компании",
    "review__header-title": "Отзыв сотрудника",
    "tags__item (2)": "Москва, сентябрь 2022",
    "dj-rating": "1,7",
    "bt": "Полезный отзыв\n 7",
    "bt href": "https://dreamjob.ru/employers/120981?review_id=1143638",
    "review__title-privileges": "Преимущества и льготы",
    "tags__item (3)": "Своевременная оплата труда"
  }
]