[
  {
    "review": "Буровой супервайзер\n...\nРаботаю 1-2 года Москва, февраль 2025\n1,5\nЧто нравится?\nПредоставление билетов до места работы и обратно за счет работодателя\nЧто можно улучшить?\nОчень низкий уровень заплаты, не производится индексация зарплаты как предусмотрено законодательством РФ. Отсутствует карьерный рост. Отношение руководства компании к сотрудникам на низком уровне.\nПреимущества и льготы\nСвоевременная оплата труда\nОплата транспортных расходов\nПолезный отзыв\n 4\nСсылка на отзыв\nОтветить от лица компании",
    "review__header-title": "Буровой супервайзер",
    "share-block__item": "...",
    "tags__item": "Работаю 1-2 года",
    "tags__item (2)": "Москва, февраль 2025",
    "dj-rating": "1,5",
    "review__title": "Что нравится?",
    "review__title (2)": "Что можно улучшить?",
    "review__title-privileges": "Преимущества и льготы",
    "tags__item (3)": "Своевременная оплата труда",
    "tags__item (4)": "Оплата транспортных расходов",
    "bt": "Полезный отзыв\n 4",
    "review__useful": "Полезный отзыв",
    "bt href": "https://dreamjob.ru/employers/287086?review_id=3404050",
    "bt (2)": "Ссылка на отзыв",
    "bt href (2)": "https://dreamjob.ru/page/employers",
    "bt (3)": "Ответить от лица компании"
  },
  {
    "vacancies-banner__inner": "Вакансии в Fersol",
    "vacancies-banner__all href": "https://dreamjob.ru/employers/287086/vakansii",
    "vacancies-banner__all": "Все\n 150",
    "d-md-block": "Все",
    "vacancies-banner__head": "Продюсер деловой программы (коммерческий транспорт)",
    "vacancies-banner__сity": "Москва",
    "vacancies-banner__salary": "от 160 000 ₽",
    "job-vacancy__currency": "₽",
    "bt-master href": "https://dreamjob.ru/employers/287086/vakansii/126889175",
    "bt-master": "Посмотреть вакансию",
    "vacancies-banner__head (2)": "Менеджер по маркетингу и рекламе",
    "bt-master href (2)": "https://dreamjob.ru/employers/287086/vakansii/126889123",
    "vacancies-banner__head (3)": "Главный специалист по телекому со знанием английского",
    "vacancies-banner__сity (3)": "Санкт-Петербург",
    "bt-master href (3)": "https://dreamjob.ru/employers/287086/vakansii/126888992",
    "vacancies-banner__head (4)": "Младший инженер ГТИ / Геофизик",
    "vacancies-banner__сity (4)": "Самара",
    "bt-master href (4)": "https://dreamjob.ru/employers/287086/vakansii/126887679",
    "vacancies-banner__head (5)": "Подсобный рабочий (производство)",
    "vacancies-banner__salary (3)": "90 000 - 90 000 ₽",
    "bt-master href (5)": "https://dreamjob.ru/employers/287086/vakansii/126886421"
  },
  {
    "review": "Слесарь механосборочных работ, бригадир участка\n...\nРаботал 1-2 года Москва, февраль 2024\n3,3\nЧто нравится?\nДмс, зарплата, спецодежда, лояльное отношение руководства, быстрая коммуникация с менеджерами в Москве.\nЧто можно улучшить?\nУровень зарплаты, расширить ДМС, увеличить надбавки за вредные условия и тд.\nПреимущества и льготы\nСвоевременная оплата труда\nНаличие кухни, места для обеда\nМедицинское страхование\nОплата больничного\nВсе 4\nПолезный отзыв\n 3\nСсылка на отзыв\nОтветить от лица компании",
    "review__header-title": "Слесарь механосборочных работ, бригадир участка",
    "share-block__item": "...",
    "tags__item": "Работал 1-2 года",
    "tags__item (2)": "Москва, февраль 2024",
    "dj-rating": "3,3",
    "review__title": "Что нравится?",
    "review__title (2)": "Что можно улучшить?",
    "review__title-privileges": "Преимущества и льготы",
    "tags__item (3)": "Своевременная оплата труда",
    "tags__item (4)": "Наличие кухни, места для обеда",
    "bt": "Полезный отзыв\n 3",
    "review__useful": "Полезный отзыв",
    "bt href": "https://dreamjob.ru/employers/287086?review_id=2373089",
    "bt (2)": "Ссылка на отзыв",
    "bt href (2)": "https://dreamjob.ru/page/employers",
    "bt (3)": "Ответить от лица компании",
    "tags__item (5)": "Медицинское страхование",
    "tags__item (6)": "Оплата больничного",
    "bt (4)": "Все 4"
  },
  {
    "review": "HR-специалист\n...\nРаботал 1-2 года Москва, июль 2022\n3,8\nЧто нравится?\nРаботодатель вполне адекватный и лояльный. Зарплаты средние по рынку - это то, что касается back-office. На ключевых позициях доход выше, но зависит от выполнения KPI, которые вполне себе реальные. Поэтому те, кто хотят работать и зарабатывать в этой компании вполне смогут это делать. Есть медицинская страховка, 2 недели больничного в год оплачивается до 100%. Можно приходить чуть позже и задерживаться на столько на сколько опоздал, никто тебя этим попрекать не будет. Главное - чтобы работу свою выполнял в срок.\nЧто можно улучшить?\nВ принципе нормальный работодатель, занимает свою нишу. Есть конечно нюансы по коллективу, но они есть во всех компаниях.\nОтвет представителя компании\nАвгуст 2025\nДобрый день! Спасибо за подробный отзыв. Мы очень рады, что вам было комфортно работать в нашей команде. Желаем вам профессионального успеха и новых карьерных высот!\nПреимущества и льготы\nСвоевременная оплата труда\nНаличие кухни, места для обеда\nМедицинское страхование\nОплата больничного\nГибкий рабочий график\nОплата мобильной связи\nКорпоративные мероприятия\nВсе 7\nПолезный отзыв\n 3\nСсылка на отзыв",
    "review__header-title": "HR-специалист",
    "share-block__item": "...",
    "tags__item": "Работал 1-2 года",
    "tags__item (2)": "Москва, июль 2022",
    "dj-rating": "3,8",
    "review__title": "Что нравится?",
    "review__title (2)": "Что можно улучшить?",
    "review__title-privileges": "Преимущества и льготы",
    "tags__item (3)": "Своевременная оплата труда",
    "tags__item (4)": "Наличие кухни, места для обеда",
    "bt": "Полезный отзыв\n 3",
    "review__useful": "Полезный отзыв",
    "bt href": "https://dreamjob.ru/employers/287086?review_id=1020091",
    "bt (2)": "Ссылка на отзыв",
    "tags__item (5)": "Медицинское страхование",
    "tags__item (6)": "Оплата больничного",
    "bt (4)": "Все 7",
    "tags__item (7)": "Гибкий рабочий график",
    "tags__item (8)": "Оплата мобильной связи",
    "tags__item (9)": "Корпоративные мероприятия"
  },
  {
    "vacancies-banner__inner": "Вакансии в Fersol",
    "vacancies-banner__all href": "https://dreamjob.ru/employers/287086/vakansii",
    "vacancies-banner__all": "Все\n 150",
    "d-md-block": "Все",
    "vacancies-banner__head": "Продюсер деловой программы (коммерческий транспорт)",
    "vacancies-banner__сity": "Москва",
    "vacancies-banner__salary": "от 160 000 ₽",
    "job-vacancy__currency": "₽",
    "bt-master href": "https://dreamjob.ru/employers/287086/vakansii/126889175",
    "bt-master": "Посмотреть вакансию",
    "vacancies-banner__head (2)": "Менеджер по маркетингу и рекламе",
    "bt-master href (2)": "https://dreamjob.ru/employers/287086/vakansii/126889123",
    "vacancies-banner__head (3)": "Главный специалист по телекому со знанием английского",
    "vacancies-banner__сity (3)": "Санкт-Петербург",
    "bt-master href (3)": "https://dreamjob.ru/employers/287086/vakansii/126888992",
    "vacancies-banner__head (4)": "Младший инженер ГТИ / Геофизик",
    "vacancies-banner__сity (4)": "Самара",
    "bt-master href (4)": "https://dreamjob.ru/employers/287086/vakansii/126887679",
    "vacancies-banner__head (5)": "Подсобный рабочий (производство)",
    "vacancies-banner__salary (3)": "90 000 - 90 000 ₽",
    "bt-master href (5)": "https://dreamjob.ru/employers/287086/vakansii/126886421"
  },
  {
    "review": "Отзыв сотрудника\n...\nРаботал 1-2 года Москва, июнь 2022\n3,8\nЧто нравится?\nОтличное руководство, «семейность» компании, тренинги и корпоративные мероприятия. Гибридный график, современный офис и оборудование, возможность обучения в процессе работы. Выплаты ЗП, премий, начислений - вовремя. ДМС программа.\nЧто можно улучшить?\nВозможности роста (профессионального и финансового), ЗП ниже рынка.\nПреимущества и льготы\nСвоевременная оплата труда\nУдобное расположение работы\nУдаленная работа\nНаличие кухни, места для обеда\nМедицинское страхование\nОплата больничного\nПрофессиональное обучение\nСистема наставничества\nКорпоративные мероприятия\nВсе 9\nПолезный отзыв\n 2\nСсылка на отзыв\nОтветить от лица компании",
    "review__header-title": "Отзыв сотрудника",
    "share-block__item": "...",
    "tags__item": "Работал 1-2 года",
    "tags__item (2)": "Москва, июнь 2022",
    "dj-rating": "3,8",
    "review__title": "Что нравится?",
    "review__title (2)": "Что можно улучшить?",
    "review__title-privileges": "Преимущества и льготы",
    "tags__item (3)": "Своевременная оплата труда",
    "tags__item (4)": "Удобное расположение работы",
    "bt": "Полезный отзыв\n 2",
    "review__useful": "Полезный отзыв",
    "bt href": "https://dreamjob.ru/employers/287086?review_id=978886",
    "bt (2)": "Ссылка на отзыв",
    "bt href (2)": "https://dreamjob.ru/page/employers",
    "bt (3)": "Ответить от лица компании",
    "tags__item (5)": "Удаленная работа",
    "tags__item (6)": "Наличие кухни, места для обеда",
    "bt (4)": "Все 9",
    "tags__item (7)": "Медицинское страхование",
    "tags__item (8)": "Оплата больничного",
    "tags__item (9)": "Профессиональное обучение"
  },
  {
    "review": "Отзыв сотрудника\n...\nРаботаю 1-2 года Москва, май 2022\n2,5\nЧто нравится?\nГибкий график, своевременная оплата труда, дмс, оплата больничных, связь\nЧто можно улучшить?\nРуководство, руководство и ещё раз руководство\nПреимущества и льготы\nСвоевременная оплата труда\nУдаленная работа\nНаличие кухни, места для обеда\nМедицинское страхование\nОплата больничного\nГибкий рабочий график\nОплата мобильной связи\nВсе 7\nПолезный отзыв\n 3\nСсылка на отзыв\nОтветить от лица компании",
    "review__header-title": "Отзыв сотрудника",
    "share-block__item": "...",
    "tags__item": "Работаю 1-2 года",
    "tags__item (2)": "Москва, май 2022",
    "dj-rating": "2,5",
    "review__title": "Что нравится?",
    "review__title (2)": "Что можно улучшить?",
    "review__title-privileges": "Преимущества и льготы",
    "tags__item (3)": "Своевременная оплата труда",
    "tags__item (4)": "Удаленная работа",
    "bt": "Полезный отзыв\n 3",
    "review__useful": "Полезный отзыв",
    "bt href": "https://dreamjob.ru/employers/287086?review_id=913018",
    "bt (2)": "Ссылка на отзыв",
    "bt href (2)": "https://dreamjob.ru/page/employers",
    "bt (3)": "Ответить от лица компании",
    "tags__item (5)": "Наличие кухни, места для обеда",
    "tags__item (6)": "Медицинское страхование",
    "bt (4)": "Все 7",
    "tags__item (7)": "Оплата больничного",
    "tags__item (8)": "Гибкий рабочий график",
    "tags__item (9)": "Оплата мобильной связи"
  }
]