[
  {
    "review": "IT Analyst\n...\nРаботал 5-10 лет Москва, август 2025\n2,7\nЧто нравится?\nСовременные условия труда\nРазвитая внутренняя коммуникация\nУдобные рабочие инструменты\nСвоевременная оплата труда\nСтоловая на территории работодателя\nОплата питания\nДоступ к брендовому магазину с большим дисконтом\nЧто можно улучшить?\n- Огромная бюрократия и этапы согласований. Из года в год таких операций и процессов становится только больше\n- Самый явный, фиктивные отборы кандидатов. Как правило проходят только заранее подготовленные кандидаты, остальные персоны необходимы только для запуска процедуры \"ассесмент\". Доходит до абсурда, что тебе даже не сообщают обратную связь, хотя бы о том, что необходимо \"подтянуть\".\n- переход на CRM системы не адаптированные под IT работу\n- отношения к подрядным организациям. Отдельная ветка в истории. С каждым годом история взаимодействия только ухудшается и подрядные организации часто становятся виновниками некомпетентного управления сотрудниками компании Марс.\n- отсутствие it льгот, так уак организация не является it аккредиованной\nОтвет представителя компании\nАвгуст 2025\nДобрый день!\n\nБлагодарим Вас за оставленный отзыв!\nМы очень рады, что вы были частью нашей команды!\n\nДля нас очень ценно, что Вы отразили различные факторы, влияющие на Вашу карьеру в нашей компании.\n\nМы будем признательны, если Вы поделитесь с нами более подробной обратной связью по описанным зонам к улучшению по электронной почте Talent.Team@mars.effem.com.\n\nС уважением,\nКоманда по привлечению и подбору персонала Mars\nПреимущества и льготы\nСвоевременная оплата труда\nНаличие кухни, места для обеда\nМедицинское страхование\nОплата больничного\nКомпенсация питания\nМесто для парковки\nКорпоративные мероприятия\nВсе 7\nПолезный отзыв\n 3\nСсылка на отзыв",
    "review__header-title": "IT Analyst",
    "share-block__item": "...",
    "tags__item": "Работал 5-10 лет",
    "tags__item (2)": "Москва, август 2025",
    "dj-rating": "2,7",
    "review__title": "Что нравится?",
    "review__title (2)": "Что можно улучшить?",
    "review__answer": "Ответ представителя компании\nАвгуст 2025\nДобрый день!\n\nБлагодарим Вас за оставленный отзыв!\nМы очень рады, что вы были частью нашей команды!\n\nДля нас очень ценно, что Вы отразили различные факторы, влияющие на Вашу карьеру в нашей компании.\n\nМы будем признательны, если Вы поделитесь с нами более подробной обратной связью по описанным зонам к улучшению по электронной почте Talent.Team@mars.effem.com.\n\nС уважением,\nКоманда по привлечению и подбору персонала Mars",
    "review__answer-title": "Ответ представителя компании",
    "review__answer-date": "Август 2025",
    "review__title-privileges": "Преимущества и льготы",
    "tags__item (3)": "Своевременная оплата труда",
    "tags__item (4)": "Наличие кухни, места для обеда",
    "tags__item (5)": "Медицинское страхование",
    "tags__item (6)": "Оплата больничного",
    "tags__item (7)": "Компенсация питания",
    "tags__item (8)": "Место для парковки",
    "tags__item (9)": "Корпоративные мероприятия",
    "bt": "Все 7",
    "bt (2)": "Полезный отзыв\n 3",
    "review__useful": "Полезный отзыв",
    "bt href": "https://dreamjob.ru/employers/26064?review_id=3963657",
    "bt (3)": "Ссылка на отзыв"
  },
  {
    "vacancies-banner__inner": "Вакансии в Марс",
    "vacancies-banner__all href": "https://dreamjob.ru/employers/26064/vakansii",
    "vacancies-banner__all": "Все\n 201",
    "d-md-none": "Все",
    "vacancies-banner__head": "Начальник смены",
    "vacancies-banner__сity": "Ульяновск",
    "bt-master href": "https://dreamjob.ru/employers/26064/vakansii/125687658",
    "bt-master": "Посмотреть вакансию",
    "vacancies-banner__head (2)": "Эксперт по научным коммуникациям по работе с ключевыми клиентами/NA Scientific Communications Expert",
    "vacancies-banner__сity (2)": "Санкт-Петербург",
    "bt-master href (2)": "https://dreamjob.ru/employers/26064/vakansii/126887912",
    "vacancies-banner__head (3)": "Младший руководитель производственного участка (Supply)",
    "vacancies-banner__сity (3)": "Москва",
    "vacancies-banner__salary": "до 170 000 ₽",
    "job-vacancy__currency": "₽",
    "bt-master href (3)": "https://dreamjob.ru/employers/26064/vakansii/123476034",
    "vacancies-banner__head (4)": "Оператор производственной линии",
    "vacancies-banner__сity (4)": "Ростов-на-Дону",
    "vacancies-banner__salary (2)": "от 106 000 ₽",
    "bt-master href (4)": "https://dreamjob.ru/employers/26064/vakansii/105121306",
    "vacancies-banner__head (5)": "Инженер-электромеханик/Manufacturing Technician",
    "vacancies-banner__salary (3)": "от 160 000 ₽",
    "bt-master href (5)": "https://dreamjob.ru/employers/26064/vakansii/121534068"
  },
  {
    "review": "Специалист линии упак‎овки\n...\nРаботал меньше года Москва, июнь 2025\n1,2\nЧто нравится?\nХорошее производство.\nИнтересно изучать все процессы,не посредственно принимая в них участие.\nВ комнате отдыха было массажное кресло.\nЧто можно улучшить?\nВсе делается для того что бы руководство-росло,а остальной персонал оставался на своем месте.\nНизкая оплата труда+ночные смены.\nВсе кто заинтересован в росте и развитие,на долго не задерживались.\nНе тратьте свое время,не советую.\nОтвет представителя компании\nИюнь 2025\nДобрый день!\n\nБлагодарим Вас за оставленный отзыв!\nМы рады, что были частью нашей команды!\n\nДля нас очень ценно, что Вы отразили различные факторы, влияющие на Вашу карьеру в нашей компании.\n\nТакже для нас очень важно, что Вами отмечены и те области, которые помогут нам как работодателю улучшать текущие процессы. При этом сотрудники компании всегда могут обратиться напрямую в отдел персонала и обсудить необходимые изменения или предложения. Также всегда есть возможность поделиться с нами более подробной обратной связью по электронной почте Talent.Team@mars.effem.com.\n\nЖелаем Вам успехов!\n\nС уважением,\nКоманда по привлечению и подбору персонала Mars\nПреимущества и льготы\nСвоевременная оплата труда\nМесто для парковки\nПолезный отзыв\n 3\nСсылка на отзыв",
    "review__header-title": "Специалист линии упак‎овки",
    "share-block__item": "...",
    "tags__item": "Работал меньше года",
    "tags__item (2)": "Москва, июнь 2025",
    "dj-rating": "1,2",
    "review__title": "Что нравится?",
    "review__title (2)": "Что можно улучшить?",
    "review__answer": "Ответ представителя компании\nИюнь 2025\nДобрый день!\n\nБлагодарим Вас за оставленный отзыв!\nМы рады, что были частью нашей команды!\n\nДля нас очень ценно, что Вы отразили различные факторы, влияющие на Вашу карьеру в нашей компании.\n\nТакже для нас очень важно, что Вами отмечены и те области, которые помогут нам как работодателю улучшать текущие процессы. При этом сотрудники компании всегда могут обратиться напрямую в отдел персонала и обсудить необходимые изменения или предложения. Также всегда есть возможность поделиться с нами более подробной обратной связью по электронной почте Talent.Team@mars.effem.com.\n\nЖелаем Вам успехов!\n\nС уважением,\nКоманда по привлечению и подбору персонала Mars",
    "review__answer-title": "Ответ представителя компании",
    "review__answer-date": "Июнь 2025",
    "review__title-privileges": "Преимущества и льготы",
    "tags__item (3)": "Своевременная оплата труда",
    "tags__item (4)": "Место для парковки",
    "bt (2)": "Полезный отзыв\n 3",
    "review__useful": "Полезный отзыв",
    "bt href": "https://dreamjob.ru/employers/26064?review_id=3755970",
    "bt (3)": "Ссылка на отзыв"
  },
  {
    "review": "Vendor Cyber security lead\n...\nРаботаю 1-2 года Москва, май 2025\n2,2\nЧто нравится?\nБренд. Говорят зп выше по рынку. Существует некий кодекс взаимоотношений (все о нем слышали, но никто точно не знает что там)\nЧто можно улучшить?\nКоммуникации нет. Никакой. Иногда узнаешь от сотрудников других отделов, что в другом (3-м) отделе работают над таким же проектом.\nОтвет представителя компании\nИюнь 2025\nДобрый день!\n\nБлагодарим Вас за оставленный отзыв!\nМы очень рады, что вы являетесь частью нашей команды!\n\nДля нас очень ценно, что Вы отразили различные факторы, влияющие на Вашу карьеру в нашей компании.\n\nТакже для нас очень важно, что Вами отмечены и те области, которые помогут нам как работодателю улучшать текущие процессы. При этом сотрудники компании всегда могут обратиться напрямую в отдел персонала и обсудить необходимые изменения или предложения. Также Вы можете поделиться с нами более подробной обратной связью по электронной почте Talent.Team@mars.effem.com.\n\nЖелаем Вам успехов!\n\nС уважением,\nКоманда по привлечению и подбору персонала Mars\nПреимущества и льготы\nСвоевременная оплата труда\nУдобное расположение работы\nУдаленная работа\nНаличие кухни, места для обеда\nМедицинское страхование\nВсе 5\nПолезный отзыв\n 0\nСсылка на отзыв",
    "review__header-title": "Vendor Cyber security lead",
    "share-block__item": "...",
    "tags__item": "Работаю 1-2 года",
    "tags__item (2)": "Москва, май 2025",
    "dj-rating": "2,2",
    "review__title": "Что нравится?",
    "review__title (2)": "Что можно улучшить?",
    "review__answer": "Ответ представителя компании\nИюнь 2025\nДобрый день!\n\nБлагодарим Вас за оставленный отзыв!\nМы очень рады, что вы являетесь частью нашей команды!\n\nДля нас очень ценно, что Вы отразили различные факторы, влияющие на Вашу карьеру в нашей компании.\n\nТакже для нас очень важно, что Вами отмечены и те области, которые помогут нам как работодателю улучшать текущие процессы. При этом сотрудники компании всегда могут обратиться напрямую в отдел персонала и обсудить необходимые изменения или предложения. Также Вы можете поделиться с нами более подробной обратной связью по электронной почте Talent.Team@mars.effem.com.\n\nЖелаем Вам успехов!\n\nС уважением,\nКоманда по привлечению и подбору персонала Mars",
    "review__answer-title": "Ответ представителя компании",
    "review__answer-date": "Июнь 2025",
    "review__title-privileges": "Преимущества и льготы",
    "tags__item (3)": "Своевременная оплата труда",
    "tags__item (4)": "Удобное расположение работы",
    "tags__item (5)": "Удаленная работа",
    "tags__item (6)": "Наличие кухни, места для обеда",
    "tags__item (7)": "Медицинское страхование",
    "bt": "Все 5",
    "bt (2)": "Полезный отзыв\n 0",
    "review__useful": "Полезный отзыв",
    "bt href": "https://dreamjob.ru/employers/26064?review_id=3702020",
    "bt (3)": "Ссылка на отзыв"
  },
  {
    "vacancies-banner__inner": "Вакансии в Марс",
    "vacancies-banner__all href": "https://dreamjob.ru/employers/26064/vakansii",
    "vacancies-banner__all": "Все\n 201",
    "d-md-none": "Все",
    "vacancies-banner__head": "Начальник смены",
    "vacancies-banner__сity": "Ульяновск",
    "bt-master href": "https://dreamjob.ru/employers/26064/vakansii/125687658",
    "bt-master": "Посмотреть вакансию",
    "vacancies-banner__head (2)": "Эксперт по научным коммуникациям по работе с ключевыми клиентами/NA Scientific Communications Expert",
    "vacancies-banner__сity (2)": "Санкт-Петербург",
    "bt-master href (2)": "https://dreamjob.ru/employers/26064/vakansii/126887912",
    "vacancies-banner__head (3)": "Младший руководитель производственного участка (Supply)",
    "vacancies-banner__сity (3)": "Москва",
    "vacancies-banner__salary": "до 170 000 ₽",
    "job-vacancy__currency": "₽",
    "bt-master href (3)": "https://dreamjob.ru/employers/26064/vakansii/123476034",
    "vacancies-banner__head (4)": "Оператор производственной линии",
    "vacancies-banner__сity (4)": "Ростов-на-Дону",
    "vacancies-banner__salary (2)": "от 106 000 ₽",
    "bt-master href (4)": "https://dreamjob.ru/employers/26064/vakansii/105121306",
    "vacancies-banner__head (5)": "Инженер-электромеханик/Manufacturing Technician",
    "vacancies-banner__salary (3)": "от 160 000 ₽",
    "bt-master href (5)": "https://dreamjob.ru/employers/26064/vakansii/121534068"
  },
  {
    "review": "Маркетолог\n...\nРаботал меньше года Москва, апрель 2025\n1,3\nЧто нравится?\nвысокая заработная плата, дмс, глобальный масштаб работы, практика английского\nЧто можно улучшить?\nдеспотизм, произвол, прессинг, эмоциональное давление, переработки\nОтвет представителя компании\nИюнь 2025\nДобрый день!\n\nБлагодарим Вас за оставленный отзыв!\nМы очень рады, что вы были частью нашей команды!\n\nДля нас очень ценно, что Вы отразили различные факторы, влияющие на Вашу карьеру в нашей компании.\n\nМы будем признательны, если Вы поделитесь с нами более подробной обратной связью по описанным зонам к улучшению по электронной почте Talent.Team@mars.effem.com.\n\nС уважением,\nКоманда по привлечению и подбору персонала Mars\nПреимущества и льготы\nСвоевременная оплата труда\nМедицинское страхование\nПолезный отзыв\n 3\nСсылка на отзыв",
    "review__header-title": "Маркетолог",
    "share-block__item": "...",
    "tags__item": "Работал меньше года",
    "tags__item (2)": "Москва, апрель 2025",
    "dj-rating": "1,3",
    "review__title": "Что нравится?",
    "review__title (2)": "Что можно улучшить?",
    "review__answer": "Ответ представителя компании\nИюнь 2025\nДобрый день!\n\nБлагодарим Вас за оставленный отзыв!\nМы очень рады, что вы были частью нашей команды!\n\nДля нас очень ценно, что Вы отразили различные факторы, влияющие на Вашу карьеру в нашей компании.\n\nМы будем признательны, если Вы поделитесь с нами более подробной обратной связью по описанным зонам к улучшению по электронной почте Talent.Team@mars.effem.com.\n\nС уважением,\nКоманда по привлечению и подбору персонала Mars",
    "review__answer-title": "Ответ представителя компании",
    "review__answer-date": "Июнь 2025",
    "review__title-privileges": "Преимущества и льготы",
    "tags__item (3)": "Своевременная оплата труда",
    "tags__item (4)": "Медицинское страхование",
    "bt (2)": "Полезный отзыв\n 3",
    "review__useful": "Полезный отзыв",
    "bt href": "https://dreamjob.ru/employers/26064?review_id=3636638",
    "bt (3)": "Ссылка на отзыв"
  },
  {
    "review": "Директор по информационной безопасности\n...\nРаботаю 1-2 года Москва, январь 2025\n1,5\nЧто нравится?\nHybrid work, flexible work hours, comfort office space and workplaces\nЧто можно улучшить?\nToo much unnecessary meetings, religious connection with US main office\nОтвет представителя компании\nФевраль 2025\nДобрый день!\n\nБлагодарим Вас за оставленный отзыв!\nМы очень рады, что вы являетесь частью нашей команды!\n\nДля нас очень ценно, что Вы отразили различные факторы, влияющие на Вашу карьеру в нашей компании.\n\nТакже для нас очень важно, что Вами отмечены и те области, которые помогут нам как работодателю улучшать текущие процессы. При этом сотрудники компании всегда могут обратиться напрямую в отдел персонала и обсудить необходимые изменения или предложения. Также Вы можете поделиться с нами более подробной обратной связью по электронной почте Talent.Team@mars.effem.com.\n\nЖелаем Вам и всяческих успехов!\n\nС уважением,\nКоманда по привлечению и подбору персонала Mars\nПреимущества и льготы\nСвоевременная оплата труда\nУдобное расположение работы\nУдаленная работа\nНаличие кухни, места для обеда\nМедицинское страхование\nОплата больничного\nГибкий рабочий график\nКомпенсация питания\nОплата транспортных расходов\nПрофессиональное обучение\nМесто для парковки\nОплата мобильной связи\nСистема наставничества\nКорпоративные мероприятия\nВсе 14\nПолезный отзыв\n 3\nСсылка на отзыв",
    "review__header-title": "Директор по информационной безопасности",
    "share-block__item": "...",
    "tags__item": "Работаю 1-2 года",
    "tags__item (2)": "Москва, январь 2025",
    "dj-rating": "1,5",
    "review__title": "Что нравится?",
    "review__title (2)": "Что можно улучшить?",
    "review__answer": "Ответ представителя компании\nФевраль 2025\nДобрый день!\n\nБлагодарим Вас за оставленный отзыв!\nМы очень рады, что вы являетесь частью нашей команды!\n\nДля нас очень ценно, что Вы отразили различные факторы, влияющие на Вашу карьеру в нашей компании.\n\nТакже для нас очень важно, что Вами отмечены и те области, которые помогут нам как работодателю улучшать текущие процессы. При этом сотрудники компании всегда могут обратиться напрямую в отдел персонала и обсудить необходимые изменения или предложения. Также Вы можете поделиться с нами более подробной обратной связью по электронной почте Talent.Team@mars.effem.com.\n\nЖелаем Вам и всяческих успехов!\n\nС уважением,\nКоманда по привлечению и подбору персонала Mars",
    "review__answer-title": "Ответ представителя компании",
    "review__answer-date": "Февраль 2025",
    "review__title-privileges": "Преимущества и льготы",
    "tags__item (3)": "Своевременная оплата труда",
    "tags__item (4)": "Удобное расположение работы",
    "tags__item (5)": "Удаленная работа",
    "tags__item (6)": "Наличие кухни, места для обеда",
    "tags__item (7)": "Медицинское страхование",
    "tags__item (8)": "Оплата больничного",
    "tags__item (9)": "Гибкий рабочий график",
    "bt": "Все 14",
    "bt (2)": "Полезный отзыв\n 3",
    "review__useful": "Полезный отзыв",
    "bt href": "https://dreamjob.ru/employers/26064?review_id=3278691",
    "bt (3)": "Ссылка на отзыв"
  },
  {
    "review": "Senior ML Engineer\n...\nРаботал меньше года Москва, сентябрь 2024\n2,5\nЧто нравится?\nВозможность удаленной работы, крупная компания, уровень дохода соответствует рынку\nЧто можно улучшить?\nПрежде всего здесь стоит бизнес и задачи бизнеса. Приходится часто перерабатывать, чтобы успевать закрывать никогда не прекращающийся поток задач.\nОтвет представителя компании\nОктябрь 2024\nДобрый день!\nБлагодарим Вас за оставленный отзыв!\n\nДля нас очень важно мнение каждого сотрудника, и мы верим, что конструктивный диалог и обратная связь всегда способствуют нашему дальнейшему развитию и улучшению текущих процессов.\n\nВ связи с этим, хотим заверить, что эффективная командная работа, мастерство линейных руководителей и этика профессионального взаимодействия – ключевые ценности и фокус внимания руководства и всех сотрудников компании Марс.\n\nВ данной и аналогичных ситуациях для своевременного разрешения любых ситуаций, мы приглашаем к открытому обсуждению всех обстоятельств с непосредственным руководителем, а также, если ситуацию не удается урегулировать самостоятельно, обратиться в отдел по работе с персоналом с целью ее разрешения. Также в компании действует программа Омбудсмена, где Омбудсмен - это независимый сотрудник, сохраняющий нейтралитет для беспристрастного обсуждения сложных ситуаций и выработки взаимовыгодных решений. Наши сотрудники в любой ситуации могут обратиться к омбудсмену, который их выслушает в неформальной обстановке, даст обратную связь по тем вопросам, которые его беспокоят.\n\nЕсли у Вас остались дополнительные вопросы – мы готовы на них ответить и оперативно помочь. Для этого свяжитесь с нами, пожалуйста, по электронной почте Talent.Team@mars.effem.com.\n\nЖелаем Вам успехов!\n\nС уважением,\nКоманда по привлечению и подбору персонала Mars\nПреимущества и льготы\nСвоевременная оплата труда\nУдаленная работа\nНаличие кухни, места для обеда\nМедицинское страхование\nВсе 4\nПолезный отзыв\n 2\nСсылка на отзыв",
    "review__header-title": "Senior ML Engineer",
    "share-block__item": "...",
    "tags__item": "Работал меньше года",
    "tags__item (2)": "Москва, сентябрь 2024",
    "dj-rating": "2,5",
    "review__title": "Что нравится?",
    "review__title (2)": "Что можно улучшить?",
    "review__answer": "Ответ представителя компании\nОктябрь 2024\nДобрый день!\nБлагодарим Вас за оставленный отзыв!\n\nДля нас очень важно мнение каждого сотрудника, и мы верим, что конструктивный диалог и обратная связь всегда способствуют нашему дальнейшему развитию и улучшению текущих процессов.\n\nВ связи с этим, хотим заверить, что эффективная командная работа, мастерство линейных руководителей и этика профессионального взаимодействия – ключевые ценности и фокус внимания руководства и всех сотрудников компании Марс.\n\nВ данной и аналогичных ситуациях для своевременного разрешения любых ситуаций, мы приглашаем к открытому обсуждению всех обстоятельств с непосредственным руководителем, а также, если ситуацию не удается урегулировать самостоятельно, обратиться в отдел по работе с персоналом с целью ее разрешения. Также в компании действует программа Омбудсмена, где Омбудсмен - это независимый сотрудник, сохраняющий нейтралитет для беспристрастного обсуждения сложных ситуаций и выработки взаимовыгодных решений. Наши сотрудники в любой ситуации могут обратиться к омбудсмену, который их выслушает в неформальной обстановке, даст обратную связь по тем вопросам, которые его беспокоят.\n\nЕсли у Вас остались дополнительные вопросы – мы готовы на них ответить и оперативно помочь. Для этого свяжитесь с нами, пожалуйста, по электронной почте Talent.Team@mars.effem.com.\n\nЖелаем Вам успехов!\n\nС уважением,\nКоманда по привлечению и подбору персонала Mars",
    "review__answer-title": "Ответ представителя компании",
    "review__answer-date": "Октябрь 2024",
    "review__title-privileges": "Преимущества и льготы",
    "tags__item (3)": "Своевременная оплата труда",
    "tags__item (4)": "Удаленная работа",
    "tags__item (5)": "Наличие кухни, места для обеда",
    "tags__item (6)": "Медицинское страхование",
    "bt": "Все 4",
    "bt (2)": "Полезный отзыв\n 2",
    "review__useful": "Полезный отзыв",
    "bt href": "https://dreamjob.ru/employers/26064?review_id=2963098",
    "bt (3)": "Ссылка на отзыв"
  },
  {
    "review": "Укладчик\n...\nРаботаю меньше года Москва, июнь 2024\n2,0\nЧто нравится?\nНичего мне не нравится в этом работодателе. Хорошо что я ушла.\nЧто можно улучшить?\nЗаработную плату, возможности для карьерного роста и побольше времени на отдых\nОтвет представителя компании\nАвгуст 2024\nДобрый день!\n\nБлагодарим Вас за оставленный отзыв и уделенное время!\n\nМы очень рады, что Вы являетесь и частью нашей команды.\n\nДля нас очень ценно, что в своем отзыве Вы учли различные факторы, влияющие на Ваш опыт работы в нашей компании.\n\nВажно отметить, что сотрудники компании всегда могут обратиться напрямую в отдел персонала и обсудить необходимые изменения и предложения, которые помогут нам как работодателю улучшать внутренние процессы.\n\nЕсли у Вас остались дополнительные вопросы, или Вы готовы поделиться более подробной обратной связью, мы будем рады оперативно ответить и помочь. Для этого свяжитесь с нами, пожалуйста, по электронной почте Talent.Team@mars.effem.com.\n\nЖелаем Вам и дальнейших успехов!\n\nС уважением,\nКоманда по привлечению и подбору персонала Mars\nПреимущества и льготы\nКомпенсация питания\nКорпоративный транспорт\nПолезный отзыв\n 1\nСсылка на отзыв",
    "review__header-title": "Укладчик",
    "share-block__item": "...",
    "tags__item": "Работаю меньше года",
    "tags__item (2)": "Москва, июнь 2024",
    "dj-rating": "2,0",
    "review__title": "Что нравится?",
    "review__title (2)": "Что можно улучшить?",
    "review__answer": "Ответ представителя компании\nАвгуст 2024\nДобрый день!\n\nБлагодарим Вас за оставленный отзыв и уделенное время!\n\nМы очень рады, что Вы являетесь и частью нашей команды.\n\nДля нас очень ценно, что в своем отзыве Вы учли различные факторы, влияющие на Ваш опыт работы в нашей компании.\n\nВажно отметить, что сотрудники компании всегда могут обратиться напрямую в отдел персонала и обсудить необходимые изменения и предложения, которые помогут нам как работодателю улучшать внутренние процессы.\n\nЕсли у Вас остались дополнительные вопросы, или Вы готовы поделиться более подробной обратной связью, мы будем рады оперативно ответить и помочь. Для этого свяжитесь с нами, пожалуйста, по электронной почте Talent.Team@mars.effem.com.\n\nЖелаем Вам и дальнейших успехов!\n\nС уважением,\nКоманда по привлечению и подбору персонала Mars",
    "review__answer-title": "Ответ представителя компании",
    "review__answer-date": "Август 2024",
    "review__title-privileges": "Преимущества и льготы",
    "tags__item (3)": "Компенсация питания",
    "tags__item (4)": "Корпоративный транспорт",
    "bt (2)": "Полезный отзыв\n 1",
    "review__useful": "Полезный отзыв",
    "bt href": "https://dreamjob.ru/employers/26064?review_id=2656944",
    "bt (3)": "Ссылка на отзыв"
  },
  {
    "review": "Отзыв сотрудника\n...\nРаботал 3-5 лет Москва, декабрь 2023\n2,0\nЧто нравится?\nГибкий график, шоколад в офисе, уютный офис, локация, питомцы\nЧто можно улучшить?\nОтсутствие перспектив для роста в компании, неактуальные навыки, бюрократия, слишком много времени уходит на согласования вместо продуктивной работы.\nОтвет представителя компании\nФевраль 2024\nДобрый день!\n\nБлагодарим Вас за подробный отзыв и уделенное время!\nМы очень рады, что Вы были частью нашей команды.\n\nДля нас очень ценно, что в своем отзыве Вы отразили различные факторы, влияющие на Вашу карьеру в нашей компании.\n\nТакже для нас очень важно, что Вами отмечены и те области, которые помогут нам как работодателю улучшать текущие процессы. На данный момент в компании уже действует программа Омбудсмена, где Омбудсмен - это независимый сотрудник, сохраняющий нейтралитет для беспристрастного обсуждения сложных ситуаций и выработки взаимовыгодных решений. Наши сотрудники в любой ситуации могут обратиться к омбудсмену, который их выслушает в неформальной обстановке, даст обратную связь по тем вопросам, которые его беспокоят. Также сотрудники компании всегда могут обратиться напрямую в отдел персонала и обсудить необходимые изменения или предложения.\n\nЖелаем Вам и дальнейших успехов!\n\nС уважением,\nКоманда по привлечению и подбору персонала Mars\nПреимущества и льготы\nСвоевременная оплата труда\nУдаленная работа\nНаличие кухни, места для обеда\nМедицинское страхование\nОплата больничного\nГибкий рабочий график\nКомпенсация питания\nВсе 7\nПолезный отзыв\n 0\nСсылка на отзыв",
    "review__header-title": "Отзыв сотрудника",
    "share-block__item": "...",
    "tags__item": "Работал 3-5 лет",
    "tags__item (2)": "Москва, декабрь 2023",
    "dj-rating": "2,0",
    "review__title": "Что нравится?",
    "review__title (2)": "Что можно улучшить?",
    "review__answer": "Ответ представителя компании\nФевраль 2024\nДобрый день!\n\nБлагодарим Вас за подробный отзыв и уделенное время!\nМы очень рады, что Вы были частью нашей команды.\n\nДля нас очень ценно, что в своем отзыве Вы отразили различные факторы, влияющие на Вашу карьеру в нашей компании.\n\nТакже для нас очень важно, что Вами отмечены и те области, которые помогут нам как работодателю улучшать текущие процессы. На данный момент в компании уже действует программа Омбудсмена, где Омбудсмен - это независимый сотрудник, сохраняющий нейтралитет для беспристрастного обсуждения сложных ситуаций и выработки взаимовыгодных решений. Наши сотрудники в любой ситуации могут обратиться к омбудсмену, который их выслушает в неформальной обстановке, даст обратную связь по тем вопросам, которые его беспокоят. Также сотрудники компании всегда могут обратиться напрямую в отдел персонала и обсудить необходимые изменения или предложения.\n\nЖелаем Вам и дальнейших успехов!\n\nС уважением,\nКоманда по привлечению и подбору персонала Mars",
    "review__answer-title": "Ответ представителя компании",
    "review__answer-date": "Февраль 2024",
    "review__title-privileges": "Преимущества и льготы",
    "tags__item (3)": "Своевременная оплата труда",
    "tags__item (4)": "Удаленная работа",
    "tags__item (5)": "Наличие кухни, места для обеда",
    "tags__item (6)": "Медицинское страхование",
    "tags__item (7)": "Оплата больничного",
    "tags__item (8)": "Гибкий рабочий график",
    "tags__item (9)": "Компенсация питания",
    "bt": "Все 7",
    "bt (2)": "Полезный отзыв\n 0",
    "review__useful": "Полезный отзыв",
    "bt href": "https://dreamjob.ru/employers/26064?review_id=2208444",
    "bt (3)": "Ссылка на отзыв"
  },
  {
    "review": "Отзыв сотрудника\n...\nРаботал меньше года Москва, сентябрь 2023\n2,5\nЧто нравится?\nУдалённый формат работы, зарплата на уровне рынка, гибкий график\nЧто можно улучшить?\nПроцесс найма сотрудников, долгое время ожидания от hr отдела, процесс рассмотрения кандидатуры от 3 недель\nОтвет представителя компании\nОктябрь 2023\nДобрый день!\n\nБлагодарим Вас за оставленный отзыв и уделенное время!\n\nМы очень рады, что Вы были частью нашей команды.\n\nДля нас очень ценно, что в своем отзыве Вы учли различные факторы, влияющие на Ваш опыт работы в нашей компании.\n\nПри этом мы сожалеем, что Вам пришлось столкнуться со сложностями в процессе найма. Важно отметить, что сотрудники компании всегда могут обратиться напрямую в отдел персонала и обсудить необходимые изменения и предложения, которые помогут нам как работодателю улучшать внутренние процессы.\n\nЕсли у Вас остались дополнительные вопросы, или Вы готовы поделиться более подробной обратной связью, мы будем рады оперативно ответить и помочь. Для этого свяжитесь с нами, пожалуйста, по электронной почте Talent.Team@mars.effem.com.\n\nЖелаем Вам и дальнейших успехов!\n\nС уважением,\nКоманда по привлечению и подбору персонала Mars\nПреимущества и льготы\nСвоевременная оплата труда\nУдаленная работа\nГибкий рабочий график\nВсе 3\nПолезный отзыв\n 1\nСсылка на отзыв",
    "review__header-title": "Отзыв сотрудника",
    "share-block__item": "...",
    "tags__item": "Работал меньше года",
    "tags__item (2)": "Москва, сентябрь 2023",
    "dj-rating": "2,5",
    "review__title": "Что нравится?",
    "review__title (2)": "Что можно улучшить?",
    "review__answer": "Ответ представителя компании\nОктябрь 2023\nДобрый день!\n\nБлагодарим Вас за оставленный отзыв и уделенное время!\n\nМы очень рады, что Вы были частью нашей команды.\n\nДля нас очень ценно, что в своем отзыве Вы учли различные факторы, влияющие на Ваш опыт работы в нашей компании.\n\nПри этом мы сожалеем, что Вам пришлось столкнуться со сложностями в процессе найма. Важно отметить, что сотрудники компании всегда могут обратиться напрямую в отдел персонала и обсудить необходимые изменения и предложения, которые помогут нам как работодателю улучшать внутренние процессы.\n\nЕсли у Вас остались дополнительные вопросы, или Вы готовы поделиться более подробной обратной связью, мы будем рады оперативно ответить и помочь. Для этого свяжитесь с нами, пожалуйста, по электронной почте Talent.Team@mars.effem.com.\n\nЖелаем Вам и дальнейших успехов!\n\nС уважением,\nКоманда по привлечению и подбору персонала Mars",
    "review__answer-title": "Ответ представителя компании",
    "review__answer-date": "Октябрь 2023",
    "review__title-privileges": "Преимущества и льготы",
    "tags__item (3)": "Своевременная оплата труда",
    "tags__item (4)": "Удаленная работа",
    "tags__item (5)": "Гибкий рабочий график",
    "bt": "Все 3",
    "bt (2)": "Полезный отзыв\n 1",
    "review__useful": "Полезный отзыв",
    "bt href": "https://dreamjob.ru/employers/26064?review_id=1977137",
    "bt (3)": "Ссылка на отзыв"
  },
  {
    "review": "Ведущий специалист производства\n...\nРаботаю 5-10 лет Москва, август 2023\n2,8\nЧто нравится?\nУсловия работы, ДМС, компенсация питания, корпоративный транспорт\nЧто можно улучшить?\nПовысить зп, изменить отношение работодателя к наемному персоналу\nОтвет представителя компании\nСентябрь 2023\nДобрый день!\n\nБлагодарим Вас за отзыв и уделенное время!\nМы очень рады, что Вы являетесь частью нашей команды.\n\nЦенно, что в своем отзыве Вы отразили различные факторы, влияющие на Вашу карьеру в нашей компании.\n\nДля нас очень важно, что Вами также отмечены области, которые помогут нам как работодателю улучшать текущие процессы. Также сотрудники компании всегда могут обратиться напрямую в отдел персонала и обсудить необходимые изменения или предложения.\n\nЖелаем Вам и дальнейших успехов!\n\nС уважением,\nКоманда по привлечению и подбору персонала Mars\nПреимущества и льготы\nСвоевременная оплата труда\nНаличие кухни, места для обеда\nМедицинское страхование\nКомпенсация питания\nКорпоративный транспорт\nМесто для парковки\nКорпоративные мероприятия\nВсе 7\nПолезный отзыв\n 0\nСсылка на отзыв",
    "review__header-title": "Ведущий специалист производства",
    "share-block__item": "...",
    "tags__item": "Работаю 5-10 лет",
    "tags__item (2)": "Москва, август 2023",
    "dj-rating": "2,8",
    "review__title": "Что нравится?",
    "review__title (2)": "Что можно улучшить?",
    "review__answer": "Ответ представителя компании\nСентябрь 2023\nДобрый день!\n\nБлагодарим Вас за отзыв и уделенное время!\nМы очень рады, что Вы являетесь частью нашей команды.\n\nЦенно, что в своем отзыве Вы отразили различные факторы, влияющие на Вашу карьеру в нашей компании.\n\nДля нас очень важно, что Вами также отмечены области, которые помогут нам как работодателю улучшать текущие процессы. Также сотрудники компании всегда могут обратиться напрямую в отдел персонала и обсудить необходимые изменения или предложения.\n\nЖелаем Вам и дальнейших успехов!\n\nС уважением,\nКоманда по привлечению и подбору персонала Mars",
    "review__answer-title": "Ответ представителя компании",
    "review__answer-date": "Сентябрь 2023",
    "review__title-privileges": "Преимущества и льготы",
    "tags__item (3)": "Своевременная оплата труда",
    "tags__item (4)": "Наличие кухни, места для обеда",
    "tags__item (5)": "Медицинское страхование",
    "tags__item (6)": "Компенсация питания",
    "tags__item (7)": "Корпоративный транспорт",
    "tags__item (8)": "Место для парковки",
    "tags__item (9)": "Корпоративные мероприятия",
    "bt": "Все 7",
    "bt (2)": "Полезный отзыв\n 0",
    "review__useful": "Полезный отзыв",
    "bt href": "https://dreamjob.ru/employers/26064?review_id=1878682",
    "bt (3)": "Ссылка на отзыв"
  }
]