[
  {
    "review": "Отзыв сотрудника\n...\nРаботал 1-2 года Москва, июль 2025\n2,3\nЧто нравится?\nНовый комфортный офис, система обучения, молодой коллектив, хорошие коллеги\nЧто можно улучшить?\nКарьерный рост практически отсутствует, руководство часто меняется, нет четкой стратегии и сумбур в процессах, микроменеджмент, нет индексации зарплат, оплата сильно ниже среднего по рынку, ДМС сомнительный, мероприятий интересных нет, только корпоративы 2 раза в год в выходные дни, если ищете стабильность и развитие - не вариант\nПреимущества и льготы\nСвоевременная оплата труда\nНаличие кухни, места для обеда\nПолезный отзыв\n 4\nСсылка на отзыв\nОтветить от лица компании",
    "review__header-title": "Отзыв сотрудника",
    "share-block__item": "...",
    "tags__item": "Работал 1-2 года",
    "tags__item (2)": "Москва, июль 2025",
    "dj-rating": "2,3",
    "review__title": "Что нравится?",
    "review__title (2)": "Что можно улучшить?",
    "review__title-privileges": "Преимущества и льготы",
    "tags__item (3)": "Своевременная оплата труда",
    "tags__item (4)": "Наличие кухни, места для обеда",
    "bt": "Полезный отзыв\n 4",
    "review__useful": "Полезный отзыв",
    "bt href": "https://dreamjob.ru/employers/191415?review_id=3817265",
    "bt (2)": "Ссылка на отзыв",
    "bt href (2)": "https://dreamjob.ru/page/employers",
    "bt (3)": "Ответить от лица компании"
  },
  {
    "vacancies-banner__inner": "Вакансии в Система Бронирования",
    "vacancies-banner__all href": "https://dreamjob.ru/employers/191415/vakansii",
    "vacancies-banner__all": "Все\n 15",
    "d-md-none": "Все",
    "vacancies-banner__head": "Менеджер контроля качества",
    "vacancies-banner__сity": "Нижний Новгород",
    "bt-master href": "https://dreamjob.ru/employers/191415/vakansii/126882228",
    "bt-master": "Посмотреть вакансию",
    "vacancies-banner__head (2)": "Руководитель департамента продаж",
    "vacancies-banner__сity (2)": "Москва",
    "bt-master href (2)": "https://dreamjob.ru/employers/191415/vakansii/124599798",
    "vacancies-banner__head (3)": "Продуктовый маркетолог",
    "bt-master href (3)": "https://dreamjob.ru/employers/191415/vakansii/126671956",
    "vacancies-banner__head (4)": "Ведущий менеджер направления внутренних коммуникаций",
    "bt-master href (4)": "https://dreamjob.ru/employers/191415/vakansii/126534317",
    "vacancies-banner__head (5)": "Руководитель отдела адаптации и оценки персонала",
    "bt-master href (5)": "https://dreamjob.ru/employers/191415/vakansii/126421079"
  },
  {
    "review": "Менеджер по бронированию\n...\nРаботал 1-2 года Москва, июль 2025\n2,8\nЧто нравится?\nГрамотное руководство, которое всегда помогает и наставляет;\nМягкое вхождение в должность;\nСтабильная компания;\nДружелюбная атмосфера в офисе;\nСредняя по рынку заработная плата;\nОтличная система обучения.\nЧто можно улучшить?\nПрактически полное отсутствие карьерного роста;\nНевозможность проявить инициативу;\nПроцесс работы требует обновления. Ощущение, что компания застряла в 2010;\nРазработка системы kpi.\nПреимущества и льготы\nСвоевременная оплата труда\nНаличие кухни, места для обеда\nПрофессиональное обучение\nСистема наставничества\nКорпоративные мероприятия\nВсе 5\nПолезный отзыв\n 2\nСсылка на отзыв\nОтветить от лица компании",
    "review__header-title": "Менеджер по бронированию",
    "share-block__item": "...",
    "tags__item": "Работал 1-2 года",
    "tags__item (2)": "Москва, июль 2025",
    "dj-rating": "2,8",
    "review__title": "Что нравится?",
    "review__title (2)": "Что можно улучшить?",
    "review__title-privileges": "Преимущества и льготы",
    "tags__item (3)": "Своевременная оплата труда",
    "tags__item (4)": "Наличие кухни, места для обеда",
    "bt": "Полезный отзыв\n 2",
    "review__useful": "Полезный отзыв",
    "bt href": "https://dreamjob.ru/employers/191415?review_id=3816387",
    "bt (2)": "Ссылка на отзыв",
    "bt href (2)": "https://dreamjob.ru/page/employers",
    "bt (3)": "Ответить от лица компании",
    "tags__item (5)": "Профессиональное обучение",
    "tags__item (6)": "Система наставничества",
    "bt (4)": "Все 5"
  },
  {
    "review": "Руководитель группы отдела сопровождения отелей\n...\nРаботал меньше года Москва, январь 2025\n1,7\nЧто нравится?\nМожно работать удалённо, зарплата белая, без задержек. Есть ДМС, но с подводными камнями.\nЧто можно улучшить?\nВ компании не хватает сотрудников из-за этого объемы работы не реальные. Руководство закрывает на это глаза и количество выполняемых задач только растёт, доходит до того что приходится работать из дома. Спрашивают даже с тех задач, которые от тебя не зависят (например отель не хочет так работать или выгружать что-то). Советую беречь свои нервы.\nПреимущества и льготы\nСвоевременная оплата труда\nУдаленная работа\nНаличие кухни, места для обеда\nОплата больничного\nВсе 4\nПолезный отзыв\n 5\nСсылка на отзыв\nОтветить от лица компании",
    "review__header-title": "Руководитель группы отдела сопровождения отелей",
    "share-block__item": "...",
    "tags__item": "Работал меньше года",
    "tags__item (2)": "Москва, январь 2025",
    "dj-rating": "1,7",
    "review__title": "Что нравится?",
    "review__title (2)": "Что можно улучшить?",
    "review__title-privileges": "Преимущества и льготы",
    "tags__item (3)": "Своевременная оплата труда",
    "tags__item (4)": "Удаленная работа",
    "bt": "Полезный отзыв\n 5",
    "review__useful": "Полезный отзыв",
    "bt href": "https://dreamjob.ru/employers/191415?review_id=3289614",
    "bt (2)": "Ссылка на отзыв",
    "bt href (2)": "https://dreamjob.ru/page/employers",
    "bt (3)": "Ответить от лица компании",
    "tags__item (5)": "Наличие кухни, места для обеда",
    "tags__item (6)": "Оплата больничного",
    "bt (4)": "Все 4"
  },
  {
    "vacancies-banner__inner": "Вакансии в Система Бронирования",
    "vacancies-banner__all href": "https://dreamjob.ru/employers/191415/vakansii",
    "vacancies-banner__all": "Все\n 15",
    "d-md-none": "Все",
    "vacancies-banner__head": "Менеджер контроля качества",
    "vacancies-banner__сity": "Нижний Новгород",
    "bt-master href": "https://dreamjob.ru/employers/191415/vakansii/126882228",
    "bt-master": "Посмотреть вакансию",
    "vacancies-banner__head (2)": "Руководитель департамента продаж",
    "vacancies-banner__сity (2)": "Москва",
    "bt-master href (2)": "https://dreamjob.ru/employers/191415/vakansii/124599798",
    "vacancies-banner__head (3)": "Продуктовый маркетолог",
    "bt-master href (3)": "https://dreamjob.ru/employers/191415/vakansii/126671956",
    "vacancies-banner__head (4)": "Ведущий менеджер направления внутренних коммуникаций",
    "bt-master href (4)": "https://dreamjob.ru/employers/191415/vakansii/126534317",
    "vacancies-banner__head (5)": "Руководитель отдела адаптации и оценки персонала",
    "bt-master href (5)": "https://dreamjob.ru/employers/191415/vakansii/126421079"
  },
  {
    "review": "Менеджер по работе с клиентами\n...\nРаботал 1-2 года Москва, август 2024\n2,7\nЧто нравится?\n- близость к метро\n- относительная стабильность компании\n- регулярные выплаты зп\nЧто можно улучшить?\n- невысокая зп\n- общение в коллективе\n- стиль руководства и обращение с сотрудниками\nПреимущества и льготы\nСвоевременная оплата труда\nУдобное расположение работы\nНаличие кухни, места для обеда\nКорпоративные мероприятия\nВсе 4\nПолезный отзыв\n 1\nСсылка на отзыв\nОтветить от лица компании",
    "review__header-title": "Менеджер по работе с клиентами",
    "share-block__item": "...",
    "tags__item": "Работал 1-2 года",
    "tags__item (2)": "Москва, август 2024",
    "dj-rating": "2,7",
    "review__title": "Что нравится?",
    "review__title (2)": "Что можно улучшить?",
    "review__title-privileges": "Преимущества и льготы",
    "tags__item (3)": "Своевременная оплата труда",
    "tags__item (4)": "Удобное расположение работы",
    "bt": "Полезный отзыв\n 1",
    "review__useful": "Полезный отзыв",
    "bt href": "https://dreamjob.ru/employers/191415?review_id=2863602",
    "bt (2)": "Ссылка на отзыв",
    "bt href (2)": "https://dreamjob.ru/page/employers",
    "bt (3)": "Ответить от лица компании",
    "tags__item (5)": "Наличие кухни, места для обеда",
    "tags__item (6)": "Корпоративные мероприятия",
    "bt (4)": "Все 4"
  },
  {
    "review": "Project Manager\n...\nРаботал 1-2 года Москва, август 2024\n2,7\nЧто нравится?\nОтличные коллеги в ИТ отделе и отделе ОБ, маркетинг достаточно специфичен, из-за жесткого руководства невыносимые условия и планы.\nКасательно отдела продаж комментарий добавить не могу, тк и сказать нечего.\nЧто можно улучшить?\nОплата труда сильно меньше среднего на рынке, если компания претендует на статус ИТ\nПреимущества и льготы\nНаличие кухни, места для обеда\nОплата больничного\nПолезный отзыв\n 1\nСсылка на отзыв\nОтветить от лица компании",
    "review__header-title": "Project Manager",
    "share-block__item": "...",
    "tags__item": "Работал 1-2 года",
    "tags__item (2)": "Москва, август 2024",
    "dj-rating": "2,7",
    "review__title": "Что нравится?",
    "review__title (2)": "Что можно улучшить?",
    "review__title-privileges": "Преимущества и льготы",
    "tags__item (3)": "Наличие кухни, места для обеда",
    "tags__item (4)": "Оплата больничного",
    "bt": "Полезный отзыв\n 1",
    "review__useful": "Полезный отзыв",
    "bt href": "https://dreamjob.ru/employers/191415?review_id=2829192",
    "bt (2)": "Ссылка на отзыв",
    "bt href (2)": "https://dreamjob.ru/page/employers",
    "bt (3)": "Ответить от лица компании"
  },
  {
    "review": "Отзыв сотрудника\n...\nРаботал меньше года Москва, декабрь 2022\n1,7\nЧто нравится?\nБольшинство коллег очень хорошие и отзывчивые (но все все, в критической ситуации могут подставить), больше плюсов нет и быть не может, хотя на др от начальства 2 тыс подарили, белый оклад + есть небольшие бонусы\nЧто можно улучшить?\nАдекватное руководство в определенных отделах, большая текучка кадров, непонятная система выплата зарплаты, офис очень сильно уставший и требует ремонта\nПреимущества и льготы\nНаличие кухни, места для обеда\nОплата больничного\nПолезный отзыв\n 1\nСсылка на отзыв\nОтветить от лица компании",
    "review__header-title": "Отзыв сотрудника",
    "share-block__item": "...",
    "tags__item": "Работал меньше года",
    "tags__item (2)": "Москва, декабрь 2022",
    "dj-rating": "1,7",
    "review__title": "Что нравится?",
    "review__title (2)": "Что можно улучшить?",
    "review__title-privileges": "Преимущества и льготы",
    "tags__item (3)": "Наличие кухни, места для обеда",
    "tags__item (4)": "Оплата больничного",
    "bt": "Полезный отзыв\n 1",
    "review__useful": "Полезный отзыв",
    "bt href": "https://dreamjob.ru/employers/191415?review_id=1373223",
    "bt (2)": "Ссылка на отзыв",
    "bt href (2)": "https://dreamjob.ru/page/employers",
    "bt (3)": "Ответить от лица компании"
  }
]