[
  {
    "review": "Оператор-монтажер\n...\nРаботал 1-2 года Москва, октябрь 2025\n2,5\nЧто нравится?\nПриятный коллектив и отличная возможность посмотреть Россию и ближнее зарубежье в командировках.\nЧто можно улучшить?\nВвести хотя бы гибридный график для сотрудников, чьи позиции абсолютно не подразумевают нахождения в офисе 5/2.\nПреимущества и льготы\nСвоевременная оплата труда\nУдобное расположение работы\nНаличие кухни, места для обеда\nМедицинское страхование\nПрофессиональное обучение\nКорпоративные мероприятия\nВсе 6\nПолезный отзыв\n 0\nСсылка на отзыв\nОтветить от лица компании",
    "review__header-title": "Оператор-монтажер",
    "share-block__item": "...",
    "tags__item": "Работал 1-2 года",
    "tags__item (2)": "Москва, октябрь 2025",
    "dj-rating": "2,5",
    "review__title": "Что нравится?",
    "review__title (2)": "Что можно улучшить?",
    "review__title-privileges": "Преимущества и льготы",
    "tags__item (3)": "Своевременная оплата труда",
    "tags__item (4)": "Удобное расположение работы",
    "tags__item (5)": "Наличие кухни, места для обеда",
    "tags__item (6)": "Медицинское страхование",
    "tags__item (7)": "Профессиональное обучение",
    "bt": "Все 6",
    "bt (2)": "Полезный отзыв\n 0",
    "review__useful": "Полезный отзыв",
    "bt href": "https://dreamjob.ru/employers/106175?review_id=4108531",
    "bt (3)": "Ссылка на отзыв",
    "bt href (2)": "https://dreamjob.ru/page/employers",
    "bt (4)": "Ответить от лица компании"
  },
  {
    "vacancies-banner__inner": "Вакансии в S8 Capital",
    "vacancies-banner__all href": "https://dreamjob.ru/employers/106175/vakansii",
    "vacancies-banner__all": "Все\n 55",
    "d-md-block": "Все",
    "vacancies-banner__head": "Оператор call-центра",
    "vacancies-banner__сity": "Москва",
    "bt-master href": "https://dreamjob.ru/employers/106175/vakansii/126195483",
    "bt-master": "Посмотреть вакансию",
    "vacancies-banner__head (2)": "Менеджер по оценке персонала",
    "bt-master href (2)": "https://dreamjob.ru/employers/106175/vakansii/126869647",
    "vacancies-banner__head (3)": "Руководитель направления безопасности приложений\\AppSec",
    "bt-master href (3)": "https://dreamjob.ru/employers/106175/vakansii/126811987",
    "vacancies-banner__head (4)": "Продуктовый аналитик",
    "bt-master href (4)": "https://dreamjob.ru/employers/106175/vakansii/126234511",
    "vacancies-banner__head (5)": "Бренд - Менеджер",
    "bt-master href (5)": "https://dreamjob.ru/employers/106175/vakansii/126810659"
  },
  {
    "review": "Менеджер по коммуникациям\n...\nРаботал меньше года Москва, октябрь 2025\n1,5\nЧто нравится?\nХороший вид из окна, оборудованная кухня, кто-то из коллег — весьма приятная личность\nЧто можно улучшить?\nПопросили уволиться, когда я решила как-то отстоять свою профессиональную позицию. В коллективе любят токсиков, которые матерятся и льстят руководству, которое, в свою очередь, матерится и кричит на тебя. Таким образом, я оказалась в окружении криков, газлайтинга и недосчёта по зп (на собеседовании мне озвучили совсем другую сумму, чем та, которую зарабатывала я).\n\nВ общем, не советую идти в марком, если вы не токсик и профессионал.\nПреимущества и льготы\nСвоевременная оплата труда\nНаличие кухни, места для обеда\nМедицинское страхование\nВсе 3\nПолезный отзыв\n 0\nСсылка на отзыв\nОтветить от лица компании",
    "review__header-title": "Менеджер по коммуникациям",
    "share-block__item": "...",
    "tags__item": "Работал меньше года",
    "tags__item (2)": "Москва, октябрь 2025",
    "dj-rating": "1,5",
    "review__title": "Что нравится?",
    "review__title (2)": "Что можно улучшить?",
    "review__title-privileges": "Преимущества и льготы",
    "tags__item (3)": "Своевременная оплата труда",
    "tags__item (4)": "Наличие кухни, места для обеда",
    "tags__item (5)": "Медицинское страхование",
    "bt": "Все 3",
    "bt (2)": "Полезный отзыв\n 0",
    "review__useful": "Полезный отзыв",
    "bt href": "https://dreamjob.ru/employers/106175?review_id=4085194",
    "bt (3)": "Ссылка на отзыв",
    "bt href (2)": "https://dreamjob.ru/page/employers",
    "bt (4)": "Ответить от лица компании"
  },
  {
    "swiper-slide": "зарплата\n(3)"
  },
  {
    "review": "2D художник\n...\nРаботал меньше года апрель 2025\n2,2\nЧто нравится?\nКоллектив более менее нормальный и зп вовремя . Больше нечего добавить\nЧто можно улучшить?\nОтсутствует удаленка ,даже гибрида нет.рабочее место плохо обустроено,все тесно , где тебе в спину дышат. Нет лицензий на фотошоп и другие программы.компы тупят. Начальство неопытное совершенно,геймдизайнеры не знают,чего хотят ,но по итогу виноват ты.непрлфессиональный подход к задачам ,сроки сжатые на все,качество страдает. Такими темпами игра не выйдет)еще и лицемеры,как оказывается.кататься каждый день в Москва сити ,без возможности гибридного графика хотя-бы-это ужасно\nПреимущества и льготы\nСвоевременная оплата труда\nОплата больничного\nПолезный отзыв\n 8\nСсылка на отзыв\nОтветить от лица компании",
    "review__header-title": "2D художник",
    "share-block__item": "...",
    "tags__item": "Работал меньше года",
    "tags__item (2)": "апрель 2025",
    "dj-rating": "2,2",
    "review__title": "Что нравится?",
    "review__title (2)": "Что можно улучшить?",
    "review__title-privileges": "Преимущества и льготы",
    "tags__item (3)": "Своевременная оплата труда",
    "tags__item (4)": "Оплата больничного",
    "bt (2)": "Полезный отзыв\n 8",
    "review__useful": "Полезный отзыв",
    "bt href": "https://dreamjob.ru/employers/106175?review_id=3586659",
    "bt (3)": "Ссылка на отзыв",
    "bt href (2)": "https://dreamjob.ru/page/employers",
    "bt (4)": "Ответить от лица компании"
  },
  {
    "vacancies-banner__inner": "Вакансии в S8 Capital",
    "vacancies-banner__all href": "https://dreamjob.ru/employers/106175/vakansii",
    "vacancies-banner__all": "Все\n 55",
    "d-md-block": "Все",
    "vacancies-banner__head": "Оператор call-центра",
    "vacancies-banner__сity": "Москва",
    "bt-master href": "https://dreamjob.ru/employers/106175/vakansii/126195483",
    "bt-master": "Посмотреть вакансию",
    "vacancies-banner__head (2)": "Менеджер по оценке персонала",
    "bt-master href (2)": "https://dreamjob.ru/employers/106175/vakansii/126869647",
    "vacancies-banner__head (3)": "Руководитель направления безопасности приложений\\AppSec",
    "bt-master href (3)": "https://dreamjob.ru/employers/106175/vakansii/126811987",
    "vacancies-banner__head (4)": "Продуктовый аналитик",
    "bt-master href (4)": "https://dreamjob.ru/employers/106175/vakansii/126234511",
    "vacancies-banner__head (5)": "Бренд - Менеджер",
    "bt-master href (5)": "https://dreamjob.ru/employers/106175/vakansii/126810659"
  },
  {
    "review": "Отзыв сотрудника\n...\nРаботал 3-5 лет Москва, апрель 2024\n2,8\nЧто нравится?\nкомфортный офис, близость всей инфраструктуры к нему, зп выше рынка, соц пакет\nЧто можно улучшить?\nбюрократия на максимуме, исключительно офисный режим, обращают внимание на время прихода-ухода, а не на реальные результаты работы, гибкости в процессах нет и \"так надо потому что так надо\", высокая текучка несмотря на высокую зп, потому что атмосферка порой так себе\nОтвет представителя компании\nМай 2024\nПривет!\nСпасибо, что прямо рассказываешь о том, что тебя вдохновило в работе с нами, а также о том, что не понравилось в бизнес-процессах и в атмосфере.\n\nМы действительно предпочитаем офисный режим – так получается быстрее обсуждать работу с коллегами и выполнять задачи на максимуме эффективности.\nЧёткие правила в рабочих процессах помогают нам строить эффективный бизнес и выстраивать максимально прозрачные процессы – как перед сотрудниками, так и перед государством.\n\nРеальные результаты деятельности мы измеряем в индивидуальных показателях KPI. Формирование целей происходит по модели SMART, руководитель с сотрудником обсуждают цели и задачи, которые потом интерпретируются в метрики эффективности.\nПреимущества и льготы\nСвоевременная оплата труда\nУдобное расположение работы\nНаличие кухни, места для обеда\nМедицинское страхование\nОплата больничного\nВсе 5\nПолезный отзыв\n 2\nСсылка на отзыв",
    "review__header-title": "Отзыв сотрудника",
    "share-block__item": "...",
    "tags__item": "Работал 3-5 лет",
    "tags__item (2)": "Москва, апрель 2024",
    "dj-rating": "2,8",
    "review__title": "Что нравится?",
    "review__title (2)": "Что можно улучшить?",
    "review__title-privileges": "Преимущества и льготы",
    "tags__item (3)": "Своевременная оплата труда",
    "tags__item (4)": "Удобное расположение работы",
    "tags__item (5)": "Наличие кухни, места для обеда",
    "tags__item (6)": "Медицинское страхование",
    "tags__item (7)": "Оплата больничного",
    "bt": "Все 5",
    "bt (2)": "Полезный отзыв\n 2",
    "review__useful": "Полезный отзыв",
    "bt href": "https://dreamjob.ru/employers/106175?review_id=2541429",
    "bt (3)": "Ссылка на отзыв",
    "review__answer": "Ответ представителя компании\nМай 2024\nПривет!\nСпасибо, что прямо рассказываешь о том, что тебя вдохновило в работе с нами, а также о том, что не понравилось в бизнес-процессах и в атмосфере.\n\nМы действительно предпочитаем офисный режим – так получается быстрее обсуждать работу с коллегами и выполнять задачи на максимуме эффективности.\nЧёткие правила в рабочих процессах помогают нам строить эффективный бизнес и выстраивать максимально прозрачные процессы – как перед сотрудниками, так и перед государством.\n\nРеальные результаты деятельности мы измеряем в индивидуальных показателях KPI. Формирование целей происходит по модели SMART, руководитель с сотрудником обсуждают цели и задачи, которые потом интерпретируются в метрики эффективности.",
    "review__answer-title": "Ответ представителя компании",
    "review__answer-date": "Май 2024"
  },
  {
    "review": "Отзыв сотрудника\n...\nРаботал меньше года Москва, март 2024\n2,5\nЧто нравится?\nУдобное местоположение. Столовая в здании, бесплатно печенье и конфеты.\nЧто можно улучшить?\nДобрее относиться к коллективу. Сделать наставничество\nНе грозить увольнением\nАтмосфера в коллективе гнетущая. Карьерный рост мало возможен.\nРабочее место плохо освещено\nПреимущества и льготы\nСвоевременная оплата труда\nУдобное расположение работы\nНаличие кухни, места для обеда\nМедицинское страхование\nВсе 4\nПолезный отзыв\n 0\nСсылка на отзыв\nОтветить от лица компании",
    "review__header-title": "Отзыв сотрудника",
    "share-block__item": "...",
    "tags__item": "Работал меньше года",
    "tags__item (2)": "Москва, март 2024",
    "dj-rating": "2,5",
    "review__title": "Что нравится?",
    "review__title (2)": "Что можно улучшить?",
    "review__title-privileges": "Преимущества и льготы",
    "tags__item (3)": "Своевременная оплата труда",
    "tags__item (4)": "Удобное расположение работы",
    "tags__item (5)": "Наличие кухни, места для обеда",
    "tags__item (6)": "Медицинское страхование",
    "bt": "Все 4",
    "bt (2)": "Полезный отзыв\n 0",
    "review__useful": "Полезный отзыв",
    "bt href": "https://dreamjob.ru/employers/106175?review_id=2447495",
    "bt (3)": "Ссылка на отзыв",
    "bt href (2)": "https://dreamjob.ru/page/employers",
    "bt (4)": "Ответить от лица компании"
  },
  {
    "review": "Руководитель отдела внешнего обучения\n...\nРаботал 3-5 лет Москва, март 2024\n2,8\nЧто нравится?\nВозможности развития проектов. Корпоративная среда. Рабочее место.\nЧто можно улучшить?\nОбучение и оценку персонала.\nОтвет представителя компании\nМарт 2024\nПривет!\nСпасибо, что открыто говоришь о процессах, которые тебе не нравятся.\nЕжегодно мы проводим опрос о качестве работы команды оценки и обучения персонала, чтобы лучше понимать запросы коллег и внешних заказчиков.\nВозможно, у тебя есть конкретные предложения, что можно было бы улучшить? Всегда готовы принять конструктивную обратную связь, пиши нам на почту корпоративного университета: s8academy@s8.capital\nПреимущества и льготы\nСвоевременная оплата труда\nНаличие кухни, места для обеда\nМедицинское страхование\nОплата мобильной связи\nКорпоративные мероприятия\nВсе 5\nПолезный отзыв\n 1\nСсылка на отзыв",
    "review__header-title": "Руководитель отдела внешнего обучения",
    "share-block__item": "...",
    "tags__item": "Работал 3-5 лет",
    "tags__item (2)": "Москва, март 2024",
    "dj-rating": "2,8",
    "review__title": "Что нравится?",
    "review__title (2)": "Что можно улучшить?",
    "review__title-privileges": "Преимущества и льготы",
    "tags__item (3)": "Своевременная оплата труда",
    "tags__item (4)": "Наличие кухни, места для обеда",
    "tags__item (5)": "Медицинское страхование",
    "tags__item (6)": "Оплата мобильной связи",
    "tags__item (7)": "Корпоративные мероприятия",
    "bt": "Все 5",
    "bt (2)": "Полезный отзыв\n 1",
    "review__useful": "Полезный отзыв",
    "bt href": "https://dreamjob.ru/employers/106175?review_id=2403585",
    "bt (3)": "Ссылка на отзыв",
    "review__answer": "Ответ представителя компании\nМарт 2024\nПривет!\nСпасибо, что открыто говоришь о процессах, которые тебе не нравятся.\nЕжегодно мы проводим опрос о качестве работы команды оценки и обучения персонала, чтобы лучше понимать запросы коллег и внешних заказчиков.\nВозможно, у тебя есть конкретные предложения, что можно было бы улучшить? Всегда готовы принять конструктивную обратную связь, пиши нам на почту корпоративного университета: s8academy@s8.capital",
    "review__answer-title": "Ответ представителя компании",
    "review__answer-date": "Март 2024"
  },
  {
    "review": "Ведущий аналитик\n...\nРаботал 1-2 года Москва, июль 2023\n2,8\nЧто нравится?\nПрезентабельный офис, неплохой коллектив, красивый вид из окна.\nЧто можно улучшить?\nПредоставить нормальную удалёнку, необходимость каждый раз согласовывать дистанционную работу раздражает и фрустрирует. Также проблемы с выдачей оборудования, получить ноутбук в дополнение к основному компьютеру практически невозможно, гарнитуру за ГОД работы предоставить не смогли, это просто смешно.\nОтвет представителя компании\nСентябрь 2023\nБлагодарим за ваш отзыв! Спасибо, что обратили на внимание на проблему с оборудованием – вопрос оперативного его предоставления сейчас один из ключевых в компании.\nНам действительно важно, чтобы у сотрудников были все условия для комфортной работы.\nПреимущества и льготы\nСвоевременная оплата труда\nНаличие кухни, места для обеда\nМедицинское страхование\nГибкий рабочий график\nВсе 4\nПолезный отзыв\n 2\nСсылка на отзыв",
    "review__header-title": "Ведущий аналитик",
    "share-block__item": "...",
    "tags__item": "Работал 1-2 года",
    "tags__item (2)": "Москва, июль 2023",
    "dj-rating": "2,8",
    "review__title": "Что нравится?",
    "review__title (2)": "Что можно улучшить?",
    "review__title-privileges": "Преимущества и льготы",
    "tags__item (3)": "Своевременная оплата труда",
    "tags__item (4)": "Наличие кухни, места для обеда",
    "tags__item (5)": "Медицинское страхование",
    "tags__item (6)": "Гибкий рабочий график",
    "bt": "Все 4",
    "bt (2)": "Полезный отзыв\n 2",
    "review__useful": "Полезный отзыв",
    "bt href": "https://dreamjob.ru/employers/106175?review_id=1798197",
    "bt (3)": "Ссылка на отзыв",
    "review__answer": "Ответ представителя компании\nСентябрь 2023\nБлагодарим за ваш отзыв! Спасибо, что обратили на внимание на проблему с оборудованием – вопрос оперативного его предоставления сейчас один из ключевых в компании.\nНам действительно важно, чтобы у сотрудников были все условия для комфортной работы.",
    "review__answer-title": "Ответ представителя компании",
    "review__answer-date": "Сентябрь 2023"
  },
  {
    "review": "Сотрудник департамента маркетинга\n...\nРаботаю 1-2 года Москва, февраль 2023\n2,0\nЧто нравится?\nОформление по ТК РФ, комфортный современный офис, удобное расположение\nЧто можно улучшить?\nДумаешь, что устраиваешься на работу в маркетинг современной компании, занимающей классный офис - а оказываешься в отделе рекламы 20-летней давности с казенно-казарменными устоями… Бренд-маркетинг отсутствует, маркетинговые коммуникации на зачаточной стадии. О каких промопланах, таймингах, запусках кампаний 360 может идти речь? Согласование одного макета длится неделями по принципу нравится - не нравится картинка. Трейд-маркетинг занимает самую низшую ступень в структурной иерархии: бессмысленная муштра и дрессировки вкупе с обслуживающей функцией быть на подхвате у всех смежных подразделений. Недопустимо пренебрежительное отношение к сотрудникам, некомпетентность менеджеров, волокита, отсутствие рабочих процедур… Узнать что-то новое, прокачать скилы и получить опыт вряд ли удастся, а вот окунуться в атмосферу конторы старорежимного формата и потерять пару лет вполне реально.\nОтвет представителя компании\nАпрель 2023\nДобрый день! Во-первых, нам очень жаль, когда у сотрудников не складываются отношения с компанией, ведь всегда можно найти компромиссы, обсудить возникшие проблемы и предложить от себя крутые рабочие решения – у нас приветствуется любая инициатива.\nВо-вторых, не согласимся с озвученной характеристикой нашего трейд-маркетинга. Данное управление зарождалось в «Столото» в 2019 году. Все начиналось с двух сотрудников, которые занимались оформлением точек продаж РИМами. Сегодня это полноценный отдел, в задачи которого входит разработка стандартов представленности бренда во всех розничных каналах продаж, включая федеральные сети. Кроме того, в это структурное подразделение входит группа, которая разрабатывает и производит оборудование под все форматы точек продаж, в том числе под все многообразие пилотных проектов.\nДанное управление является одним из ключевых в Дирекции операционного маркетинга и требует к себе все больше ресурсов квалифицированных специалистов как с обширным, так и узконаправленным опытом в трейд-маркетинге. Высокая вовлеченность в проекты за последние 3 года, четко выстроенные процессы внутри, а также гибкость в изменениях дали возможность команде трейд-маркетинга реализовать значимые бизнес-задачи и помочь достичь поставленных финансовых показателей.\nЧто касается бюрократии – не без этого. У нас большой холдинг, и пристальное внимание к процессам иногда чревато волокитой. Но мы постоянно работаем над автоматизацией и внедряем оптимальные решения для ускорения бизнес-процессов.\nИ в завершение пару слов на тему профессионального роста. К сожалению, не всегда сотрудники соответствуют высоким стандартам профессии и демонстрируют необходимые компетенции, но мы всегда даем возможность развить их. Это можно делать в формате action learning в тесной связке с руководителями на боевых задачах, а также используя возможности нашей собственной образовательной Академии S8. Сожалеем, что у вас сложилось противоположное мнение.\nПреимущества и льготы\nСвоевременная оплата труда\nПолезный отзыв\n 26\nСсылка на отзыв",
    "review__header-title": "Сотрудник департамента маркетинга",
    "share-block__item": "...",
    "tags__item": "Работаю 1-2 года",
    "tags__item (2)": "Москва, февраль 2023",
    "dj-rating": "2,0",
    "review__title": "Что нравится?",
    "review__title (2)": "Что можно улучшить?",
    "review__title-privileges": "Преимущества и льготы",
    "tags__item (3)": "Своевременная оплата труда",
    "bt (2)": "Полезный отзыв\n 26",
    "review__useful": "Полезный отзыв",
    "bt href": "https://dreamjob.ru/employers/106175?review_id=1536872",
    "bt (3)": "Ссылка на отзыв",
    "review__answer": "Ответ представителя компании\nАпрель 2023\nДобрый день! Во-первых, нам очень жаль, когда у сотрудников не складываются отношения с компанией, ведь всегда можно найти компромиссы, обсудить возникшие проблемы и предложить от себя крутые рабочие решения – у нас приветствуется любая инициатива.\nВо-вторых, не согласимся с озвученной характеристикой нашего трейд-маркетинга. Данное управление зарождалось в «Столото» в 2019 году. Все начиналось с двух сотрудников, которые занимались оформлением точек продаж РИМами. Сегодня это полноценный отдел, в задачи которого входит разработка стандартов представленности бренда во всех розничных каналах продаж, включая федеральные сети. Кроме того, в это структурное подразделение входит группа, которая разрабатывает и производит оборудование под все форматы точек продаж, в том числе под все многообразие пилотных проектов.\nДанное управление является одним из ключевых в Дирекции операционного маркетинга и требует к себе все больше ресурсов квалифицированных специалистов как с обширным, так и узконаправленным опытом в трейд-маркетинге. Высокая вовлеченность в проекты за последние 3 года, четко выстроенные процессы внутри, а также гибкость в изменениях дали возможность команде трейд-маркетинга реализовать значимые бизнес-задачи и помочь достичь поставленных финансовых показателей.\nЧто касается бюрократии – не без этого. У нас большой холдинг, и пристальное внимание к процессам иногда чревато волокитой. Но мы постоянно работаем над автоматизацией и внедряем оптимальные решения для ускорения бизнес-процессов.\nИ в завершение пару слов на тему профессионального роста. К сожалению, не всегда сотрудники соответствуют высоким стандартам профессии и демонстрируют необходимые компетенции, но мы всегда даем возможность развить их. Это можно делать в формате action learning в тесной связке с руководителями на боевых задачах, а также используя возможности нашей собственной образовательной Академии S8. Сожалеем, что у вас сложилось противоположное мнение.",
    "review__answer-title": "Ответ представителя компании",
    "review__answer-date": "Апрель 2023"
  },
  {
    "bt (2)": "Посмотреть все зарплаты (53)",
    "bt href": "https://dreamjob.ru/employers/106175/zarplata",
    "swiper-slide": "Посмотреть\nеще зарплаты"
  },
  {
    "review": "Территориальный менеджер\n...\nРаботал 1-2 года Москва, декабрь 2022\n2,3\nЧто нравится?\nСвоевременно выплачивается ЗП, и все положенные выплаты. Есть вся информация для изучения продукта.\nЧто можно улучшить?\nОтношение к подчинённым. График работы 24/7, в выходные приходится заниматься сбором различных отчётов, включая фото. Карьерного роста нет, огромная текучка территориальных менеджеров и руководителей по продажам дивизиона. Достойного обучения и развития нет, внешних тренингов в том числе.\nОтвет представителя компании\nФевраль 2023\nПривет! Спасибо за развернутую обратную связь, она поможет нам стать лучше. Нам очень жаль, что твои ожидания по поводу обучения и развития не оправдались. На самом деле мы уделяем много времени обучению наших сотрудников, поэтому твой отзыв вызвал у нас беспокойство, как и сообщение о работе в выходные дни. Хотим разобрать эту ситуацию внутри. Будем благодарны, если напишешь подробнее на почту orm@stoloto.ru. Нам очень поможет, если в письме ты представишься и укажешь адреса точек, с которыми работал.\nПреимущества и льготы\nСвоевременная оплата труда\nОплата транспортных расходов\nПолезный отзыв\n 5\nСсылка на отзыв",
    "review__header-title": "Территориальный менеджер",
    "share-block__item": "...",
    "tags__item": "Работал 1-2 года",
    "tags__item (2)": "Москва, декабрь 2022",
    "dj-rating": "2,3",
    "review__title": "Что нравится?",
    "review__title (2)": "Что можно улучшить?",
    "review__title-privileges": "Преимущества и льготы",
    "tags__item (3)": "Своевременная оплата труда",
    "tags__item (4)": "Оплата транспортных расходов",
    "bt (2)": "Полезный отзыв\n 5",
    "review__useful": "Полезный отзыв",
    "bt href": "https://dreamjob.ru/employers/106175?review_id=1383175",
    "bt (3)": "Ссылка на отзыв",
    "review__answer": "Ответ представителя компании\nФевраль 2023\nПривет! Спасибо за развернутую обратную связь, она поможет нам стать лучше. Нам очень жаль, что твои ожидания по поводу обучения и развития не оправдались. На самом деле мы уделяем много времени обучению наших сотрудников, поэтому твой отзыв вызвал у нас беспокойство, как и сообщение о работе в выходные дни. Хотим разобрать эту ситуацию внутри. Будем благодарны, если напишешь подробнее на почту orm@stoloto.ru. Нам очень поможет, если в письме ты представишься и укажешь адреса точек, с которыми работал.",
    "review__answer-title": "Ответ представителя компании",
    "review__answer-date": "Февраль 2023"
  },
  {
    "review": "Территориальный менеджер\n...\nРаботал меньше года Владимир, август 2022\n1,7\nЧто нравится?\nНет кабинетной работы, постоянные разъезды\nЧто можно улучшить?\nГСМ оплачивать , сократить длительность рабочего дня, не 16 часов в сутки, ввести выходные, а не 24/7\nОтвет представителя компании\nДекабрь 2022\nСпасибо, что отмечаешь динамичный формат работы столь любимый для энергичных продажников, нацеленных на результат. Жаль, что тебе не хватило, выделяемых компанией средств для оплаты ГСМ и ты был сильно перегружен. Несмотря на то что в пиковые периоды работа действительно интенсивная, а в остальное время график оптимальный, мы озабочены твоим сообщением об отсутствии выходных. Пришли, пожалуйста, более детальную информацию на orm@stoloto.ru, чтобы мы провели внутреннюю проверку. Возможно, твоя обратная связь позволит нам выявить реальную проблему и оперативно устранить ее. Просьба в письме также указать ссылку на свой отзыв.\nПолезный отзыв\n 6\nСсылка на отзыв",
    "review__header-title": "Территориальный менеджер",
    "share-block__item": "...",
    "tags__item": "Работал меньше года",
    "tags__item (2)": "Владимир, август 2022",
    "dj-rating": "1,7",
    "review__title": "Что нравится?",
    "review__title (2)": "Что можно улучшить?",
    "bt (2)": "Полезный отзыв\n 6",
    "review__useful": "Полезный отзыв",
    "bt href": "https://dreamjob.ru/employers/106175?review_id=1104744",
    "bt (3)": "Ссылка на отзыв",
    "review__answer": "Ответ представителя компании\nДекабрь 2022\nСпасибо, что отмечаешь динамичный формат работы столь любимый для энергичных продажников, нацеленных на результат. Жаль, что тебе не хватило, выделяемых компанией средств для оплаты ГСМ и ты был сильно перегружен. Несмотря на то что в пиковые периоды работа действительно интенсивная, а в остальное время график оптимальный, мы озабочены твоим сообщением об отсутствии выходных. Пришли, пожалуйста, более детальную информацию на orm@stoloto.ru, чтобы мы провели внутреннюю проверку. Возможно, твоя обратная связь позволит нам выявить реальную проблему и оперативно устранить ее. Просьба в письме также указать ссылку на свой отзыв.",
    "review__answer-title": "Ответ представителя компании",
    "review__answer-date": "Декабрь 2022"
  }
]