[
  {
    "review": "Старший специалист развития\n...\nРаботал 1-2 года Москва, сентябрь 2025\n2,3\nЧто нравится?\n- Интересная сфера деятельности\n- Коллектив зрелых специалистов\nЧто можно улучшить?\n- Зарплата сильно ниже рынка\n- Руководство часто даёт бесперспективные и непонятные задачи\n- Руководящий состав часто не имеет представления о прикладной специальности сотрудника, но делает вид, что понимает облась и даёт противоречивые задачи\nОтвет представителя компании\nСентябрь 2025\nПривет! Спасибо за обратную связь.\n\nЗарплата формируется в рамках введенной системы грейдов с опорой на рынок, уровень роли и ответственности может корректироваться по итогам результатов работы.\nВ управленческой части держим фокус на понятных задачах и ясности процессов. Твои сигналы учтем.\n\nНам жаль, что у тебя сложился подобный опыт взаимодействия с руководством в Бюро 1440, и тебе не удалось воспользоваться всеми доступными каналами коммуникации. В подобных ситуациях и других возникших вопросах каждый сотрудник может обратиться к вышестоящему руководителю или HR BP.\nПреимущества и льготы\nСвоевременная оплата труда\nМедицинское страхование\nПолезный отзыв\n 8\nСсылка на отзыв",
    "review__header-title": "Старший специалист развития",
    "share-block__item": "...",
    "tags__item": "Работал 1-2 года",
    "tags__item (2)": "Москва, сентябрь 2025",
    "dj-rating": "2,3",
    "review__title": "Что нравится?",
    "review__title (2)": "Что можно улучшить?",
    "review__answer": "Ответ представителя компании\nСентябрь 2025\nПривет! Спасибо за обратную связь.\n\nЗарплата формируется в рамках введенной системы грейдов с опорой на рынок, уровень роли и ответственности может корректироваться по итогам результатов работы.\nВ управленческой части держим фокус на понятных задачах и ясности процессов. Твои сигналы учтем.\n\nНам жаль, что у тебя сложился подобный опыт взаимодействия с руководством в Бюро 1440, и тебе не удалось воспользоваться всеми доступными каналами коммуникации. В подобных ситуациях и других возникших вопросах каждый сотрудник может обратиться к вышестоящему руководителю или HR BP.",
    "review__answer-title": "Ответ представителя компании",
    "review__answer-date": "Сентябрь 2025",
    "review__title-privileges": "Преимущества и льготы",
    "tags__item (3)": "Своевременная оплата труда",
    "tags__item (4)": "Медицинское страхование",
    "bt": "Полезный отзыв\n 8",
    "review__useful": "Полезный отзыв",
    "bt href": "https://dreamjob.ru/employers/130433?review_id=4021053",
    "bt (2)": "Ссылка на отзыв"
  },
  {
    "vacancies-banner__inner": "Вакансии в БЮРО 1440",
    "vacancies-banner__all href": "https://dreamjob.ru/employers/130433/vakansii",
    "vacancies-banner__all": "Все\n 233",
    "d-md-none": "Все",
    "vacancies-banner__head": "Системный архитектор",
    "vacancies-banner__сity": "Москва",
    "bt-master href": "https://dreamjob.ru/employers/130433/vakansii/126907099",
    "bt-master": "Посмотреть вакансию",
    "vacancies-banner__head (2)": "Специалист по кибербезопасности",
    "bt-master href (2)": "https://dreamjob.ru/employers/130433/vakansii/126907078",
    "vacancies-banner__head (3)": "Инженер по качеству",
    "bt-master href (3)": "https://dreamjob.ru/employers/130433/vakansii/124707701",
    "vacancies-banner__head (4)": "Специалист по качеству",
    "bt-master href (4)": "https://dreamjob.ru/employers/130433/vakansii/124892325",
    "vacancies-banner__head (5)": "Инженер по нормоконтролю",
    "bt-master href (5)": "https://dreamjob.ru/employers/130433/vakansii/126207815"
  },
  {
    "review": "Руководитель отдела\n...\nРаботаю меньше года Москва, сентябрь 2025\n1,0\nЧто нравится?\nРядом с метро.\nМожно поучаствовать в огромное проекте.\nИнтересные задачи.\nЧто можно улучшить?\n1) - Отношение к людям.\n2) - Уровень оплаты труда.\n3) - Обратная связь.\nПолезный отзыв\n 0\nСсылка на отзыв\nОтветить от лица компании",
    "review__header-title": "Руководитель отдела",
    "share-block__item": "...",
    "tags__item": "Работаю меньше года",
    "tags__item (2)": "Москва, сентябрь 2025",
    "dj-rating": "1,0",
    "review__title": "Что нравится?",
    "review__title (2)": "Что можно улучшить?",
    "bt": "Полезный отзыв\n 0",
    "review__useful": "Полезный отзыв",
    "bt href": "https://dreamjob.ru/employers/130433?review_id=4009820",
    "bt (2)": "Ссылка на отзыв"
  },
  {
    "review": "Системный администратор\n...\nРаботал меньше года Москва, апрель 2025\n1,7\nЧто нравится?\nГрафик , доступность от метро, вовремя выплачивается зарплата.\nЧто можно улучшить?\nРуководство , проще общаться с людьми, не подставлять людей.\nОтвет представителя компании\nАпрель 2025\nДобрый день!\n\nСпасибо за Ваш отзыв. Мы рады слышать, что вам нравятся график работы, удобное расположение офиса и своевременные выплаты зарплаты. Что касается ваших замечаний о руководстве и общении внутри команды, мы обязательно примем их во внимание. Открытое и конструктивное взаимодействие — важная часть нашей корпоративной культуры, и мы будем работать над тем, чтобы улучшить атмосферу общения.\n\nС уважением,\nКомпания БЮРО 1440.\nПреимущества и льготы\nСвоевременная оплата труда\nУдобное расположение работы\nУдаленная работа\nНаличие кухни, места для обеда\nВсе 4\nПолезный отзыв\n 6\nСсылка на отзыв",
    "review__header-title": "Системный администратор",
    "share-block__item": "...",
    "tags__item": "Работал меньше года",
    "tags__item (2)": "Москва, апрель 2025",
    "dj-rating": "1,7",
    "review__title": "Что нравится?",
    "review__title (2)": "Что можно улучшить?",
    "review__answer": "Ответ представителя компании\nАпрель 2025\nДобрый день!\n\nСпасибо за Ваш отзыв. Мы рады слышать, что вам нравятся график работы, удобное расположение офиса и своевременные выплаты зарплаты. Что касается ваших замечаний о руководстве и общении внутри команды, мы обязательно примем их во внимание. Открытое и конструктивное взаимодействие — важная часть нашей корпоративной культуры, и мы будем работать над тем, чтобы улучшить атмосферу общения.\n\nС уважением,\nКомпания БЮРО 1440.",
    "review__answer-title": "Ответ представителя компании",
    "review__answer-date": "Апрель 2025",
    "review__title-privileges": "Преимущества и льготы",
    "tags__item (3)": "Своевременная оплата труда",
    "tags__item (4)": "Удобное расположение работы",
    "bt": "Полезный отзыв\n 6",
    "review__useful": "Полезный отзыв",
    "bt href": "https://dreamjob.ru/employers/130433?review_id=3555942",
    "bt (2)": "Ссылка на отзыв",
    "tags__item (5)": "Удаленная работа",
    "tags__item (6)": "Наличие кухни, места для обеда",
    "bt (4)": "Все 4"
  },
  {
    "vacancies-banner__inner": "Вакансии в БЮРО 1440",
    "vacancies-banner__all href": "https://dreamjob.ru/employers/130433/vakansii",
    "vacancies-banner__all": "Все\n 233",
    "d-md-none": "Все",
    "vacancies-banner__head": "Системный архитектор",
    "vacancies-banner__сity": "Москва",
    "bt-master href": "https://dreamjob.ru/employers/130433/vakansii/126907099",
    "bt-master": "Посмотреть вакансию",
    "vacancies-banner__head (2)": "Специалист по кибербезопасности",
    "bt-master href (2)": "https://dreamjob.ru/employers/130433/vakansii/126907078",
    "vacancies-banner__head (3)": "Инженер по качеству",
    "bt-master href (3)": "https://dreamjob.ru/employers/130433/vakansii/124707701",
    "vacancies-banner__head (4)": "Специалист по качеству",
    "bt-master href (4)": "https://dreamjob.ru/employers/130433/vakansii/124892325",
    "vacancies-banner__head (5)": "Инженер по нормоконтролю",
    "bt-master href (5)": "https://dreamjob.ru/employers/130433/vakansii/126207815"
  },
  {
    "review": "Оператор\n...\nРаботал 1-2 года Москва, март 2025\n1,3\nЧто нравится?\nНичего, кроме белой зп, офис близко расположен к метро.Чисто\nЧто можно улучшить?\nПоменять сотрудников на адекватных и тактичных.\nОтвет представителя компании\nАвгуст 2025\nДобрый вечер!\n\nСпасибо за отзыв. Мы ценим ваше замечание и работаем над улучшением коммуникации и созданием более позитивной и продуктивной атмосферы в команде.\n\nС уважением,\nКомпания БЮРО 1440.\nПреимущества и льготы\nСвоевременная оплата труда\nУдобное расположение работы\nПолезный отзыв\n 1\nСсылка на отзыв",
    "review__header-title": "Оператор",
    "share-block__item": "...",
    "tags__item": "Работал 1-2 года",
    "tags__item (2)": "Москва, март 2025",
    "dj-rating": "1,3",
    "review__title": "Что нравится?",
    "review__title (2)": "Что можно улучшить?",
    "review__answer": "Ответ представителя компании\nАвгуст 2025\nДобрый вечер!\n\nСпасибо за отзыв. Мы ценим ваше замечание и работаем над улучшением коммуникации и созданием более позитивной и продуктивной атмосферы в команде.\n\nС уважением,\nКомпания БЮРО 1440.",
    "review__answer-title": "Ответ представителя компании",
    "review__answer-date": "Август 2025",
    "review__title-privileges": "Преимущества и льготы",
    "tags__item (3)": "Своевременная оплата труда",
    "tags__item (4)": "Удобное расположение работы",
    "bt": "Полезный отзыв\n 1",
    "review__useful": "Полезный отзыв",
    "bt href": "https://dreamjob.ru/employers/130433?review_id=3501483",
    "bt (2)": "Ссылка на отзыв"
  },
  {
    "review": "Ведущий инженер-конструктор\n...\nРаботаю меньше года Москва, март 2025\n2,7\nЧто нравится?\nУровень дохода и возможность работать удаленно. Близко от метро\nЧто можно улучшить?\nВсе. Организация рабочего процесса просто катастрофическая.\nОтвет представителя компании\nМарт 2025\nДобрый вечер!\n\nСпасибо за Ваш отзыв. Мы активно работаем над улучшением процессов внутреннего взаимодействия и оптимизацией.\n\nС уважением,\nКомпания БЮРО 1440.\nПреимущества и льготы\nСвоевременная оплата труда\nУдобное расположение работы\nУдаленная работа\nНаличие кухни, места для обеда\nМедицинское страхование\nОплата больничного\nВсе 6\nПолезный отзыв\n 11\nСсылка на отзыв",
    "review__header-title": "Ведущий инженер-конструктор",
    "share-block__item": "...",
    "tags__item": "Работаю меньше года",
    "tags__item (2)": "Москва, март 2025",
    "dj-rating": "2,7",
    "review__title": "Что нравится?",
    "review__title (2)": "Что можно улучшить?",
    "review__answer": "Ответ представителя компании\nМарт 2025\nДобрый вечер!\n\nСпасибо за Ваш отзыв. Мы активно работаем над улучшением процессов внутреннего взаимодействия и оптимизацией.\n\nС уважением,\nКомпания БЮРО 1440.",
    "review__answer-title": "Ответ представителя компании",
    "review__answer-date": "Март 2025",
    "review__title-privileges": "Преимущества и льготы",
    "tags__item (3)": "Своевременная оплата труда",
    "tags__item (4)": "Удобное расположение работы",
    "bt": "Полезный отзыв\n 11",
    "review__useful": "Полезный отзыв",
    "bt href": "https://dreamjob.ru/employers/130433?review_id=3493165",
    "bt (2)": "Ссылка на отзыв",
    "tags__item (5)": "Удаленная работа",
    "tags__item (6)": "Наличие кухни, места для обеда",
    "bt (4)": "Все 6",
    "tags__item (7)": "Медицинское страхование",
    "tags__item (8)": "Оплата больничного"
  },
  {
    "review": "Старший администратор проектного офиса\n...\nРаботал 1-2 года Москва, октябрь 2024\n2,7\nЧто нравится?\nБыстроразвивающаяся компания, как минимум быстрый рост знаний вам обеспечен. Собрали сливки со всего рынка, поэтому коллектив в основном очень талантливый и молодой, все горят идеей.\nЧто можно улучшить?\nУсловия труда 24/7, живешь только работой.\nКомпания очень быстро выросла, а процессы не выстроены от слова совсем и админ.отдел просто не в состоянии обеспечить разработку. У самого проекта очень сжатые сроки и меняющиеся требования каждый день, а все шишки летят в РП.\nВ целом в компании отношение к сотрудникам как к просто ресурсу, людей там не ценят.\nОтвет представителя компании\nМай 2025\nДобрый вечер!\n\nБлагодарим Вас за обратную связь. Мы принимаем во внимание Ваши замечания относительно условий труда и процессов в компании. Улучшение организационной структуры и поддержка сотрудников являются нашими приоритетами, и мы активно работаем над решением обозначенных вами проблем.\n\nС уважением,\nКомпания БЮРО 1440.\nПреимущества и льготы\nСвоевременная оплата труда\nУдобное расположение работы\nНаличие кухни, места для обеда\nМедицинское страхование\nВсе 4\nПолезный отзыв\n 10\nСсылка на отзыв",
    "review__header-title": "Старший администратор проектного офиса",
    "share-block__item": "...",
    "tags__item": "Работал 1-2 года",
    "tags__item (2)": "Москва, октябрь 2024",
    "dj-rating": "2,7",
    "review__title": "Что нравится?",
    "review__title (2)": "Что можно улучшить?",
    "review__answer": "Ответ представителя компании\nМай 2025\nДобрый вечер!\n\nБлагодарим Вас за обратную связь. Мы принимаем во внимание Ваши замечания относительно условий труда и процессов в компании. Улучшение организационной структуры и поддержка сотрудников являются нашими приоритетами, и мы активно работаем над решением обозначенных вами проблем.\n\nС уважением,\nКомпания БЮРО 1440.",
    "review__answer-title": "Ответ представителя компании",
    "review__answer-date": "Май 2025",
    "review__title-privileges": "Преимущества и льготы",
    "tags__item (3)": "Своевременная оплата труда",
    "tags__item (4)": "Удобное расположение работы",
    "bt": "Полезный отзыв\n 10",
    "review__useful": "Полезный отзыв",
    "bt href": "https://dreamjob.ru/employers/130433?review_id=3015542",
    "bt (2)": "Ссылка на отзыв",
    "tags__item (5)": "Наличие кухни, места для обеда",
    "tags__item (6)": "Медицинское страхование",
    "bt (4)": "Все 4"
  },
  {
    "review": "Сотрудник\n...\nРаботаю 1-2 года Москва, май 2024\n2,5\nЧто нравится?\nДМС, гибридный график работы, белая зп. Местами хороший коллектив, но местами.\nЧто можно улучшить?\nИндексация зп не соответствует инфляции и проходит редко и сложно. Отсутствие прозрачной системы грейдов, нет роста в компании, только обещания и не более. Местами невоспитанное руководство использующее нецензурную лексику. Отсутствие мотивации, как материальной, так и нематериальной.\nОтвет представителя компании\nМарт 2025\nДобрый день!\n\nСпасибо за Ваш отзыв и за то, что нашли время поделиться своими мыслями о работе в нашей компании.\n\nМы серьезно относимся к вашим замечаниям о недостаточной индексации заработной платы и отсутствии прозрачной системы грейдов. Это действительно важные аспекты, и мы будем работать над тем, чтобы улучшить ситуацию. Ваши комментарии о росте в компании и мотивации также будут учтены — мы стремимся создать условия для профессионального развития и удовлетворенности сотрудников. Что касается руководства, мы обязательно проведем дополнительные обсуждения на эту тему и примем меры для улучшения ситуации.\n\nС уважением,\nКомпания БЮРО 1440.\nПреимущества и льготы\nСвоевременная оплата труда\nУдаленная работа\nНаличие кухни, места для обеда\nМедицинское страхование\nВсе 4\nПолезный отзыв\n 14\nСсылка на отзыв",
    "review__header-title": "Сотрудник",
    "share-block__item": "...",
    "tags__item": "Работаю 1-2 года",
    "tags__item (2)": "Москва, май 2024",
    "dj-rating": "2,5",
    "review__title": "Что нравится?",
    "review__title (2)": "Что можно улучшить?",
    "review__answer": "Ответ представителя компании\nМарт 2025\nДобрый день!\n\nСпасибо за Ваш отзыв и за то, что нашли время поделиться своими мыслями о работе в нашей компании.\n\nМы серьезно относимся к вашим замечаниям о недостаточной индексации заработной платы и отсутствии прозрачной системы грейдов. Это действительно важные аспекты, и мы будем работать над тем, чтобы улучшить ситуацию. Ваши комментарии о росте в компании и мотивации также будут учтены — мы стремимся создать условия для профессионального развития и удовлетворенности сотрудников. Что касается руководства, мы обязательно проведем дополнительные обсуждения на эту тему и примем меры для улучшения ситуации.\n\nС уважением,\nКомпания БЮРО 1440.",
    "review__answer-title": "Ответ представителя компании",
    "review__answer-date": "Март 2025",
    "review__title-privileges": "Преимущества и льготы",
    "tags__item (3)": "Своевременная оплата труда",
    "tags__item (4)": "Удаленная работа",
    "bt": "Полезный отзыв\n 14",
    "review__useful": "Полезный отзыв",
    "bt href": "https://dreamjob.ru/employers/130433?review_id=2593914",
    "bt (2)": "Ссылка на отзыв",
    "tags__item (5)": "Наличие кухни, места для обеда",
    "tags__item (6)": "Медицинское страхование",
    "bt (4)": "Все 4"
  },
  {
    "review": "Отзыв сотрудника\n...\nРаботаю 1-2 года Москва, февраль 2024\n2,0\nЧто нравится?\nСоц пакет, офисы, молодой коллектив\nЧто можно улучшить?\nКоличество рабочих мест и управление командами\nОтвет представителя компании\nМарт 2025\nДобрый вечер!\n\nБлагодарим Вас за обратную связь. Мы понимаем, что комфортное рабочее место — залог продуктивной работы. Обязательно учтем ваши замечания по поводу рабочих мест и управления командами для дальнейшего улучшения условий работы.\n\nС уважением,\nКомпания Бюро 1440.\nПреимущества и льготы\nСвоевременная оплата труда\nУдобное расположение работы\nУдаленная работа\nНаличие кухни, места для обеда\nМедицинское страхование\nОплата больничного\nВсе 6\nПолезный отзыв\n 0\nСсылка на отзыв",
    "review__header-title": "Отзыв сотрудника",
    "share-block__item": "...",
    "tags__item": "Работаю 1-2 года",
    "tags__item (2)": "Москва, февраль 2024",
    "dj-rating": "2,0",
    "review__title": "Что нравится?",
    "review__title (2)": "Что можно улучшить?",
    "review__answer": "Ответ представителя компании\nМарт 2025\nДобрый вечер!\n\nБлагодарим Вас за обратную связь. Мы понимаем, что комфортное рабочее место — залог продуктивной работы. Обязательно учтем ваши замечания по поводу рабочих мест и управления командами для дальнейшего улучшения условий работы.\n\nС уважением,\nКомпания Бюро 1440.",
    "review__answer-title": "Ответ представителя компании",
    "review__answer-date": "Март 2025",
    "review__title-privileges": "Преимущества и льготы",
    "tags__item (3)": "Своевременная оплата труда",
    "tags__item (4)": "Удобное расположение работы",
    "bt": "Полезный отзыв\n 0",
    "review__useful": "Полезный отзыв",
    "bt href": "https://dreamjob.ru/employers/130433?review_id=2386625",
    "bt (2)": "Ссылка на отзыв",
    "tags__item (5)": "Удаленная работа",
    "tags__item (6)": "Наличие кухни, места для обеда",
    "bt (4)": "Все 6",
    "tags__item (7)": "Медицинское страхование",
    "tags__item (8)": "Оплата больничного"
  }
]