[
  {
    "review": "Печатник\n...\nРаботаю меньше года Москва, июль 2025\n5,0\nЧто нравится?\nКреативная команда, интересные проекты,отличная атмосфера. Работать здесь удовольствие!Рекомендую.\nЧто можно улучшить?\nВсе и так просто супер.1000000 работодателей из 10.\nПреимущества и льготы\nСвоевременная оплата труда\nУдобное расположение работы\nНаличие кухни, места для обеда\nОплата больничного\nГибкий рабочий график\nПрофессиональное обучение\nМесто для парковки\nСистема наставничества\nВсе 8\nПолезный отзыв\n 0\nСсылка на отзыв\nОтветить от лица компании",
    "review__header-title": "Печатник",
    "share-block__item": "...",
    "tags__item": "Работаю меньше года",
    "tags__item (2)": "Москва, июль 2025",
    "dj-rating": "5,0",
    "review__title": "Что нравится?",
    "review__title (2)": "Что можно улучшить?",
    "review__title-privileges": "Преимущества и льготы",
    "tags__item (3)": "Своевременная оплата труда",
    "tags__item (4)": "Удобное расположение работы",
    "tags__item (5)": "Наличие кухни, места для обеда",
    "tags__item (6)": "Оплата больничного",
    "tags__item (7)": "Гибкий рабочий график",
    "tags__item (8)": "Профессиональное обучение",
    "tags__item (9)": "Место для парковки",
    "bt": "Все 8",
    "bt (2)": "Полезный отзыв\n 0",
    "review__useful": "Полезный отзыв",
    "bt href": "https://dreamjob.ru/employers/116942?review_id=3826485",
    "bt (3)": "Ссылка на отзыв",
    "bt href (2)": "https://dreamjob.ru/page/employers",
    "bt (4)": "Ответить от лица компании"
  },
  {
    "vacancies-banner__inner": "Вакансии в РПК Медиасфера",
    "vacancies-banner__all href": "https://dreamjob.ru/employers/116942/vakansii",
    "vacancies-banner__all": "Все\n 7",
    "d-md-none": "Все",
    "vacancies-banner__head": "Директор по персоналу (HRD)",
    "vacancies-banner__сity": "Москва",
    "vacancies-banner__salary": "250 000 - 250 000 ₽",
    "job-vacancy__currency": "₽",
    "bt-master href": "https://dreamjob.ru/employers/116942/vakansii/125942027",
    "bt-master": "Посмотреть вакансию",
    "vacancies-banner__head (2)": "Руководитель печатного цеха",
    "vacancies-banner__salary (2)": "150 000 - 200 000 ₽",
    "bt-master href (2)": "https://dreamjob.ru/employers/116942/vakansii/126747533",
    "vacancies-banner__head (3)": "Грузчик/Разнорабочий на производство",
    "vacancies-banner__salary (3)": "80 000 - 90 000 ₽",
    "bt-master href (3)": "https://dreamjob.ru/employers/116942/vakansii/121115615",
    "vacancies-banner__head (4)": "Сборщик рекламных конструкций/ Макетчик",
    "vacancies-banner__salary (4)": "120 000 - 130 000 ₽",
    "bt-master href (4)": "https://dreamjob.ru/employers/116942/vakansii/121654857",
    "vacancies-banner__head (5)": "Постпечатник / сборщик наружной рекламы",
    "vacancies-banner__salary (5)": "90 000 - 100 000 ₽",
    "bt-master href (5)": "https://dreamjob.ru/employers/116942/vakansii/126123458"
  },
  {
    "review": "Руководитель отдела широкоформатной печати и фрезеровки\n...\nРаботаю меньше года Москва, июль 2025\n5,0\nЧто нравится?\nОчень приятный коллектив и руководство. Все отзывчивые и всегда готовы помочь. Советую данную компанию к сотрудничеству.\nЧто можно улучшить?\nНароду бы побольше) иногда в моменты запары не хватает рук и надо работать шустрее.\nПреимущества и льготы\nСвоевременная оплата труда\nУдобное расположение работы\nОплата больничного\nПрофессиональное обучение\nМесто для парковки\nСистема наставничества\nКорпоративные мероприятия\nВсе 7\nПолезный отзыв\n 0\nСсылка на отзыв\nОтветить от лица компании",
    "review__header-title": "Руководитель отдела широкоформатной печати и фрезеровки",
    "share-block__item": "...",
    "tags__item": "Работаю меньше года",
    "tags__item (2)": "Москва, июль 2025",
    "dj-rating": "5,0",
    "review__title": "Что нравится?",
    "review__title (2)": "Что можно улучшить?",
    "review__title-privileges": "Преимущества и льготы",
    "tags__item (3)": "Своевременная оплата труда",
    "tags__item (4)": "Удобное расположение работы",
    "tags__item (5)": "Оплата больничного",
    "tags__item (6)": "Профессиональное обучение",
    "tags__item (7)": "Место для парковки",
    "tags__item (8)": "Система наставничества",
    "tags__item (9)": "Корпоративные мероприятия",
    "bt": "Все 7",
    "bt (2)": "Полезный отзыв\n 0",
    "review__useful": "Полезный отзыв",
    "bt href": "https://dreamjob.ru/employers/116942?review_id=3826440",
    "bt (3)": "Ссылка на отзыв",
    "bt href (2)": "https://dreamjob.ru/page/employers",
    "bt (4)": "Ответить от лица компании"
  },
  {
    "swiper-slide": "зарплата\n(9)"
  },
  {
    "review": "Директор по производству\n...\nРаботал меньше года Москва, май 2025\n5,0\nЧто нравится?\nХороший коллектив, много работы. Владельцы молодцы. Жаль не прислушиваются к предложениям.\nЧто можно улучшить?\nОрганизацию труда. Т.к. новые сотрудники теряются в обилии задач и не справляются\nПреимущества и льготы\nМесто для парковки\nПолезный отзыв\n 0\nСсылка на отзыв\nОтветить от лица компании",
    "review__header-title": "Директор по производству",
    "share-block__item": "...",
    "tags__item": "Работал меньше года",
    "tags__item (2)": "Москва, май 2025",
    "dj-rating": "5,0",
    "review__title": "Что нравится?",
    "review__title (2)": "Что можно улучшить?",
    "review__title-privileges": "Преимущества и льготы",
    "tags__item (3)": "Место для парковки",
    "bt (2)": "Полезный отзыв\n 0",
    "review__useful": "Полезный отзыв",
    "bt href": "https://dreamjob.ru/employers/116942?review_id=3686204",
    "bt (3)": "Ссылка на отзыв",
    "bt href (2)": "https://dreamjob.ru/page/employers",
    "bt (4)": "Ответить от лица компании"
  },
  {
    "vacancies-banner__inner": "Вакансии в РПК Медиасфера",
    "vacancies-banner__all href": "https://dreamjob.ru/employers/116942/vakansii",
    "vacancies-banner__all": "Все\n 7",
    "d-md-none": "Все",
    "vacancies-banner__head": "Директор по персоналу (HRD)",
    "vacancies-banner__сity": "Москва",
    "vacancies-banner__salary": "250 000 - 250 000 ₽",
    "job-vacancy__currency": "₽",
    "bt-master href": "https://dreamjob.ru/employers/116942/vakansii/125942027",
    "bt-master": "Посмотреть вакансию",
    "vacancies-banner__head (2)": "Руководитель печатного цеха",
    "vacancies-banner__salary (2)": "150 000 - 200 000 ₽",
    "bt-master href (2)": "https://dreamjob.ru/employers/116942/vakansii/126747533",
    "vacancies-banner__head (3)": "Грузчик/Разнорабочий на производство",
    "vacancies-banner__salary (3)": "80 000 - 90 000 ₽",
    "bt-master href (3)": "https://dreamjob.ru/employers/116942/vakansii/121115615",
    "vacancies-banner__head (4)": "Сборщик рекламных конструкций/ Макетчик",
    "vacancies-banner__salary (4)": "120 000 - 130 000 ₽",
    "bt-master href (4)": "https://dreamjob.ru/employers/116942/vakansii/121654857",
    "vacancies-banner__head (5)": "Постпечатник / сборщик наружной рекламы",
    "vacancies-banner__salary (5)": "90 000 - 100 000 ₽",
    "bt-master href (5)": "https://dreamjob.ru/employers/116942/vakansii/126123458"
  },
  {
    "review": "Административный ассистент\n...\nРаботал 3-5 лет Москва, декабрь 2024\n3,8\nЧто нравится?\nСвоевременная оплата труда, комфортный светлый офис, график работы.\nЧто можно улучшить?\nДМС, короткий рабочий день в пред праздничные дни, пятницу.\nПреимущества и льготы\nСвоевременная оплата труда\nУдобное расположение работы\nПолезный отзыв\n 0\nСсылка на отзыв\nОтветить от лица компании",
    "review__header-title": "Административный ассистент",
    "share-block__item": "...",
    "tags__item": "Работал 3-5 лет",
    "tags__item (2)": "Москва, декабрь 2024",
    "dj-rating": "3,8",
    "review__title": "Что нравится?",
    "review__title (2)": "Что можно улучшить?",
    "review__title-privileges": "Преимущества и льготы",
    "tags__item (3)": "Своевременная оплата труда",
    "tags__item (4)": "Удобное расположение работы",
    "bt (2)": "Полезный отзыв\n 0",
    "review__useful": "Полезный отзыв",
    "bt href": "https://dreamjob.ru/employers/116942?review_id=3241856",
    "bt (3)": "Ссылка на отзыв",
    "bt href (2)": "https://dreamjob.ru/page/employers",
    "bt (4)": "Ответить от лица компании"
  },
  {
    "review": "Грузчик-разнорабочий\n...\nРаботал 1-2 года Москва, декабрь 2024\n1,0\nЧто нравится?\nРаботал около года по специальности макетчик-монтажник-грузчик-разнорабочий. Итог:\nЭто лучшее место на моем опыте, что я видел! Не ищите подводных камней)\nВ этой организации лучшие условия! И никаких нарушений! В раздевалках нет камер, отсутствуют штрафы, санитарные нормы на уровне. ТБ и ПБ исполняются, что сразу бросается в глаза. Удобное расположение кухни, и в принципе отличный ремонт, чистота и порядок.\nОтдел кадров на высоте. Сотрудники выполняют свою работу на совесть. Трудовой договор дают сразу и на руки. Ничего лишнего вы не подписываете. Переработки и ночные оплачиваются в полном соответствии с законом.\nРаботать в будете строго по трудовым обязанностям, установленному графику: ничего сверх от вас требовать не будут. Зарплата ВСЕГДА день в день, минута в минуту. Спасибо ответственным за это.\nВсе обещания и договоренности выполняются беспрекословно и в срок! В управлении следят за языком, знают о корпоративной этике. Отвечают за слова, не обманывают. Отсутствует ксенофобия, уважаются права ( во всех смыслах).\nНедовольных единицы, большинству (почти всех) всё устраивает. Контингент приезжих работает также без нарушений, ими и их незнанием законов РФ никто не пользуется.\nЧто можно улучшить?\nИз минусов - фирма не развивается по всем указанным выше пунктам. Наверное потому что фирма итак на высоте.\nПолезный отзыв\n 4\nСсылка на отзыв\nОтветить от лица компании",
    "review__header-title": "Грузчик-разнорабочий",
    "share-block__item": "...",
    "tags__item": "Работал 1-2 года",
    "tags__item (2)": "Москва, декабрь 2024",
    "dj-rating": "1,0",
    "review__title": "Что нравится?",
    "review__title (2)": "Что можно улучшить?",
    "bt (2)": "Полезный отзыв\n 4",
    "review__useful": "Полезный отзыв",
    "bt href": "https://dreamjob.ru/employers/116942?review_id=3215595",
    "bt (3)": "Ссылка на отзыв",
    "bt href (2)": "https://dreamjob.ru/page/employers",
    "bt (4)": "Ответить от лица компании"
  },
  {
    "review": "Менеджер по работе с клиентами\n...\nРаботаю 1-2 года Москва, ноябрь 2024\n5,0\nЧто нравится?\nРабота интересная, привлекает разнообразием проектов и тем, что нет готовых шаблонных решений.\nВысокий уровень дохода.\nСовременный комфортный офис в бизнес центре.\nАктивная корпоративная жизнь, спасибо руководству за организацию тимбилдингов.\nЧто можно улучшить?\nВсе отлично, есть чай/кофе/вода в неограниченном количестве, можно заказать все, что необходимо для комфортной работы.\nПреимущества и льготы\nСвоевременная оплата труда\nУдобное расположение работы\nОплата мобильной связи\nКорпоративные мероприятия\nВсе 4\nПолезный отзыв\n 0\nСсылка на отзыв\nОтветить от лица компании",
    "review__header-title": "Менеджер по работе с клиентами",
    "share-block__item": "...",
    "tags__item": "Работаю 1-2 года",
    "tags__item (2)": "Москва, ноябрь 2024",
    "dj-rating": "5,0",
    "review__title": "Что нравится?",
    "review__title (2)": "Что можно улучшить?",
    "review__title-privileges": "Преимущества и льготы",
    "tags__item (3)": "Своевременная оплата труда",
    "tags__item (4)": "Удобное расположение работы",
    "tags__item (5)": "Оплата мобильной связи",
    "tags__item (6)": "Корпоративные мероприятия",
    "bt": "Все 4",
    "bt (2)": "Полезный отзыв\n 0",
    "review__useful": "Полезный отзыв",
    "bt href": "https://dreamjob.ru/employers/116942?review_id=3187863",
    "bt (3)": "Ссылка на отзыв",
    "bt href (2)": "https://dreamjob.ru/page/employers",
    "bt (4)": "Ответить от лица компании"
  },
  {
    "review": "Помощник бухгалтера\n...\nРаботаю меньше года Москва, январь 2024\n5,0\nЧто нравится?\nРаботаю помощником бухгалтера третий месяц в компании, меня работа устраивает. Все официально, никакого хамства со стороны начальства и надменных высказываний. К сотрудникам относятся уважительно, при необходимости идут на встречу. По деньгам вполне нормально, главное вовремя.\nЧто можно улучшить?\nХотелось бы наладить удаленный формат работы, особенно когда болеешь\nПреимущества и льготы\nСвоевременная оплата труда\nУдобное расположение работы\nНаличие кухни, места для обеда\nОплата больничного\nКорпоративные мероприятия\nВсе 5\nПолезный отзыв\n 0\nСсылка на отзыв\nОтветить от лица компании",
    "review__header-title": "Помощник бухгалтера",
    "share-block__item": "...",
    "tags__item": "Работаю меньше года",
    "tags__item (2)": "Москва, январь 2024",
    "dj-rating": "5,0",
    "review__title": "Что нравится?",
    "review__title (2)": "Что можно улучшить?",
    "review__title-privileges": "Преимущества и льготы",
    "tags__item (3)": "Своевременная оплата труда",
    "tags__item (4)": "Удобное расположение работы",
    "tags__item (5)": "Наличие кухни, места для обеда",
    "tags__item (6)": "Оплата больничного",
    "tags__item (7)": "Корпоративные мероприятия",
    "bt": "Все 5",
    "bt (2)": "Полезный отзыв\n 0",
    "review__useful": "Полезный отзыв",
    "bt href": "https://dreamjob.ru/employers/116942?review_id=2309814",
    "bt (3)": "Ссылка на отзыв",
    "bt href (2)": "https://dreamjob.ru/page/employers",
    "bt (4)": "Ответить от лица компании"
  },
  {
    "review": "Альпинист\n...\nРаботал меньше года Москва, декабрь 2023\n5,0\nЧто нравится?\nотработал в данной компании почти год, все необходимое для работы предоставляют, выдают все новое - оборудование, крепление, защиту, одежду, обувь. При увольнении все денежные выплаты и компенсацию за отпуск получил.\nЧто можно улучшить?\nНет дмс для сотрудников, было бы не плохо чтобы сделали. Строгая дисциплина.\nПреимущества и льготы\nСвоевременная оплата труда\nУдобное расположение работы\nНаличие кухни, места для обеда\nКорпоративные мероприятия\nВсе 4\nПолезный отзыв\n 0\nСсылка на отзыв\nОтветить от лица компании",
    "review__header-title": "Альпинист",
    "share-block__item": "...",
    "tags__item": "Работал меньше года",
    "tags__item (2)": "Москва, декабрь 2023",
    "dj-rating": "5,0",
    "review__title": "Что нравится?",
    "review__title (2)": "Что можно улучшить?",
    "review__title-privileges": "Преимущества и льготы",
    "tags__item (3)": "Своевременная оплата труда",
    "tags__item (4)": "Удобное расположение работы",
    "tags__item (5)": "Наличие кухни, места для обеда",
    "tags__item (6)": "Корпоративные мероприятия",
    "bt": "Все 4",
    "bt (2)": "Полезный отзыв\n 0",
    "review__useful": "Полезный отзыв",
    "bt href": "https://dreamjob.ru/employers/116942?review_id=2201015",
    "bt (3)": "Ссылка на отзыв",
    "bt href (2)": "https://dreamjob.ru/page/employers",
    "bt (4)": "Ответить от лица компании"
  },
  {
    "bt (2)": "Посмотреть все зарплаты (3)",
    "bt href": "https://dreamjob.ru/employers/116942/zarplata",
    "job-vacancy__currency": "₽",
    "swiper-slide": "Посмотреть\nеще зарплаты"
  },
  {
    "review": "Фрезеровщик\n...\nРаботаю 3-5 лет Москва, ноябрь 2023\n5,0\nЧто нравится?\nРаботаю в этой компании уже почти 3 года. Есть официальное оформление для граждан снг, деньги платят всегда вовремя, выдают спец одежду.\nЧто можно улучшить?\nНедостатки: строгая дисциплина и высокие требования к качеству работы.\nПреимущества и льготы\nСвоевременная оплата труда\nУдобное расположение работы\nНаличие кухни, места для обеда\nОплата больничного\nКорпоративные мероприятия\nВсе 5\nПолезный отзыв\n 0\nСсылка на отзыв\nОтветить от лица компании",
    "review__header-title": "Фрезеровщик",
    "share-block__item": "...",
    "tags__item": "Работаю 3-5 лет",
    "tags__item (2)": "Москва, ноябрь 2023",
    "dj-rating": "5,0",
    "review__title": "Что нравится?",
    "review__title (2)": "Что можно улучшить?",
    "review__title-privileges": "Преимущества и льготы",
    "tags__item (3)": "Своевременная оплата труда",
    "tags__item (4)": "Удобное расположение работы",
    "tags__item (5)": "Наличие кухни, места для обеда",
    "tags__item (6)": "Оплата больничного",
    "tags__item (7)": "Корпоративные мероприятия",
    "bt": "Все 5",
    "bt (2)": "Полезный отзыв\n 0",
    "review__useful": "Полезный отзыв",
    "bt href": "https://dreamjob.ru/employers/116942?review_id=2129772",
    "bt (3)": "Ссылка на отзыв",
    "bt href (2)": "https://dreamjob.ru/page/employers",
    "bt (4)": "Ответить от лица компании"
  },
  {
    "review": "Дизайнер\n...\nРаботаю 5-10 лет Москва, ноябрь 2023\n5,0\nЧто нравится?\nЯ проработала в этой компании 7 лет, когда только устроилась, никаких отзывов не было. Компания порядочная, руководители вменяемые и лояльные, коллектив отличный. Не жалею что работала здесь долгие года, получила колоссальный опыт.\nЧто можно улучшить?\nХотелось бы, чтобы было ДМС, недавно слышала от бывшей коллеги, что руководители двигаются в этом направлении.\nПреимущества и льготы\nСвоевременная оплата труда\nУдобное расположение работы\nНаличие кухни, места для обеда\nОплата больничного\nКорпоративные мероприятия\nВсе 5\nПолезный отзыв\n 0\nСсылка на отзыв\nОтветить от лица компании",
    "review__header-title": "Дизайнер",
    "share-block__item": "...",
    "tags__item": "Работаю 5-10 лет",
    "tags__item (2)": "Москва, ноябрь 2023",
    "dj-rating": "5,0",
    "review__title": "Что нравится?",
    "review__title (2)": "Что можно улучшить?",
    "review__title-privileges": "Преимущества и льготы",
    "tags__item (3)": "Своевременная оплата труда",
    "tags__item (4)": "Удобное расположение работы",
    "tags__item (5)": "Наличие кухни, места для обеда",
    "tags__item (6)": "Оплата больничного",
    "tags__item (7)": "Корпоративные мероприятия",
    "bt": "Все 5",
    "bt (2)": "Полезный отзыв\n 0",
    "review__useful": "Полезный отзыв",
    "bt href": "https://dreamjob.ru/employers/116942?review_id=2120748",
    "bt (3)": "Ссылка на отзыв",
    "bt href (2)": "https://dreamjob.ru/page/employers",
    "bt (4)": "Ответить от лица компании"
  }
]