[
  {
    "review": "Специалист по контекстной рекламе\n...\nРаботаю 1-2 года Москва, август 2025\n2,2\nЧто нравится?\nКаким-то чудом мне согласовали удалёнку. Зарплата по графику\nЧто можно улучшить?\nРаботал в нескольких отделах.\nВ первом - удивительно некомпетентные ребята. Ничего не знают, не понимают, часами обсуждают на созвонах простейшие вещи. На созвоны собирались всем отделом, даже если большая его часть вообще не имеет отношения к вопросу.\nВо втором - фантастически закостенелые и неподвижные. Используют устаревшие методы работы. Тут без деталей, но молодым и активным там делать нечего.\n\nБезопасники - вообще особенные люди в данной компании. Корпоративный ВПН, аутлук, запрет на гугл-документы. \"Палки в колёса\" - на каждом шагу.\nРеальная история. Отвалился пароль от ВПН. Чтобы его восстановить, нужно написать в корпоративный мессенджер. Чтобы в него войти (в мессенджер), нужно подтвердить вход с помощью кода, который присылают на почту. Чтобы попасть в почту, нужен пароль от ВПН...\nТак всё в компании. И, не поверите, каждый день. Я видел корпорации с некомпетентным руководством и супер-медленными процессами, но это - нечто\nПреимущества и льготы\nУдаленная работа\nКорпоративные мероприятия\nПолезный отзыв\n 5\nСсылка на отзыв\nОтветить от лица компании",
    "review__header-title": "Специалист по контекстной рекламе",
    "share-block__item": "...",
    "tags__item": "Работаю 1-2 года",
    "tags__item (2)": "Москва, август 2025",
    "dj-rating": "2,2",
    "review__title": "Что нравится?",
    "review__title (2)": "Что можно улучшить?",
    "review__title-privileges": "Преимущества и льготы",
    "tags__item (3)": "Удаленная работа",
    "tags__item (4)": "Корпоративные мероприятия",
    "bt": "Полезный отзыв\n 5",
    "review__useful": "Полезный отзыв",
    "bt href": "https://dreamjob.ru/employers/102326?review_id=3929689",
    "bt (2)": "Ссылка на отзыв",
    "bt href (2)": "https://dreamjob.ru/page/employers",
    "bt (3)": "Ответить от лица компании"
  },
  {
    "vacancies-banner__inner": "Вакансии в А101",
    "vacancies-banner__all href": "https://dreamjob.ru/employers/102326/vakansii",
    "vacancies-banner__all": "Все\n 63",
    "d-md-none": "Все",
    "vacancies-banner__head": "Менеджер направления клиентских коммуникаций",
    "vacancies-banner__сity": "Москва",
    "bt-master href": "https://dreamjob.ru/employers/102326/vakansii/126062077",
    "bt-master": "Посмотреть вакансию",
    "vacancies-banner__head (2)": "Главный инженер проекта (котельные)",
    "bt-master href (2)": "https://dreamjob.ru/employers/102326/vakansii/121507274",
    "vacancies-banner__head (3)": "Менеджер по работе с арендаторами",
    "bt-master href (3)": "https://dreamjob.ru/employers/102326/vakansii/126776286",
    "vacancies-banner__head (4)": "Главный инженер проекта по сетям",
    "bt-master href (4)": "https://dreamjob.ru/employers/102326/vakansii/124012683",
    "vacancies-banner__head (5)": "Главный специалист ЭОМ",
    "bt-master href (5)": "https://dreamjob.ru/employers/102326/vakansii/125688616"
  },
  {
    "review": "Руководитель строительства\n...\nРаботал меньше года Москва, июнь 2025\n2,8\nЧто нравится?\nОтносительно небольшое расстояние от дома до работы. Время в пути менее часа.\nЧто можно улучшить?\nДа во многом есть куда развиваться, но главное- руководству на объектах необходимо научиться правильно управлять коллективом.\nПреимущества и льготы\nСвоевременная оплата труда\nУдобное расположение работы\nНаличие кухни, места для обеда\nКорпоративные мероприятия\nВсе 4\nПолезный отзыв\n 2\nСсылка на отзыв\nОтветить от лица компании",
    "review__header-title": "Руководитель строительства",
    "share-block__item": "...",
    "tags__item": "Работал меньше года",
    "tags__item (2)": "Москва, июнь 2025",
    "dj-rating": "2,8",
    "review__title": "Что нравится?",
    "review__title (2)": "Что можно улучшить?",
    "review__title-privileges": "Преимущества и льготы",
    "tags__item (3)": "Своевременная оплата труда",
    "tags__item (4)": "Удобное расположение работы",
    "bt": "Полезный отзыв\n 2",
    "review__useful": "Полезный отзыв",
    "bt href": "https://dreamjob.ru/employers/102326?review_id=3781277",
    "bt (2)": "Ссылка на отзыв",
    "bt href (2)": "https://dreamjob.ru/page/employers",
    "bt (3)": "Ответить от лица компании",
    "tags__item (5)": "Наличие кухни, места для обеда",
    "tags__item (6)": "Корпоративные мероприятия",
    "bt (4)": "Все 4"
  },
  {
    "swiper-slide": "зарплата\n(12)"
  },
  {
    "review": "Отзыв сотрудника\n...\nРаботал 1-2 года Москва, июнь 2025\n2,2\nЧто нравится?\nБыла возможность работать удаленно, было хорошее руководство пока его не заменили новым, часть коллектива замечательные люди, корпоратив на день строителя всегда хороший, ДМС, зп без задержек, индексация зп ежегодная, премия по итогам года\nЧто можно улучшить?\nАйтишники и отдел кадров через пару месяцев начнут вас игнорировать, ответы на многие вопросы придется искать самостоятельно. Техническое обслуживание очень страдает и что-то не работать у вас будет постоянно, задачи ставятся спустя рукава, часть информации придется ходить и собирать у всех кто хоть что-то может знать. Как считается премия так и осталось вопросом. Часть коллектива с гнильцой или некомпетентные, руководству бывает наплевать на вас, не во всех отделах так, как повезет. Вырасти внутри компании нереально, на мой взгляд. Субботник раз в год на который вам придется ездить за мкад, это не оплачивается. Переработки есть, некоторые работают до ночи, если вы против переработок - начальству это не понравится. Будете время от времени созваниваться на час из-за вопроса который можно было решить за 5 минут. Текучка есть\nПреимущества и льготы\nСвоевременная оплата труда\nУдаленная работа\nНаличие кухни, места для обеда\nМедицинское страхование\nОплата больничного\nПрофессиональное обучение\nКорпоративные мероприятия\nВсе 7\nПолезный отзыв\n 8\nСсылка на отзыв\nОтветить от лица компании",
    "review__header-title": "Отзыв сотрудника",
    "share-block__item": "...",
    "tags__item": "Работал 1-2 года",
    "tags__item (2)": "Москва, июнь 2025",
    "dj-rating": "2,2",
    "review__title": "Что нравится?",
    "review__title (2)": "Что можно улучшить?",
    "review__title-privileges": "Преимущества и льготы",
    "tags__item (3)": "Своевременная оплата труда",
    "tags__item (4)": "Удаленная работа",
    "bt": "Полезный отзыв\n 8",
    "review__useful": "Полезный отзыв",
    "bt href": "https://dreamjob.ru/employers/102326?review_id=3742987",
    "bt (2)": "Ссылка на отзыв",
    "bt href (2)": "https://dreamjob.ru/page/employers",
    "bt (3)": "Ответить от лица компании",
    "tags__item (5)": "Наличие кухни, места для обеда",
    "tags__item (6)": "Медицинское страхование",
    "bt (4)": "Все 7",
    "tags__item (7)": "Оплата больничного"
  },
  {
    "vacancies-banner__inner": "Вакансии в А101",
    "vacancies-banner__all href": "https://dreamjob.ru/employers/102326/vakansii",
    "vacancies-banner__all": "Все\n 63",
    "d-md-none": "Все",
    "vacancies-banner__head": "Менеджер направления клиентских коммуникаций",
    "vacancies-banner__сity": "Москва",
    "bt-master href": "https://dreamjob.ru/employers/102326/vakansii/126062077",
    "bt-master": "Посмотреть вакансию",
    "vacancies-banner__head (2)": "Главный инженер проекта (котельные)",
    "bt-master href (2)": "https://dreamjob.ru/employers/102326/vakansii/121507274",
    "vacancies-banner__head (3)": "Менеджер по работе с арендаторами",
    "bt-master href (3)": "https://dreamjob.ru/employers/102326/vakansii/126776286",
    "vacancies-banner__head (4)": "Главный инженер проекта по сетям",
    "bt-master href (4)": "https://dreamjob.ru/employers/102326/vakansii/124012683",
    "vacancies-banner__head (5)": "Главный специалист ЭОМ",
    "bt-master href (5)": "https://dreamjob.ru/employers/102326/vakansii/125688616"
  },
  {
    "review": "Менеджер по передаче объектов недвижимости и гарантийному обслуживанию\n...\nРаботаю меньше года Москва, апрель 2025\n2,8\nЧто нравится?\nПостоянный трудовой договор , ДМС есть , но оператора поменяли и условия по нему стали не очень , униформу выдают круглогодично : поло , куртки , джемперы, корпоративы не очень … Больше плюсов я не нашел\nЧто можно улучшить?\nМенеджер по передаче отдела заселения выполняет свои функции , функции менеджера - оформителя по документам, функции менеджера управляющей компании и менеджера по продажам за оклад который ниже рынка постпродажного обслуживания московских застройщиков , ежегодной индексации зарплаты нет, рассчитывать на квартальную премию тоже не приходится , т.к за объект переданный с замечаниям премия не начисляется , а с введением аудиобейджей вашу квартальную премию сократят за непроговоренный чек - лист и за то, что вы не предложили услуги партнеров , жесткий тайминг встреч , учитывая обьемы компании окончательно вас разочарует. Хорошенько подумайте и верьте только тому , что написано в договоре\nПреимущества и льготы\nСвоевременная оплата труда\nНаличие кухни, места для обеда\nМедицинское страхование\nОплата больничного\nКорпоративные мероприятия\nВсе 5\nПолезный отзыв\n 1\nСсылка на отзыв\nОтветить от лица компании",
    "review__header-title": "Менеджер по передаче объектов недвижимости и гарантийному обслуживанию",
    "share-block__item": "...",
    "tags__item": "Работаю меньше года",
    "tags__item (2)": "Москва, апрель 2025",
    "dj-rating": "2,8",
    "review__title": "Что нравится?",
    "review__title (2)": "Что можно улучшить?",
    "review__title-privileges": "Преимущества и льготы",
    "tags__item (3)": "Своевременная оплата труда",
    "tags__item (4)": "Наличие кухни, места для обеда",
    "bt": "Полезный отзыв\n 1",
    "review__useful": "Полезный отзыв",
    "bt href": "https://dreamjob.ru/employers/102326?review_id=3596814",
    "bt (2)": "Ссылка на отзыв",
    "bt href (2)": "https://dreamjob.ru/page/employers",
    "bt (3)": "Ответить от лица компании",
    "tags__item (5)": "Медицинское страхование",
    "tags__item (6)": "Оплата больничного",
    "bt (4)": "Все 5",
    "tags__item (7)": "Корпоративные мероприятия"
  },
  {
    "review": "Инженер-проектировщик ВК\n...\nРаботаю 1-2 года Москва, апрель 2025\n1,3\nЧто нравится?\nВозможность работать удаленно, белая заработная плата, оплата больничного\nЧто можно улучшить?\nУвеличить сроки проектирования и снизить нагрузку на проектировщиков. Дать время на повышение квалификации: курсы, тренинги, посещение выставок. Организовать командировки на объекты проектирования.\nОплачивать удаленным сотрудникам проезд и проживание в случае их приезда на день строителя или новый год. Вернуть выплату премий, так как такой сверхинтенсивный режим работы должен хорошо оплачиваться.\nПреимущества и льготы\nСвоевременная оплата труда\nУдаленная работа\nОплата больничного\nВсе 3\nПолезный отзыв\n 4\nСсылка на отзыв\nОтветить от лица компании",
    "review__header-title": "Инженер-проектировщик ВК",
    "share-block__item": "...",
    "tags__item": "Работаю 1-2 года",
    "tags__item (2)": "Москва, апрель 2025",
    "dj-rating": "1,3",
    "review__title": "Что нравится?",
    "review__title (2)": "Что можно улучшить?",
    "review__title-privileges": "Преимущества и льготы",
    "tags__item (3)": "Своевременная оплата труда",
    "tags__item (4)": "Удаленная работа",
    "bt": "Полезный отзыв\n 4",
    "review__useful": "Полезный отзыв",
    "bt href": "https://dreamjob.ru/employers/102326?review_id=3556800",
    "bt (2)": "Ссылка на отзыв",
    "bt href (2)": "https://dreamjob.ru/page/employers",
    "bt (3)": "Ответить от лица компании",
    "tags__item (5)": "Оплата больничного",
    "bt (4)": "Все 3"
  },
  {
    "review": "Отзыв сотрудника\n...\nРаботал меньше года Москва, февраль 2025\n2,7\nЧто нравится?\nГрафик работы, ДМС, удаленность офиса от дома,премии, много проектов\nЧто можно улучшить?\nОчень сильно хромает коммуникация между отделами, нет четкого понимания,кто за что отвечает. Всегда тебя хотят сделать крайнего . Сотрудников не ценят,даже за хорошие показатели,все как пушечное мясо. Обязанностей много ,зп не высокое и свою премию нужно еще заслужить ,всегда ищут повод тебя оштрафовать. Большая текучка,ценят только тех ,кто ходит на четвереньках.\nПреимущества и льготы\nСвоевременная оплата труда\nМедицинское страхование\nПолезный отзыв\n 15\nСсылка на отзыв\nОтветить от лица компании",
    "review__header-title": "Отзыв сотрудника",
    "share-block__item": "...",
    "tags__item": "Работал меньше года",
    "tags__item (2)": "Москва, февраль 2025",
    "dj-rating": "2,7",
    "review__title": "Что нравится?",
    "review__title (2)": "Что можно улучшить?",
    "review__title-privileges": "Преимущества и льготы",
    "tags__item (3)": "Своевременная оплата труда",
    "tags__item (4)": "Медицинское страхование",
    "bt": "Полезный отзыв\n 15",
    "review__useful": "Полезный отзыв",
    "bt href": "https://dreamjob.ru/employers/102326?review_id=3386840",
    "bt (2)": "Ссылка на отзыв",
    "bt href (2)": "https://dreamjob.ru/page/employers",
    "bt (3)": "Ответить от лица компании"
  },
  {
    "review": "Отзыв сотрудника\n...\nРаботал 1-2 года Москва, февраль 2025\n1,7\nЧто нравится?\nДля работы предоставляют все необходимое, есть ДМС после 3 месяцев ( но это больше пафос а не ДМС )\nЧто можно улучшить?\nЗП не большая для того что приходиться делать, ещё и уменьшить могут премию в виде штрафов,про которые при трудоустройстве не говорят, в активную передачу объектов сложно выбрать время для обеда, работаешь без остановки до самого окончания рабочей смены, если не будешь друг на друга стучать то долго не продержишься, коллектив подобран таким образом, куча не нужных и не входящих в твой функционал работы задач, обучения тоже нет , вникать самим, плюсов работы нет , зп не поднимается а может наоборот снизиться\nПреимущества и льготы\nСвоевременная оплата труда\nКорпоративные мероприятия\nПолезный отзыв\n 13\nСсылка на отзыв\nОтветить от лица компании",
    "review__header-title": "Отзыв сотрудника",
    "share-block__item": "...",
    "tags__item": "Работал 1-2 года",
    "tags__item (2)": "Москва, февраль 2025",
    "dj-rating": "1,7",
    "review__title": "Что нравится?",
    "review__title (2)": "Что можно улучшить?",
    "review__title-privileges": "Преимущества и льготы",
    "tags__item (3)": "Своевременная оплата труда",
    "tags__item (4)": "Корпоративные мероприятия",
    "bt": "Полезный отзыв\n 13",
    "review__useful": "Полезный отзыв",
    "bt href": "https://dreamjob.ru/employers/102326?review_id=3364926",
    "bt (2)": "Ссылка на отзыв",
    "bt href (2)": "https://dreamjob.ru/page/employers",
    "bt (3)": "Ответить от лица компании"
  },
  {
    "review": "Отзыв сотрудника\n...\nРаботаю меньше года Москва, январь 2025\n2,0\nЧто нравится?\nСтабильная выплата з/п, месторасположение объектов не далеко от метро,ДМС,корпоративные мероприятия для сотрудников\nЧто можно улучшить?\nРаботать тяжело,ставят очень много задач,задержки на работе не оплачиваются(а они бывают довольно часто в период активной передачи объектов),очень клиентоориентированное руководство,поэтому в компании все условия для клиентов,но не для сотрудников,коллектив токсичный,при сменном графике работы возможность меняться сменами отсутствует,отпуск для сотрудника делают как удобно руководству, на собеседовании много моментов не говорят,чтобы не спугнуть кандидата\nПреимущества и льготы\nСвоевременная оплата труда\nМедицинское страхование\nКорпоративные мероприятия\nВсе 3\nПолезный отзыв\n 13\nСсылка на отзыв\nОтветить от лица компании",
    "review__header-title": "Отзыв сотрудника",
    "share-block__item": "...",
    "tags__item": "Работаю меньше года",
    "tags__item (2)": "Москва, январь 2025",
    "dj-rating": "2,0",
    "review__title": "Что нравится?",
    "review__title (2)": "Что можно улучшить?",
    "review__title-privileges": "Преимущества и льготы",
    "tags__item (3)": "Своевременная оплата труда",
    "tags__item (4)": "Медицинское страхование",
    "bt": "Полезный отзыв\n 13",
    "review__useful": "Полезный отзыв",
    "bt href": "https://dreamjob.ru/employers/102326?review_id=3355034",
    "bt (2)": "Ссылка на отзыв",
    "bt href (2)": "https://dreamjob.ru/page/employers",
    "bt (3)": "Ответить от лица компании",
    "tags__item (5)": "Корпоративные мероприятия",
    "bt (4)": "Все 3"
  },
  {
    "bt": "Посмотреть все зарплаты (33)",
    "bt href": "https://dreamjob.ru/employers/102326/zarplata",
    "swiper-slide": "Посмотреть\nеще зарплаты"
  },
  {
    "review": "Отзыв сотрудника\n...\nРаботал меньше года Москва, январь 2025\n2,5\nЧто нравится?\nНе так уж много бюрократии\nГенеральный директор за клиента\nКорпоративная культура в стадии зарождения, но будет\nОбещают новый офис\nЧто можно улучшить?\nИз соцпакета только ДМС\nНизкий уровень всего ощущается во всем: крики и ругань на встречах, очень-очень старый офис, hr очень многого не договаривают при приеме\nНе рекомендую\nПреимущества и льготы\nСвоевременная оплата труда\nМедицинское страхование\nОплата больничного\nКорпоративные мероприятия\nВсе 4\nПолезный отзыв\n 9\nСсылка на отзыв\nОтветить от лица компании",
    "review__header-title": "Отзыв сотрудника",
    "share-block__item": "...",
    "tags__item": "Работал меньше года",
    "tags__item (2)": "Москва, январь 2025",
    "dj-rating": "2,5",
    "review__title": "Что нравится?",
    "review__title (2)": "Что можно улучшить?",
    "review__title-privileges": "Преимущества и льготы",
    "tags__item (3)": "Своевременная оплата труда",
    "tags__item (4)": "Медицинское страхование",
    "bt": "Полезный отзыв\n 9",
    "review__useful": "Полезный отзыв",
    "bt href": "https://dreamjob.ru/employers/102326?review_id=3284134",
    "bt (2)": "Ссылка на отзыв",
    "bt href (2)": "https://dreamjob.ru/page/employers",
    "bt (3)": "Ответить от лица компании",
    "tags__item (5)": "Оплата больничного",
    "tags__item (6)": "Корпоративные мероприятия",
    "bt (4)": "Все 4"
  },
  {
    "review": "Специалист клиентского отдела\n...\nРаботал 1-2 года Москва, январь 2025\n1,0\nЧто нравится?\nНаличие ДМС, вовремя оплачивали зарплату, больше плюсов не увидела\nЧто можно улучшить?\nВ компании отсутствуют обеденные перерывы, повезло, если удастся сбегать на 7 минут перекусить, пока никто не пришел.\nМного непонятных правил, полное отсутствие дисциплины внутри коллектива, праздничные дни не оплачивают от слова совсем, но работать будете). Захотите карьерного роста - на должности « специалист клиентского отдела», вы будете никому не нужны. И нужно увольняться после 20-го числа, а то премию 100% заберут себе)\nПреимущества и льготы\nСвоевременная оплата труда\nНаличие кухни, места для обеда\nМедицинское страхование\nВсе 3\nПолезный отзыв\n 13\nСсылка на отзыв\nОтветить от лица компании",
    "review__header-title": "Специалист клиентского отдела",
    "share-block__item": "...",
    "tags__item": "Работал 1-2 года",
    "tags__item (2)": "Москва, январь 2025",
    "dj-rating": "1,0",
    "review__title": "Что нравится?",
    "review__title (2)": "Что можно улучшить?",
    "review__title-privileges": "Преимущества и льготы",
    "tags__item (3)": "Своевременная оплата труда",
    "tags__item (4)": "Наличие кухни, места для обеда",
    "bt": "Полезный отзыв\n 13",
    "review__useful": "Полезный отзыв",
    "bt href": "https://dreamjob.ru/employers/102326?review_id=3283986",
    "bt (2)": "Ссылка на отзыв",
    "bt href (2)": "https://dreamjob.ru/page/employers",
    "bt (3)": "Ответить от лица компании",
    "tags__item (5)": "Медицинское страхование",
    "bt (4)": "Все 3"
  }
]