[
  {
    "review": "Кассир\n...\nРаботал меньше года Москва, октябрь 2025\n1,7\nЧто нравится?\nСвоевременная оплата труда\nЕсть большая комната отдыха\nОбучение в виде тестов, которые надо проходить.\nЧто можно улучшить?\nПоднять зарплаты кассирам и продавцам\nИ меньше выносить мозги из-за показателей (сбп, ек, мп и тд...)\nПреимущества и льготы\nСвоевременная оплата труда\nНаличие кухни, места для обеда\nОплата больничного\nПрофессиональное обучение\nВсе 4\nПолезный отзыв\n 1\nСсылка на отзыв\nОтветить от лица компании",
    "review__header-title": "Кассир",
    "share-block__item": "...",
    "tags__item": "Работал меньше года",
    "tags__item (2)": "Москва, октябрь 2025",
    "dj-rating": "1,7",
    "review__title": "Что нравится?",
    "review__title (2)": "Что можно улучшить?",
    "review__title-privileges": "Преимущества и льготы",
    "tags__item (3)": "Своевременная оплата труда",
    "tags__item (4)": "Наличие кухни, места для обеда",
    "tags__item (5)": "Оплата больничного",
    "tags__item (6)": "Профессиональное обучение",
    "bt": "Все 4",
    "bt (2)": "Полезный отзыв\n 1",
    "review__useful": "Полезный отзыв",
    "bt href": "https://dreamjob.ru/employers/25596?review_id=4115198",
    "bt (3)": "Ссылка на отзыв",
    "bt href (2)": "https://dreamjob.ru/page/employers",
    "bt (4)": "Ответить от лица компании"
  },
  {
    "vacancies-banner__inner": "Вакансии в Спортмастер",
    "vacancies-banner__all href": "https://dreamjob.ru/employers/25596/vakansii",
    "vacancies-banner__all": "Все\n 1275",
    "d-md-block": "Все",
    "vacancies-banner__head": "Продавец-консультант (Ярославское ш. , 103,)",
    "vacancies-banner__сity": "Мытищи (Московская область)",
    "vacancies-banner__salary": "от 71 000 ₽",
    "job-vacancy__currency": "₽",
    "bt-master href": "https://dreamjob.ru/employers/25596/vakansii/125071658",
    "bt-master": "Посмотреть вакансию",
    "vacancies-banner__head (2)": "Продавец-консультант (ТЦ Торговый парк №1)",
    "vacancies-banner__сity (2)": "Тверь",
    "vacancies-banner__salary (2)": "от 50 500 ₽",
    "bt-master href (2)": "https://dreamjob.ru/employers/25596/vakansii/125071596",
    "vacancies-banner__head (3)": "Продавец в магазин Спортмастер (ТЦ РИО)",
    "vacancies-banner__сity (3)": "Ярославль",
    "vacancies-banner__salary (3)": "от 48 500 ₽",
    "bt-master href (3)": "https://dreamjob.ru/employers/25596/vakansii/126333794",
    "vacancies-banner__head (4)": "Сотрудник на склад (ТЦ \"Саларис\")",
    "vacancies-banner__сity (4)": "Москва",
    "vacancies-banner__salary (4)": "от 66 000 ₽",
    "bt-master href (4)": "https://dreamjob.ru/employers/25596/vakansii/125071488",
    "vacancies-banner__head (5)": "Продавец (ТЦ Меркурий)",
    "vacancies-banner__сity (5)": "Санкт-Петербург",
    "vacancies-banner__salary (5)": "от 65 500 ₽",
    "bt-master href (5)": "https://dreamjob.ru/employers/25596/vakansii/118903211"
  },
  {
    "review": "IT-рекрутер\n...\nРаботаю 1-2 года Москва, октябрь 2025\n1,3\nЧто нравится?\nУдаленный формат работы - это единственный плюс.\nЕсть своя библиотека книг, которые можно скачивать и читать.\nЧто можно улучшить?\nНизкий уровень дохода, отсутствие повышении и индексации зарплаты.\nНикакого развития и роста.\nОтсутствие лояльности со стороны руководства по отношению к сотрудникам.\nПостоянно придумывают какие-то странные задачи, которые никак не соотносятся с трудовыми обязанностями, прописанными в договоре.\nОбманывают по выплатам премий.\nПреимущества и льготы\nУдаленная работа\nПолезный отзыв\n 0\nСсылка на отзыв\nОтветить от лица компании",
    "review__header-title": "IT-рекрутер",
    "share-block__item": "...",
    "tags__item": "Работаю 1-2 года",
    "tags__item (2)": "Москва, октябрь 2025",
    "dj-rating": "1,3",
    "review__title": "Что нравится?",
    "review__title (2)": "Что можно улучшить?",
    "review__title-privileges": "Преимущества и льготы",
    "tags__item (3)": "Удаленная работа",
    "bt (2)": "Полезный отзыв\n 0",
    "review__useful": "Полезный отзыв",
    "bt href": "https://dreamjob.ru/employers/25596?review_id=4112176",
    "bt (3)": "Ссылка на отзыв",
    "bt href (2)": "https://dreamjob.ru/page/employers",
    "bt (4)": "Ответить от лица компании"
  },
  {
    "swiper-slide": "коллектив\n(31)"
  },
  {
    "review": "Продавец-консультант\n...\nРаботал меньше года Москва, октябрь 2025\n1,3\nЧто нравится?\n1)График действительно можно подгонять полностью свои желания,’ коллектив поможет\n2) скидки на одежду\nЧто можно улучшить?\n1)зарплата очень маленького для того количества задач. Руководство очень хамски ведет себя, ищет виноватого, но проблема в самом руководстве\n2) большое количество хамств от клиентов, вечно приходилось терпеть\nПреимущества и льготы\nСвоевременная оплата труда\nУдобное расположение работы\nНаличие кухни, места для обеда\nОплата больничного\nГибкий рабочий график\nПрофессиональное обучение\nВсе 6\nПолезный отзыв\n 0\nСсылка на отзыв\nОтветить от лица компании",
    "review__header-title": "Продавец-консультант",
    "share-block__item": "...",
    "tags__item": "Работал меньше года",
    "tags__item (2)": "Москва, октябрь 2025",
    "dj-rating": "1,3",
    "review__title": "Что нравится?",
    "review__title (2)": "Что можно улучшить?",
    "review__title-privileges": "Преимущества и льготы",
    "tags__item (3)": "Своевременная оплата труда",
    "tags__item (4)": "Удобное расположение работы",
    "tags__item (5)": "Наличие кухни, места для обеда",
    "tags__item (6)": "Оплата больничного",
    "bt": "Все 6",
    "bt (2)": "Полезный отзыв\n 0",
    "review__useful": "Полезный отзыв",
    "bt href": "https://dreamjob.ru/employers/25596?review_id=4091631",
    "bt (3)": "Ссылка на отзыв",
    "bt href (2)": "https://dreamjob.ru/page/employers",
    "bt (4)": "Ответить от лица компании"
  },
  {
    "vacancies-banner__inner": "Вакансии в Спортмастер",
    "vacancies-banner__all href": "https://dreamjob.ru/employers/25596/vakansii",
    "vacancies-banner__all": "Все\n 1275",
    "d-md-block": "Все",
    "vacancies-banner__head": "Продавец-консультант (Ярославское ш. , 103,)",
    "vacancies-banner__сity": "Мытищи (Московская область)",
    "vacancies-banner__salary": "от 71 000 ₽",
    "job-vacancy__currency": "₽",
    "bt-master href": "https://dreamjob.ru/employers/25596/vakansii/125071658",
    "bt-master": "Посмотреть вакансию",
    "vacancies-banner__head (2)": "Продавец-консультант (ТЦ Торговый парк №1)",
    "vacancies-banner__сity (2)": "Тверь",
    "vacancies-banner__salary (2)": "от 50 500 ₽",
    "bt-master href (2)": "https://dreamjob.ru/employers/25596/vakansii/125071596",
    "vacancies-banner__head (3)": "Продавец в магазин Спортмастер (ТЦ РИО)",
    "vacancies-banner__сity (3)": "Ярославль",
    "vacancies-banner__salary (3)": "от 48 500 ₽",
    "bt-master href (3)": "https://dreamjob.ru/employers/25596/vakansii/126333794",
    "vacancies-banner__head (4)": "Сотрудник на склад (ТЦ \"Саларис\")",
    "vacancies-banner__сity (4)": "Москва",
    "vacancies-banner__salary (4)": "от 66 000 ₽",
    "bt-master href (4)": "https://dreamjob.ru/employers/25596/vakansii/125071488",
    "vacancies-banner__head (5)": "Продавец (ТЦ Меркурий)",
    "vacancies-banner__сity (5)": "Санкт-Петербург",
    "vacancies-banner__salary (5)": "от 65 500 ₽",
    "bt-master href (5)": "https://dreamjob.ru/employers/25596/vakansii/118903211"
  },
  {
    "review": "Продавец-кассир\n...\nРаботал меньше года Москва, октябрь 2025\n1,5\nЧто нравится?\nГрафик и возможность подмениться, 2 обеда по 30 минут. Большой коллектив, обучение\nЧто можно улучшить?\nРуководство позволяет оскорблять на ненормативной лексике. Зарплата в 2 раза меньше чем указана.\nКоллектив не дружный, не хватка людей. За месяц ушло 10 человек.\nНа кассе тяжело с перерывами не всегда отпускают.\nПреимущества и льготы\nНаличие кухни, места для обеда\nОплата больничного\nГибкий рабочий график\nВсе 3\nПолезный отзыв\n 0\nСсылка на отзыв\nОтветить от лица компании",
    "review__header-title": "Продавец-кассир",
    "share-block__item": "...",
    "tags__item": "Работал меньше года",
    "tags__item (2)": "Москва, октябрь 2025",
    "dj-rating": "1,5",
    "review__title": "Что нравится?",
    "review__title (2)": "Что можно улучшить?",
    "review__title-privileges": "Преимущества и льготы",
    "tags__item (3)": "Наличие кухни, места для обеда",
    "tags__item (4)": "Оплата больничного",
    "tags__item (5)": "Гибкий рабочий график",
    "bt": "Все 3",
    "bt (2)": "Полезный отзыв\n 0",
    "review__useful": "Полезный отзыв",
    "bt href": "https://dreamjob.ru/employers/25596?review_id=4082728",
    "bt (3)": "Ссылка на отзыв",
    "bt href (2)": "https://dreamjob.ru/page/employers",
    "bt (4)": "Ответить от лица компании"
  },
  {
    "review": "Кассир\n...\nРаботал 1-2 года Москва, сентябрь 2025\n1,5\nЧто нравится?\nЗарплата без задержек.\nКоллектив,не считая некоторых личностей.\nЧто можно улучшить?\nСменить руководство.\nПовысить зп.\nДавать сотрудникам работать по своему графику и не просить выходить на работу в их выходные.\nПреимущества и льготы\nСвоевременная оплата труда\nПолезный отзыв\n 1\nСсылка на отзыв\nОтветить от лица компании",
    "review__header-title": "Кассир",
    "share-block__item": "...",
    "tags__item": "Работал 1-2 года",
    "tags__item (2)": "Москва, сентябрь 2025",
    "dj-rating": "1,5",
    "review__title": "Что нравится?",
    "review__title (2)": "Что можно улучшить?",
    "review__title-privileges": "Преимущества и льготы",
    "tags__item (3)": "Своевременная оплата труда",
    "bt (2)": "Полезный отзыв\n 1",
    "review__useful": "Полезный отзыв",
    "bt href": "https://dreamjob.ru/employers/25596?review_id=4066615",
    "bt (3)": "Ссылка на отзыв",
    "bt href (2)": "https://dreamjob.ru/page/employers",
    "bt (4)": "Ответить от лица компании"
  },
  {
    "review": "Продавец-кассир\n...\nРаботал меньше года Москва, сентябрь 2025\n1,8\nЧто нравится?\nВыплаты в указанный срок\nВроде как можно подняться до админа и директора , ну если позволят\nЧто можно улучшить?\nКрайне маленькая зп для Москвы\nОтношение руководства ужасно, полное не соблюдение субординации, графики устанавливают как хотят , вечная текучка\nНу как то так\nПреимущества и льготы\nСвоевременная оплата труда\nУдобное расположение работы\nНаличие кухни, места для обеда\nВсе 3\nПолезный отзыв\n 0\nСсылка на отзыв\nОтветить от лица компании",
    "review__header-title": "Продавец-кассир",
    "share-block__item": "...",
    "tags__item": "Работал меньше года",
    "tags__item (2)": "Москва, сентябрь 2025",
    "dj-rating": "1,8",
    "review__title": "Что нравится?",
    "review__title (2)": "Что можно улучшить?",
    "review__title-privileges": "Преимущества и льготы",
    "tags__item (3)": "Своевременная оплата труда",
    "tags__item (4)": "Удобное расположение работы",
    "tags__item (5)": "Наличие кухни, места для обеда",
    "bt": "Все 3",
    "bt (2)": "Полезный отзыв\n 0",
    "review__useful": "Полезный отзыв",
    "bt href": "https://dreamjob.ru/employers/25596?review_id=4047559",
    "bt (3)": "Ссылка на отзыв",
    "bt href (2)": "https://dreamjob.ru/page/employers",
    "bt (4)": "Ответить от лица компании"
  },
  {
    "review": "Продавец\n...\nРаботаю меньше года Москва, сентябрь 2025\n1,8\nЧто нравится?\nБлизость к дому, график строишь себе сам, на этом в целом все\nЧто можно улучшить?\nУровень зп, никогда не знаешь сколько получишь, задержки на работе, бывали дни когда уходили оттуда почти в 12 ночи, целый день на ногах, не знаю, кому подойдет такая работа, коллектив 50/50, в дальнейшем узнала, что смены не всегда проставляют, то есть работаешь за \"спасибо\" при такой маленькой зп смешно не проставлять отработки сотрудникам.\nПреимущества и льготы\nСвоевременная оплата труда\nНаличие кухни, места для обеда\nОплата больничного\nГибкий рабочий график\nВсе 4\nПолезный отзыв\n 2\nСсылка на отзыв\nОтветить от лица компании",
    "review__header-title": "Продавец",
    "share-block__item": "...",
    "tags__item": "Работаю меньше года",
    "tags__item (2)": "Москва, сентябрь 2025",
    "dj-rating": "1,8",
    "review__title": "Что нравится?",
    "review__title (2)": "Что можно улучшить?",
    "review__title-privileges": "Преимущества и льготы",
    "tags__item (3)": "Своевременная оплата труда",
    "tags__item (4)": "Наличие кухни, места для обеда",
    "tags__item (5)": "Оплата больничного",
    "tags__item (6)": "Гибкий рабочий график",
    "bt": "Все 4",
    "bt (2)": "Полезный отзыв\n 2",
    "review__useful": "Полезный отзыв",
    "bt href": "https://dreamjob.ru/employers/25596?review_id=4010042",
    "bt (3)": "Ссылка на отзыв",
    "bt href (2)": "https://dreamjob.ru/page/employers",
    "bt (4)": "Ответить от лица компании"
  },
  {
    "review": "Начальник отдела\n...\nРаботаю 5-10 лет Москва, сентябрь 2025\n1,8\nЧто нравится?\nРанее был хороший коллектив\nРуководство все испортило\nЗарплата ниже среднего\nОбязанностей выше крыши\nЧто можно улучшить?\nПовысить зарплату рядовым сотрудникам\nОбратить внимание на руководство, которое не умеет соблюдать субординацию с подчиненными. И в целом научить выполнять свою функцию\nПреимущества и льготы\nСвоевременная оплата труда\nОплата больничного\nПолезный отзыв\n 1\nСсылка на отзыв\nОтветить от лица компании",
    "review__header-title": "Начальник отдела",
    "share-block__item": "...",
    "tags__item": "Работаю 5-10 лет",
    "tags__item (2)": "Москва, сентябрь 2025",
    "dj-rating": "1,8",
    "review__title": "Что нравится?",
    "review__title (2)": "Что можно улучшить?",
    "review__title-privileges": "Преимущества и льготы",
    "tags__item (3)": "Своевременная оплата труда",
    "tags__item (4)": "Оплата больничного",
    "bt (2)": "Полезный отзыв\n 1",
    "review__useful": "Полезный отзыв",
    "bt href": "https://dreamjob.ru/employers/25596?review_id=3997524",
    "bt (3)": "Ссылка на отзыв",
    "bt href (2)": "https://dreamjob.ru/page/employers",
    "bt (4)": "Ответить от лица компании"
  },
  {
    "bt (2)": "Посмотреть все зарплаты (5 838)",
    "bt href": "https://dreamjob.ru/employers/25596/zarplata",
    "job-vacancy__currency": "₽",
    "swiper-slide": "Посмотреть\nеще зарплаты"
  },
  {
    "review": "Кассир\n...\nРаботал 1-2 года Москва, август 2025\n1,0\nЧто нравится?\nИмеется своя кухня. Это пожалуй все . Больше хорошего ни чего а этой компании нет\nЧто можно улучшить?\nЗарплату поднять ! Премию сделать своим работникам ! Не обманывать !\nПреимущества и льготы\nСвоевременная оплата труда\nНаличие кухни, места для обеда\nПолезный отзыв\n 0\nСсылка на отзыв\nОтветить от лица компании",
    "review__header-title": "Кассир",
    "share-block__item": "...",
    "tags__item": "Работал 1-2 года",
    "tags__item (2)": "Москва, август 2025",
    "dj-rating": "1,0",
    "review__title": "Что нравится?",
    "review__title (2)": "Что можно улучшить?",
    "review__title-privileges": "Преимущества и льготы",
    "tags__item (3)": "Своевременная оплата труда",
    "tags__item (4)": "Наличие кухни, места для обеда",
    "bt (2)": "Полезный отзыв\n 0",
    "review__useful": "Полезный отзыв",
    "bt href": "https://dreamjob.ru/employers/25596?review_id=3982305",
    "bt (3)": "Ссылка на отзыв",
    "bt href (2)": "https://dreamjob.ru/page/employers",
    "bt (4)": "Ответить от лица компании"
  },
  {
    "review": "Директор магазина\n...\nРаботал меньше года Москва, август 2025\n1,7\nЧто нравится?\nНе обманули с зарплатой.\nВ будущем неплохие плюшки для сотрудников\nЧто можно улучшить?\nНет адекватной адаптации\nМного разговоров, а на деле все процессы , в т.ч. подбор, занимает немало времени\nОтношение к сотрудникам со стороны руководства. Даже комнату отдыха, которая создана для сотрудников, занята вечными \"переговорами\" директора отделения и обсуждением с подружками-подчиненными других подчинённых.\nКроме того, руководитель совершенно некомпетентен, не может решить ни один вопрос.\nТакого бардака не видела давно.\nПреимущества и льготы\nСвоевременная оплата труда\nОплата больничного\nПолезный отзыв\n 0\nСсылка на отзыв\nОтветить от лица компании",
    "review__header-title": "Директор магазина",
    "share-block__item": "...",
    "tags__item": "Работал меньше года",
    "tags__item (2)": "Москва, август 2025",
    "dj-rating": "1,7",
    "review__title": "Что нравится?",
    "review__title (2)": "Что можно улучшить?",
    "review__title-privileges": "Преимущества и льготы",
    "tags__item (3)": "Своевременная оплата труда",
    "tags__item (4)": "Оплата больничного",
    "bt (2)": "Полезный отзыв\n 0",
    "review__useful": "Полезный отзыв",
    "bt href": "https://dreamjob.ru/employers/25596?review_id=3942093",
    "bt (3)": "Ссылка на отзыв",
    "bt href (2)": "https://dreamjob.ru/page/employers",
    "bt (4)": "Ответить от лица компании"
  }
]